Workbook
Name く５４: #REF!
Name く５４: 資金運用表!#REF!
Name く５４: 資金運用表!#REF!
Name く５４: #REF!
Name く５４: #REF!
Name 様式: #REF!

Sheet 財務諸表（入力）
A1: 企業名 : | O1: =TODAY() -> 46071
A2: 貸 借 対 照 表 （ Ｂ ／ Ｓ ）
O3: 単位：千円
A4: 項目 | E4: 2020年2月1日～ 2021年1月31日 | F4: 構成比 | G4: 2021年2月1日～2022年1月31日 | H4: 構成比 | I4: 前年比 増加率 | J4: 2022年2月1日～2023年1月31日 | K4: 構成比 | L4: 前年比 増加率 | M4: 増減額 | O4: 特徴／備考
E5: 前々期 | F5: ％ | G5: 前期 | H5: ％ | I5: ％ | J5: 今期 | K5: ％ | L5: ％ | M5: =G5 -> 前期 | N5: =J5 -> 今期
A6: 資産の部 | B6: 流動資産 | C6: 当座資産 | D6: 現金・預金 | F6: =IF(E6=0,"",E6/E$50) | H6: =IF(G6=0,"",G6/G$50) | I6: =IF(E6*G6=0,"",G6/E6) | K6: =IF(J6=0,"",J6/J$50) | L6: =IF(G6*J6=0,"",J6/G6) | M6: =G6-E6 -> 0 | N6: =J6-G6 -> 0
D7: （うち定期預金） | F7: =IF(E7=0,"",E7/E$50) | H7: =IF(G7=0,"",G7/G$50) | I7: =IF(E7*G7=0,"",G7/E7) | K7: =IF(J7=0,"",J7/J$50) | L7: =IF(G7*J7=0,"",J7/G7) | M7: =G7-E7 -> 0 | N7: =J7-G7 -> 0
D8: 受取手形 | F8: =IF(E8=0,"",E8/E$50) | H8: =IF(G8=0,"",G8/G$50) | I8: =IF(E8*G8=0,"",G8/E8) | K8: =IF(J8=0,"",J8/J$50) | L8: =IF(G8*J8=0,"",J8/G8) | M8: =G8-E8 -> 0 | N8: =J8-G8 -> 0
D9: 売掛金 | F9: =IF(E9=0,"",E9/E$50) | H9: =IF(G9=0,"",G9/G$50) | I9: =IF(E9*G9=0,"",G9/E9) | K9: =IF(J9=0,"",J9/J$50) | L9: =IF(G9*J9=0,"",J9/G9) | M9: =G9-E9 -> 0 | N9: =J9-G9 -> 0
F10: =IF(E10=0,"",E10/E$50) | H10: =IF(G10=0,"",G10/G$50) | I10: =IF(E10*G10=0,"",G10/E10) | K10: =IF(J10=0,"",J10/J$50) | L10: =IF(G10*J10=0,"",J10/G10) | M10: =G10-E10 -> 0 | N10: =J10-G10 -> 0
D11: 小計 | E11: =SUM(E6:E10)-E7 -> 0 | F11: =IF(E11=0,"",E11/E$50) | G11: =SUM(G6:G10)-G7 -> 0 | H11: =IF(G11=0,"",G11/G$50) | I11: =IF(E11*G11=0,"",G11/E11) | J11: =SUM(J6:J10)-J7 -> 0 | K11: =IF(J11=0,"",J11/J$50) | L11: =IF(G11*J11=0,"",J11/G11) | M11: =G11-E11 -> 0 | N11: =J11-G11 -> 0
C12: 棚卸資産 | D12: 製品・商品 | E12: 0 | F12: =IF(E12=0,"",E12/E$50) | H12: =IF(G12=0,"",G12/G$50) | I12: =IF(E12*G12=0,"",G12/E12) | K12: =IF(J12=0,"",J12/J$50) | L12: =IF(G12*J12=0,"",J12/G12) | M12: =G12-E12 -> 0 | N12: =J12-G12 -> 0
D13: 原材料 | E13: 0 | F13: =IF(E13=0,"",E13/E$50) | H13: =IF(G13=0,"",G13/G$50) | I13: =IF(E13*G13=0,"",G13/E13) | K13: =IF(J13=0,"",J13/J$50) | L13: =IF(G13*J13=0,"",J13/G13) | M13: =G13-E13 -> 0 | N13: =J13-G13 -> 0
D14: 仕掛品 | E14: 0 | F14: =IF(E14=0,"",E14/E$50) | H14: =IF(G14=0,"",G14/G$50) | I14: =IF(E14*G14=0,"",G14/E14) | K14: =IF(J14=0,"",J14/J$50) | L14: =IF(G14*J14=0,"",J14/G14) | M14: =G14-E14 -> 0 | N14: =J14-G14 -> 0
F15: =IF(E15=0,"",E15/E$50) | H15: =IF(G15=0,"",G15/G$50) | I15: =IF(E15*G15=0,"",G15/E15) | K15: =IF(J15=0,"",J15/J$50) | L15: =IF(G15*J15=0,"",J15/G15) | M15: =G15-E15 -> 0 | N15: =J15-G15 -> 0
D16: 小計 | E16: =SUM(E12:E15) -> 0 | F16: =IF(E16=0,"",E16/E$50) | G16: =SUM(G12:G15) -> 0 | H16: =IF(G16=0,"",G16/G$50) | I16: =IF(E16*G16=0,"",G16/E16) | J16: =SUM(J12:J15) -> 0 | K16: =IF(J16=0,"",J16/J$50) | L16: =IF(G16*J16=0,"",J16/G16) | M16: =G16-E16 -> 0 | N16: =J16-G16 -> 0
C17: その他流動資産 | F17: =IF(E17=0,"",E17/E$50) | H17: =IF(G17=0,"",G17/G$50) | I17: =IF(E17*G17=0,"",G17/E17) | K17: =IF(J17=0,"",J17/J$50) | L17: =IF(G17*J17=0,"",J17/G17) | M17: =G17-E17 -> 0 | N17: =J17-G17 -> 0
F18: =IF(E18=0,"",E18/E$50) | H18: =IF(G18=0,"",G18/G$50) | I18: =IF(E18*G18=0,"",G18/E18) | K18: =IF(J18=0,"",J18/J$50) | L18: =IF(G18*J18=0,"",J18/G18) | M18: =G18-E18 -> 0 | N18: =J18-G18 -> 0
F19: =IF(E19=0,"",E19/E$50) | H19: =IF(G19=0,"",G19/G$50) | I19: =IF(E19*G19=0,"",G19/E19) | K19: =IF(J19=0,"",J19/J$50) | L19: =IF(G19*J19=0,"",J19/G19) | M19: =G19-E19 -> 0 | N19: =J19-G19 -> 0
F20: =IF(E20=0,"",E20/E$50) | H20: =IF(G20=0,"",G20/G$50) | I20: =IF(E20*G20=0,"",G20/E20) | K20: =IF(J20=0,"",J20/J$50) | L20: =IF(G20*J20=0,"",J20/G20) | M20: =G20-E20 -> 0 | N20: =J20-G20 -> 0
F21: =IF(E21=0,"",E21/E$50) | H21: =IF(G21=0,"",G21/G$50) | I21: =IF(E21*G21=0,"",G21/E21) | K21: =IF(J21=0,"",J21/J$50) | L21: =IF(G21*J21=0,"",J21/G21) | M21: =G21-E21 -> 0 | N21: =J21-G21 -> 0
F22: =IF(E22=0,"",E22/E$50) | H22: =IF(G22=0,"",G22/G$50) | I22: =IF(E22*G22=0,"",G22/E22) | K22: =IF(J22=0,"",J22/J$50) | L22: =IF(G22*J22=0,"",J22/G22) | M22: =G22-E22 -> 0 | N22: =J22-G22 -> 0
F23: =IF(E23=0,"",E23/E$50) | H23: =IF(G23=0,"",G23/G$50) | I23: =IF(E23*G23=0,"",G23/E23) | K23: =IF(J23=0,"",J23/J$50) | L23: =IF(G23*J23=0,"",J23/G23) | M23: =G23-E23 -> 0 | N23: =J23-G23 -> 0
F24: =IF(E24=0,"",E24/E$50) | H24: =IF(G24=0,"",G24/G$50) | I24: =IF(E24*G24=0,"",G24/E24) | K24: =IF(J24=0,"",J24/J$50) | L24: =IF(G24*J24=0,"",J24/G24) | M24: =G24-E24 -> 0 | N24: =J24-G24 -> 0
D25: 貸倒引当金（▲） | E25: 0 | F25: =IF(E25=0,"",E25/E$50) | H25: =IF(G25=0,"",G25/G$50) | I25: =IF(E25*G25=0,"",G25/E25) | K25: =IF(J25=0,"",J25/J$50) | L25: =IF(G25*J25=0,"",J25/G25) | M25: =G25-E25 -> 0 | N25: =J25-G25 -> 0
F26: =IF(E26=0,"",E26/E$50) | H26: =IF(G26=0,"",G26/G$50) | I26: =IF(E26*G26=0,"",G26/E26) | K26: =IF(J26=0,"",J26/J$50) | L26: =IF(G26*J26=0,"",J26/G26) | M26: =G26-E26 -> 0 | N26: =J26-G26 -> 0
D27: 小計 | E27: =SUM(E17:E26) -> 0 | F27: =IF(E27=0,"",E27/E$50) | G27: =SUM(G17:G26) -> 0 | H27: =IF(G27=0,"",G27/G$50) | I27: =IF(E27*G27=0,"",G27/E27) | J27: =SUM(J17:J26) -> 0 | K27: =IF(J27=0,"",J27/J$50) | L27: =IF(G27*J27=0,"",J27/G27) | M27: =G27-E27 -> 0 | N27: =J27-G27 -> 0
B28: 流動資産合計 | E28: =E11+E16+E27 -> 0 | F28: =IF(E28=0,"",E28/E$50) | G28: =G11+G16+G27 -> 0 | H28: =IF(G28=0,"",G28/G$50) | I28: =IF(E28*G28=0,"",G28/E28) | J28: =J11+J16+J27 -> 0 | K28: =IF(J28=0,"",J28/J$50) | L28: =IF(G28*J28=0,"",J28/G28) | M28: =G28-E28 -> 0 | N28: =J28-G28 -> 0
B29: 固定資産 | C29: 有形固定資産 | D29: 建物付属設備 | F29: =IF(E29=0,"",E29/E$50) | H29: =IF(G29=0,"",G29/G$50) | I29: =IF(E29*G29=0,"",G29/E29) | K29: =IF(J29=0,"",J29/J$50) | L29: =IF(G29*J29=0,"",J29/G29) | M29: =G29-E29 -> 0 | N29: =J29-G29 -> 0
D30: 構築物 | F30: =IF(E30=0,"",E30/E$50) | H30: =IF(G30=0,"",G30/G$50) | I30: =IF(E30*G30=0,"",G30/E30) | K30: =IF(J30=0,"",J30/J$50) | L30: =IF(G30*J30=0,"",J30/G30) | M30: =G30-E30 -> 0 | N30: =J30-G30 -> 0
D31: 機械装置 | F31: =IF(E31=0,"",E31/E$50) | H31: =IF(G31=0,"",G31/G$50) | I31: =IF(E31*G31=0,"",G31/E31) | K31: =IF(J31=0,"",J31/J$50) | L31: =IF(G31*J31=0,"",J31/G31) | M31: =G31-E31 -> 0 | N31: =J31-G31 -> 0
D32: 車両運搬具 | F32: =IF(E32=0,"",E32/E$50) | H32: =IF(G32=0,"",G32/G$50) | I32: =IF(E32*G32=0,"",G32/E32) | K32: =IF(J32=0,"",J32/J$50) | L32: =IF(G32*J32=0,"",J32/G32) | M32: =G32-E32 -> 0 | N32: =J32-G32 -> 0
D33: 什器・備品 | F33: =IF(E33=0,"",E33/E$50) | H33: =IF(G33=0,"",G33/G$50) | I33: =IF(E33*G33=0,"",G33/E33) | K33: =IF(J33=0,"",J33/J$50) | L33: =IF(G33*J33=0,"",J33/G33) | M33: =G33-E33 -> 0 | N33: =J33-G33 -> 0
D34: 土地 | F34: =IF(E34=0,"",E34/E$50) | H34: =IF(G34=0,"",G34/G$50) | I34: =IF(E34*G34=0,"",G34/E34) | K34: =IF(J34=0,"",J34/J$50) | L34: =IF(G34*J34=0,"",J34/G34) | M34: =G34-E34 -> 0 | N34: =J34-G34 -> 0
D35: 建設仮勘定 | F35: =IF(E35=0,"",E35/E$50) | H35: =IF(G35=0,"",G35/G$50) | I35: =IF(E35*G35=0,"",G35/E35) | K35: =IF(J35=0,"",J35/J$50) | L35: =IF(G35*J35=0,"",J35/G35) | M35: =G35-E35 -> 0 | N35: =J35-G35 -> 0
D36: リース資産 | F36: =IF(E36=0,"",E36/E$50) | H36: =IF(G36=0,"",G36/G$50) | I36: =IF(E36*G36=0,"",G36/E36) | K36: =IF(J36=0,"",J36/J$50) | L36: =IF(G36*J36=0,"",J36/G36) | M36: =G36-E36 -> 0 | N36: =J36-G36 -> 0
D37: 小計 | E37: =SUM(E29:E36) -> 0 | F37: =IF(E37=0,"",E37/E$50) | G37: =SUM(G29:G36) -> 0 | H37: =IF(G37=0,"",G37/G$50) | I37: =IF(E37*G37=0,"",G37/E37) | J37: =SUM(J29:J36) -> 0 | K37: =IF(J37=0,"",J37/J$50) | L37: =IF(G37*J37=0,"",J37/G37) | M37: =G37-E37 -> 0 | N37: =J37-G37 -> 0
C38: 無形固定資産 | F38: =IF(E38=0,"",E38/E$50) | H38: =IF(G38=0,"",G38/G$50) | I38: =IF(E38*G38=0,"",G38/E38) | K38: =IF(J38=0,"",J38/J$50) | L38: =IF(G38*J38=0,"",J38/G38) | M38: =G38-E38 -> 0 | N38: =J38-G38 -> 0
C39: 投資等 | D39: 投資有価証券 | F39: =IF(E39=0,"",E39/E$50) | H39: =IF(G39=0,"",G39/G$50) | I39: =IF(E39*G39=0,"",G39/E39) | K39: =IF(J39=0,"",J39/J$50) | L39: =IF(G39*J39=0,"",J39/G39) | M39: =G39-E39 -> 0 | N39: =J39-G39 -> 0
D40: 出資金 | F40: =IF(E40=0,"",E40/E$50) | H40: =IF(G40=0,"",G40/G$50) | I40: =IF(E40*G40=0,"",G40/E40) | K40: =IF(J40=0,"",J40/J$50) | L40: =IF(G40*J40=0,"",J40/G40) | M40: =G40-E40 -> 0 | N40: =J40-G40 -> 0
D41: 保証金他 | F41: =IF(E41=0,"",E41/E$50) | H41: =IF(G41=0,"",G41/G$50) | I41: =IF(E41*G41=0,"",G41/E41) | K41: =IF(J41=0,"",J41/J$50) | L41: =IF(G41*J41=0,"",J41/G41) | M41: =G41-E41 -> 0 | N41: =J41-G41 -> 0
D42: 敷金 | F42: =IF(E42=0,"",E42/E$50) | H42: =IF(G42=0,"",G42/G$50) | I42: =IF(E42*G42=0,"",G42/E42) | K42: =IF(J42=0,"",J42/J$50) | L42: =IF(G42*J42=0,"",J42/G42) | M42: =G42-E42 -> 0 | N42: =J42-G42 -> 0
D43: 関係会社株式 | F43: =IF(E43=0,"",E43/E$50) | H43: =IF(G43=0,"",G43/G$50) | I43: =IF(E43*G43=0,"",G43/E43) | K43: =IF(J43=0,"",J43/J$50) | L43: =IF(G43*J43=0,"",J43/G43) | M43: =G43-E43 -> 0 | N43: =J43-G43 -> 0
D44: 保険積立金 | F44: =IF(E44=0,"",E44/E$50) | H44: =IF(G44=0,"",G44/G$50) | I44: =IF(E44*G44=0,"",G44/E44) | K44: =IF(J44=0,"",J44/J$50) | L44: =IF(G44*J44=0,"",J44/G44) | M44: =G44-E44 -> 0 | N44: =J44-G44 -> 0
D45: 貸倒引当金（▲） | F45: =IF(E45=0,"",E45/E$50) | H45: =IF(G45=0,"",G45/G$50) | I45: =IF(E45*G45=0,"",G45/E45) | K45: =IF(J45=0,"",J45/J$50) | L45: =IF(G45*J45=0,"",J45/G45) | M45: =G45-E45 -> 0 | N45: =J45-G45 -> 0
D46: 長期前払費用 | F46: =IF(E46=0,"",E46/E$50) | H46: =IF(G46=0,"",G46/G$50) | I46: =IF(E46*G46=0,"",G46/E46) | K46: =IF(J46=0,"",J46/J$50) | L46: =IF(G46*J46=0,"",J46/G46) | M46: =G46-E46 -> 0 | N46: =J46-G46 -> 0
D47: 小計 | E47: =SUM(E39:E46) -> 0 | F47: =IF(E47=0,"",E47/E$50) | G47: =SUM(G39:G46) -> 0 | H47: =IF(G47=0,"",G47/G$50) | I47: =IF(E47*G47=0,"",G47/E47) | J47: =SUM(J39:J46) -> 0 | K47: =IF(J47=0,"",J47/J$50) | L47: =IF(G47*J47=0,"",J47/G47) | M47: =G47-E47 -> 0 | N47: =J47-G47 -> 0
C48: 繰延資産 | F48: =IF(E48=0,"",E48/E$50) | H48: =IF(G48=0,"",G48/G$50) | I48: =IF(E48*G48=0,"",G48/E48) | K48: =IF(J48=0,"",J48/J$50) | L48: =IF(G48*J48=0,"",J48/G48) | M48: =G48-E48 -> 0 | N48: =J48-G48 -> 0
B49: 固定資産合計 | E49: =E37+E38+E47+E48 -> 0 | F49: =IF(E49=0,"",E49/E$50) | G49: =G37+G38+G47+G48 -> 0 | H49: =IF(G49=0,"",G49/G$50) | I49: =IF(E49*G49=0,"",G49/E49) | J49: =J37+J38+J47+J48 -> 0 | K49: =IF(J49=0,"",J49/J$50) | L49: =IF(G49*J49=0,"",J49/G49) | M49: =G49-E49 -> 0 | N49: =J49-G49 -> 0
A50: 資産合計 | E50: =E28+E49 -> 0 | F50: =F28+F49 -> #VALUE! | G50: =G28+G49 -> 0 | H50: =H28+H49 -> #VALUE! | I50: =IF(E50*G50=0,"",G50/E50) | J50: =J28+J49 -> 0 | K50: =K28+K49 -> #VALUE! | L50: =IF(G50*J50=0,"",J50/G50) | M50: =G50-E50 -> 0 | N50: =J50-G50 -> 0
A51: 負債の部 | B51: 流動負債 | D51: 支払手形 | E51: 0 | F51: =IF(E51=0,"",E51/E$80) | H51: =IF(G51=0,"",G51/G$80) | I51: =IF(E51*G51=0,"",G51/E51) | K51: =IF(J51=0,"",J51/J$80) | L51: =IF(G51*J51=0,"",J51/G51) | M51: =G51-E51 -> 0 | N51: =J51-G51 -> 0
D52: 買掛金 | F52: =IF(E52=0,"",E52/E$80) | H52: =IF(G52=0,"",G52/G$80) | I52: =IF(E52*G52=0,"",G52/E52) | K52: =IF(J52=0,"",J52/J$80) | L52: =IF(G52*J52=0,"",J52/G52) | M52: =G52-E52 -> 0 | N52: =J52-G52 -> 0
D53: 短期借入金 | F53: =IF(E53=0,"",E53/E$80) | H53: =IF(G53=0,"",G53/G$80) | I53: =IF(E53*G53=0,"",G53/E53) | K53: =IF(J53=0,"",J53/J$80) | L53: =IF(G53*J53=0,"",J53/G53) | M53: =G53-E53 -> 0 | N53: =J53-G53 -> 0
D54: 未払金 | F54: =IF(E54=0,"",E54/E$80) | H54: =IF(G54=0,"",G54/G$80) | I54: =IF(E54*G54=0,"",G54/E54) | K54: =IF(J54=0,"",J54/J$80) | L54: =IF(G54*J54=0,"",J54/G54) | M54: =G54-E54 -> 0 | N54: =J54-G54 -> 0
D55: 未払費用 | F55: =IF(E55=0,"",E55/E$80) | H55: =IF(G55=0,"",G55/G$80) | I55: =IF(E55*G55=0,"",G55/E55) | K55: =IF(J55=0,"",J55/J$80) | L55: =IF(G55*J55=0,"",J55/G55) | M55: =G55-E55 -> 0 | N55: =J55-G55 -> 0
D56: 前受金 | F56: =IF(E56=0,"",E56/E$80) | H56: =IF(G56=0,"",G56/G$80) | I56: =IF(E56*G56=0,"",G56/E56) | K56: =IF(J56=0,"",J56/J$80) | L56: =IF(G56*J56=0,"",J56/G56) | M56: =G56-E56 -> 0 | N56: =J56-G56 -> 0
D57: 預り金 | F57: =IF(E57=0,"",E57/E$80) | H57: =IF(G57=0,"",G57/G$80) | I57: =IF(E57*G57=0,"",G57/E57) | K57: =IF(J57=0,"",J57/J$80) | L57: =IF(G57*J57=0,"",J57/G57) | M57: =G57-E57 -> 0 | N57: =J57-G57 -> 0
D58: 未払法人税等 | F58: =IF(E58=0,"",E58/E$80) | H58: =IF(G58=0,"",G58/G$80) | I58: =IF(E58*G58=0,"",G58/E58) | K58: =IF(J58=0,"",J58/J$80) | L58: =IF(G58*J58=0,"",J58/G58) | M58: =G58-E58 -> 0 | N58: =J58-G58 -> 0
D59: 未払消費税 | F59: =IF(E59=0,"",E59/E$80) | H59: =IF(G59=0,"",G59/G$80) | I59: =IF(E59*G59=0,"",G59/E59) | K59: =IF(J59=0,"",J59/J$80) | L59: =IF(G59*J59=0,"",J59/G59) | M59: =G59-E59 -> 0 | N59: =J59-G59 -> 0
D60: 預り保証金他 | F60: =IF(E60=0,"",E60/E$80) | H60: =IF(G60=0,"",G60/G$80) | I60: =IF(E60*G60=0,"",G60/E60) | K60: =IF(J60=0,"",J60/J$80) | L60: =IF(G60*J60=0,"",J60/G60) | M60: =G60-E60 -> 0 | N60: =J60-G60 -> 0
B61: 流動負債合計 | E61: =SUM(E51:E60) -> 0 | F61: =IF(E61=0,"",E61/E$80) | G61: =SUM(G51:G60) -> 0 | H61: =IF(G61=0,"",G61/G$80) | I61: =IF(E61*G61=0,"",G61/E61) | J61: =SUM(J51:J60) -> 0 | K61: =IF(J61=0,"",J61/J$80) | L61: =IF(G61*J61=0,"",J61/G61) | M61: =G61-E61 -> 0 | N61: =J61-G61 -> 0
B62: 固定負債 | D62: 長期借入金 | F62: =IF(E62=0,"",E62/E$80) | H62: =IF(G62=0,"",G62/G$80) | I62: =IF(E62*G62=0,"",G62/E62) | K62: =IF(J62=0,"",J62/J$80) | L62: =IF(G62*J62=0,"",J62/G62) | M62: =G62-E62 -> 0 | N62: =J62-G62 -> 0
D63: 社債 | F63: =IF(E63=0,"",E63/E$80) | H63: =IF(G63=0,"",G63/G$80) | I63: =IF(E63*G63=0,"",G63/E63) | K63: =IF(J63=0,"",J63/J$80) | L63: =IF(G63*J63=0,"",J63/G63) | M63: =G63-E63 -> 0 | N63: =J63-G63 -> 0
D64: 設備支払手形 | F64: =IF(E64=0,"",E64/E$80) | H64: =IF(G64=0,"",G64/G$80) | I64: =IF(E64*G64=0,"",G64/E64) | K64: =IF(J64=0,"",J64/J$80) | L64: =IF(G64*J64=0,"",J64/G64) | M64: =G64-E64 -> 0 | N64: =J64-G64 -> 0
D65: リース債務 | F65: =IF(E65=0,"",E65/E$80) | H65: =IF(G65=0,"",G65/G$80) | I65: =IF(E65*G65=0,"",G65/E65) | K65: =IF(J65=0,"",J65/J$80) | L65: =IF(G65*J65=0,"",J65/G65) | M65: =G65-E65 -> 0 | N65: =J65-G65 -> 0
F66: =IF(E66=0,"",E66/E$80) | H66: =IF(G66=0,"",G66/G$80) | I66: =IF(E66*G66=0,"",G66/E66) | K66: =IF(J66=0,"",J66/J$80) | L66: =IF(G66*J66=0,"",J66/G66) | M66: =G66-E66 -> 0 | N66: =J66-G66 -> 0
F67: =IF(E67=0,"",E67/E$80) | H67: =IF(G67=0,"",G67/G$80) | I67: =IF(E67*G67=0,"",G67/E67) | K67: =IF(J67=0,"",J67/J$80) | L67: =IF(G67*J67=0,"",J67/G67) | M67: =G67-E67 -> 0 | N67: =J67-G67 -> 0
F68: =IF(E68=0,"",E68/E$80) | H68: =IF(G68=0,"",G68/G$80) | I68: =IF(E68*G68=0,"",G68/E68) | K68: =IF(J68=0,"",J68/J$80) | L68: =IF(G68*J68=0,"",J68/G68) | M68: =G68-E68 -> 0 | N68: =J68-G68 -> 0
B69: 固定負債合計 | E69: =SUM(E62:E68) -> 0 | F69: =IF(E69=0,"",E69/E$80) | G69: =SUM(G62:G68) -> 0 | H69: =IF(G69=0,"",G69/G$80) | I69: =IF(E69*G69=0,"",G69/E69) | J69: =SUM(J62:J68) -> 0 | K69: =IF(J69=0,"",J69/J$80) | L69: =IF(G69*J69=0,"",J69/G69) | M69: =G69-E69 -> 0 | N69: =J69-G69 -> 0
A70: 負債合計 | E70: =E61+E69 -> 0 | F70: =IF(E70=0,"",E70/E$80) | G70: =G61+G69 -> 0 | H70: =IF(G70=0,"",G70/G$80) | I70: =IF(E70*G70=0,"",G70/E70) | J70: =J61+J69 -> 0 | K70: =IF(J70=0,"",J70/J$80) | L70: =IF(G70*J70=0,"",J70/G70) | M70: =G70-E70 -> 0 | N70: =J70-G70 -> 0
A71: 純資産の部 | B71: 資本等 | D71: 資本金 | F71: =IF(E71=0,"",E71/E$80) | H71: =IF(G71=0,"",G71/G$80) | I71: =IF(E71*G71=0,"",G71/E71) | K71: =IF(J71=0,"",J71/J$80) | L71: =IF(G71*J71=0,"",J71/G71) | M71: =G71-E71 -> 0 | N71: =J71-G71 -> 0
D72: 資本剰余金 | F72: =IF(E72=0,"",E72/E$80) | H72: =IF(G72=0,"",G72/G$80) | I72: =IF(E72*G72=0,"",G72/E72) | K72: =IF(J72=0,"",J72/J$80) | L72: =IF(G72*J72=0,"",J72/G72) | M72: =G72-E72 -> 0 | N72: =J72-G72 -> 0
D73: 利益剰余金 | F73: =IF(E73=0,"",E73/E$80) | H73: =IF(G73=0,"",G73/G$80) | I73: =IF(E73*G73=0,"",G73/E73) | K73: =IF(J73=0,"",J73/J$80) | L73: =IF(G73*J73=0,"",J73/G73) | M73: =G73-E73 -> 0 | N73: =J73-G73 -> 0
D74: うち準備金、積立金 | F74: =IF(E74=0,"",E74/E$80) | H74: =IF(G74=0,"",G74/G$80) | I74: =IF(E74*G74=0,"",G74/E74) | K74: =IF(J74=0,"",J74/J$80) | L74: =IF(G74*J74=0,"",J74/G74) | M74: =G74-E74 -> 0 | N74: =J74-G74 -> 0
D75: うち繰越利益剰余金 | F75: =IF(E75=0,"",E75/E$80) | H75: =IF(G75=0,"",G75/G$80) | I75: =IF(E75*G75=0,"",G75/E75) | K75: =IF(J75=0,"",J75/J$80) | L75: =IF(G75*J75=0,"",J75/G75) | M75: =G75-E75 -> 0 | N75: =J75-G75 -> 0
D76: 小計 | E76: =SUM(E71:E73) -> 0 | F76: =IF(E76=0,"",E76/E$80) | G76: =SUM(G71:G73) -> 0 | H76: =IF(G76=0,"",G76/G$80) | I76: =IF(E76*G76=0,"",G76/E76) | J76: =SUM(J71:J73) -> 0 | K76: =IF(J76=0,"",J76/J$80) | L76: =IF(G76*J76=0,"",J76/G76) | M76: =G76-E76 -> 0 | N76: =J76-G76 -> 0
B77: 自己株式（▲） | F77: =IF(E77=0,"",E77/E$80) | H77: =IF(G77=0,"",G77/G$80) | I77: =IF(E77*G77=0,"",G77/E77) | K77: =IF(J77=0,"",J77/J$80) | L77: =IF(G77*J77=0,"",J77/G77) | M77: =G77-E77 -> 0 | N77: =J77-G77 -> 0
F78: =IF(E78=0,"",E78/E$80) | H78: =IF(G78=0,"",G78/G$80) | I78: =IF(E78*G78=0,"",G78/E78) | K78: =IF(J78=0,"",J78/J$80) | L78: =IF(G78*J78=0,"",J78/G78) | M78: =G78-E78 -> 0 | N78: =J78-G78 -> 0
B79: 純資産合計 | E79: =E76+E77+E78 -> 0 | F79: =IF(E79=0,"",E79/E$80) | G79: =G76+G77+G78 -> 0 | H79: =IF(G79=0,"",G79/G$80) | I79: =IF(E79*G79=0,"",G79/E79) | J79: =J76+J77+J78 -> 0 | K79: =IF(J79=0,"",J79/J$80) | L79: =IF(G79*J79=0,"",J79/G79) | M79: =G79-E79 -> 0 | N79: =J79-G79 -> 0
A80: 純資産・負債合計 | E80: =E70+E79 -> 0 | F80: =F70+F79 -> #VALUE! | G80: =G70+G79 -> 0 | H80: =H70+H79 -> #VALUE! | I80: =IF(E80*G80=0,"",G80/E80) | J80: =J70+J79 -> 0 | K80: =K70+K79 -> #VALUE! | L80: =IF(G80*J80=0,"",J80/G80) | M80: =G80-E80 -> 0 | N80: =J80-G80 -> 0
A81: 借方／貸方照合（0でＯＫ） | E81: =E50-E80 -> 0 | G81: =G50-G80 -> 0 | J81: =J50-J80 -> 0
B83: 受取手形割引高 | F83: =IF(E83=0,"",E83/E$80) | H83: =IF(G83=0,"",G83/G$80) | I83: =IF(E83*G83=0,"",G83/E83) | K83: =IF(J83=0,"",J83/J$80) | L83: =IF(G83*J83=0,"",J83/G83) | M83: =G83-E83 -> 0 | N83: =J83-G83 -> 0
B84: 受取手形裏書譲渡高 | F84: =IF(E84=0,"",E84/E$80) | H84: =IF(G84=0,"",G84/G$80) | I84: =IF(E84*G84=0,"",G84/E84) | K84: =IF(J84=0,"",J84/J$80) | L84: =IF(G84*J84=0,"",J84/G84) | M84: =G84-E84 -> 0 | N84: =J84-G84 -> 0
A86: 【集計項目】
A87: 経営資本額 （総資本-建設仮勘定-投資等-繰延資産） | E87: =E50-E35-E39 -> 0 | F87: =IF(E87=0,"",E87/E$80) | G87: =G50-G35-G39 -> 0 | H87: =IF(G87=0,"",G87/G$80) | I87: =IF(E87*G87=0,"",G87/E87) | J87: =J50-J35-J39 -> 0 | K87: =IF(J87=0,"",J87/J$80) | L87: =IF(G87*J87=0,"",J87/G87) | M87: =G87-E87 -> 0 | N87: =J87-G87 -> 0
A88: 経常運転資金額 （売上債権＋棚卸資産－買入債務） | E88: =(E9+E8+E16+E83+E84)-(E51+E52+E84) -> 0 | F88: =IF(E88=0,"",E88/E$80) | G88: =(G9+G8+G16+G83+G84)-(G51+G52+G84) -> 0 | H88: =IF(G88=0,"",G88/G$80) | I88: =IF(E88*G88=0,"",G88/E88) | J88: =(J9+J8+J16+J83+J84)-(J51+J52+J84) -> 0 | K88: =IF(J88=0,"",J88/J$80) | L88: =IF(G88*J88=0,"",J88/G88) | M88: =G88-E88 -> 0 | N88: =J88-G88 -> 0
A89: =A1 -> 企業名 : | D89: =D1 -> 0 | F89: 製 造 原 価 報 告 書 （ C ／ R ）
O90: 単位：千円
A91: 項目 | E91: =E4 -> 2020年2月1日～ 2021年1月31日 | F91: 売上比 | G91: =G4 -> 2021年2月1日～2022年1月31日 | H91: 売上比 | I91: 前年比 増加率 | J91: =J4 -> 2022年2月1日～2023年1月31日 | K91: 売上比 | L91: 前年比 増加率 | M91: 増減額 | O91: 特徴／備考
E92: =E5 -> 前々期 | F92: ％ | G92: =G5 -> 前期 | H92: ％ | I92: ％ | J92: =J5 -> 今期 | K92: ％ | L92: ％ | M92: =G92 -> 前期 | N92: =J92 -> 今期
A93: 製造原価報告書 | B93: 材料費 | C93: 材料棚卸高 | F93: =IF(E93=0,"",E93/E$129) | H93: =IF(G93=0,"",G93/G$129) | I93: =IF(E93*G93=0,"",G93/E93) | K93: =IF(J93=0,"",J93/J$129) | L93: =IF(G93*J93=0,"",J93/G93) | M93: =G93-E93 -> 0 | N93: =J93-G93 -> 0
C94: 当期材料仕入高 | F94: =IF(E94=0,"",E94/E$129) | H94: =IF(G94=0,"",G94/G$129) | I94: =IF(E94*G94=0,"",G94/E94) | K94: =IF(J94=0,"",J94/J$129) | L94: =IF(G94*J94=0,"",J94/G94) | M94: =G94-E94 -> 0 | N94: =J94-G94 -> 0
C95: 期末材料棚卸高 | F95: =IF(E95=0,"",E95/E$129) | H95: =IF(G95=0,"",G95/G$129) | I95: =IF(E95*G95=0,"",G95/E95) | K95: =IF(J95=0,"",J95/J$129) | L95: =IF(G95*J95=0,"",J95/G95) | M95: =G95-E95 -> 0 | N95: =J95-G95 -> 0
B96: 当期材料費（Ｖ） | E96: =E93+E94-E95 -> 0 | F96: =IF(E96=0,"",E96/E$129) | G96: =G93+G94-G95 -> 0 | H96: =IF(G96=0,"",G96/G$129) | I96: =IF(E96*G96=0,"",G96/E96) | J96: =J93+J94-J95 -> 0 | K96: =IF(J96=0,"",J96/J$129) | L96: =IF(G96*J96=0,"",J96/G96) | M96: =G96-E96 -> 0 | N96: =J96-G96 -> 0
B97: 労務費 | C97: F | D97: 賃金 | F97: =IF(E97=0,"",E97/E$129) | H97: =IF(G97=0,"",G97/G$129) | I97: =IF(E97*G97=0,"",G97/E97) | K97: =IF(J97=0,"",J97/J$129) | L97: =IF(G97*J97=0,"",J97/G97) | M97: =G97-E97 -> 0 | N97: =J97-G97 -> 0
C98: F | D98: 賞与 | F98: =IF(E98=0,"",E98/E$129) | H98: =IF(G98=0,"",G98/G$129) | I98: =IF(E98*G98=0,"",G98/E98) | K98: =IF(J98=0,"",J98/J$129) | L98: =IF(G98*J98=0,"",J98/G98) | M98: =G98-E98 -> 0 | N98: =J98-G98 -> 0
C99: F | D99: 退職金 | F99: =IF(E99=0,"",E99/E$129) | H99: =IF(G99=0,"",G99/G$129) | I99: =IF(E99*G99=0,"",G99/E99) | K99: =IF(J99=0,"",J99/J$129) | L99: =IF(G99*J99=0,"",J99/G99) | M99: =G99-E99 -> 0 | N99: =J99-G99 -> 0
C100: F | D100: 厚生費 | F100: =IF(E100=0,"",E100/E$129) | H100: =IF(G100=0,"",G100/G$129) | I100: =IF(E100*G100=0,"",G100/E100) | K100: =IF(J100=0,"",J100/J$129) | L100: =IF(G100*J100=0,"",J100/G100) | M100: =G100-E100 -> 0 | N100: =J100-G100 -> 0
B101: 当期労務費 | E101: =SUM(E97:E100) -> 0 | F101: =IF(E101=0,"",E101/E$129) | G101: =SUM(G97:G100) -> 0 | H101: =IF(G101=0,"",G101/G$129) | I101: =IF(E101*G101=0,"",G101/E101) | J101: =SUM(J97:J100) -> 0 | K101: =IF(J101=0,"",J101/J$129) | L101: =IF(G101*J101=0,"",J101/G101) | M101: =G101-E101 -> 0 | N101: =J101-G101 -> 0
B102: 製造経費 | C102: F | D102: 減価償却費 | F102: =IF(E102=0,"",E102/E$129) | H102: =IF(G102=0,"",G102/G$129) | I102: =IF(E102*G102=0,"",G102/E102) | K102: =IF(J102=0,"",J102/J$129) | L102: =IF(G102*J102=0,"",J102/G102) | M102: =G102-E102 -> 0 | N102: =J102-G102 -> 0
...

Sheet 経営分析シート
A1: ='財務諸表（入力）'!D1 -> 0
A3: １．損益分岐点分析
G4: 単位：千円 | J4: 増減率
E5: ='財務諸表（入力）'!$E$5 -> 前々期 | F5: ='財務諸表（入力）'!$G$5 -> 前期 | G5: ='財務諸表（入力）'!$J$5 -> 今期 | H5: 算式 | J5: =F5 -> 前期 | K5: =G5 -> 今期 | AC5: 変動費の内訳
A6: 売上高 | E6: ='財務諸表（入力）'!E129 -> 0 | F6: ='財務諸表（入力）'!G129 -> 0 | G6: ='財務諸表（入力）'!J129 -> 0 | J6: =IF(F6="","",F6/E6) -> #DIV/0! | K6: =IF(G6="","",G6/F6) -> #DIV/0! | AD6: ='財務諸表（入力）'!$E$5 -> 前々期 | AE6: ='財務諸表（入力）'!$G$5 -> 前期 | AF6: ='財務諸表（入力）'!$J$5 -> 今期
A7: 変動費 | E7: ='財務諸表（入力）'!E96+SUMIF('財務諸表（入力）'!$C$97:$C$116,"V",'財務諸表（入力）'!$E$97:$E$116)+'財務諸表（入力）'!E122+'財務諸表（入力）'!E131+'財務諸表（入力）'!E135+SUMIF('財務諸表（入力）'!$C$138:$C$155,"V",'財務諸表（入力）'!$E$138:$E$155)-'財務諸表（入力）'!E121-'財務諸表（入力）'!E133 -> 0 | F7: ='財務諸表（入力）'!G96+SUMIF('財務諸表（入力）'!$C$97:$C$116,"V",'財務諸表（入力）'!$G$97:$G$116)+'財務諸表（入力）'!G122+'財務諸表（入力）'!G131+'財務諸表（入力）'!G135+SUMIF('財務諸表（入力）'!$C$138:$C$155,"V",'財務諸表（入力）'!$G$138:$G$155)-'財務諸表（入力）'!$G121-'財務諸表（入力）'!G133 -> 0 | G7: ='財務諸表（入力）'!J96+SUMIF('財務諸表（入力）'!$C$97:$C$116,"V",'財務諸表（入力）'!$J$97:$J$116)+'財務諸表（入力）'!J122+'財務諸表（入力）'!J131+'財務諸表（入力）'!J135+SUMIF('財務諸表（入力）'!$C$138:$C$155,"V",'財務諸表（入力）'!$J$138:$J$155)-'財務諸表（入力）'!$J121-'財務諸表（入力）'!J133 -> 0 | J7: =IF(F7="","",F7/E7) -> #DIV/0! | K7: =IF(G7="","",G7/F7) -> #DIV/0! | AC7: 材料費 | AD7: ='財務諸表（入力）'!E96 -> 0 | AE7: ='財務諸表（入力）'!G96 -> 0 | AF7: ='財務諸表（入力）'!J96 -> 0
A8: 限界利益 | E8: =E6-E7 -> 0 | F8: =F6-F7 -> 0 | G8: =G6-G7 -> 0 | H8: 売上高-変動費 | J8: =IF(F8="","",F8/E8) -> #DIV/0! | K8: =IF(G8="","",G8/F8) -> #DIV/0! | AC8: 労務費 | AD8: =SUMIF('財務諸表（入力）'!$C$97:$C$100,"V",'財務諸表（入力）'!$E$97:$E$100) -> 0 | AE8: =SUMIF('財務諸表（入力）'!$C$97:$C$100,"V",'財務諸表（入力）'!$G$97:$G$100) -> 0 | AF8: =SUMIF('財務諸表（入力）'!$C$97:$C$100,"V",'財務諸表（入力）'!$J$97:$J$100) -> 0
A9: 限界利益率 | E9: =IF(E8*E6=0,"",E8/E6) | F9: =IF(F8*F6=0,"",F8/F6) | G9: =IF(G8*G6=0,"",G8/G6) | H9: 限界利益÷売上高（％） | J9: =IF(F9="","",F9/E9) | K9: =IF(G9="","",G9/F9) | AC9: 製造原価 | AD9: =SUMIF('財務諸表（入力）'!$C$102:$C$116,"V",'財務諸表（入力）'!$E$102:$E$116) -> 0 | AE9: =SUMIF('財務諸表（入力）'!$C$102:$C$116,"V",'財務諸表（入力）'!$G$102:$G$116) -> 0 | AF9: =SUMIF('財務諸表（入力）'!$C$102:$C$116,"V",'財務諸表（入力）'!$J$102:$J$116) -> 0
A10: 固定費 | E10: =SUMIF('財務諸表（入力）'!$C$97:$C$116,"F",'財務諸表（入力）'!$E$97:$E$116)+SUMIF('財務諸表（入力）'!$C$138:$C$155,"F",'財務諸表（入力）'!$E$138:$E$155)+'財務諸表（入力）'!E165-'財務諸表（入力）'!E162 -> 0 | F10: =SUMIF('財務諸表（入力）'!$C$97:$C$116,"F",'財務諸表（入力）'!$G$97:$G$116)+SUMIF('財務諸表（入力）'!$C$138:$C$155,"F",'財務諸表（入力）'!$G$138:$G$155)+'財務諸表（入力）'!G165-'財務諸表（入力）'!G162 -> 0 | G10: =SUMIF('財務諸表（入力）'!$C$97:$C$116,"F",'財務諸表（入力）'!$J$97:$J$116)+SUMIF('財務諸表（入力）'!$C$138:$C$155,"F",'財務諸表（入力）'!$J$138:$J$155)+'財務諸表（入力）'!J165-'財務諸表（入力）'!J162 -> 0 | J10: =IF(F10="","",F10/E10) -> #DIV/0! | K10: =IF(G10="","",G10/F10) -> #DIV/0! | AC10: 販売管理費 | AD10: =SUMIF('財務諸表（入力）'!$C$138:$C$155,"V",'財務諸表（入力）'!$E$138:$E$155) -> 0 | AE10: =SUMIF('財務諸表（入力）'!$C$138:$C$155,"V",'財務諸表（入力）'!$G$138:$G$155) -> 0 | AF10: =SUMIF('財務諸表（入力）'!$C$138:$C$155,"V",'財務諸表（入力）'!$J$138:$J$155) -> 0
A11: 経常利益 | E11: =E8-E10 -> 0 | F11: =F8-F10 -> 0 | G11: =G8-G10 -> 0 | H11: 限界利益ー固定費 | J11: =IF(F11="","",F11/E11) -> #DIV/0! | K11: =IF(G11="","",G11/F11) -> #DIV/0! | AC11: 期首－期末仕掛品 | AD11: ='財務諸表（入力）'!E122 -> 0 | AE11: ='財務諸表（入力）'!G122 -> 0 | AF11: ='財務諸表（入力）'!J122 -> 0
A12: 損益分岐点売上高 | E12: =IF(E10*E9=0,"",E10/E9) -> #VALUE! | F12: =IF(F10*F9=0,"",F10/F9) -> #VALUE! | G12: =IF(G10*G9=0,"",G10/G9) -> #VALUE! | H12: 固定費÷限界利益率 | J12: =IF(F12="","",F12/E12) -> #VALUE! | K12: =IF(G12="","",G12/F12) -> #VALUE! | AC12: 商品仕入高 | AD12: ='財務諸表（入力）'!E131 -> 0 | AE12: ='財務諸表（入力）'!G131 -> 0 | AF12: ='財務諸表（入力）'!J131 -> 0
A13: 損益分岐点比率 | E13: =IF(E12*E6=0,"",E12/E6) -> #VALUE! | F13: =IF(F12*F6=0,"",F12/F6) -> #VALUE! | G13: =IF(G12*G6=0,"",G12/G6) -> #VALUE! | H13: 損益分岐点売上高÷売上高 | J13: =IF(F13="","",F13/E13) -> #VALUE! | K13: =IF(G13="","",G13/F13) -> #VALUE! | AC13: 期首－期末製品棚卸高 | AD13: ='財務諸表（入力）'!E135 -> 0 | AE13: ='財務諸表（入力）'!G135 -> 0 | AF13: ='財務諸表（入力）'!J135 -> 0
A14: 安全余裕率 | E14: =IF(E13=0,"",1-E13) -> #VALUE! | F14: =IF(F13=0,"",1-F13) -> #VALUE! | G14: =IF(G13=0,"",1-G13) -> #VALUE! | H14: 100%-損益分岐点比率 | J14: =IF(F14="","",F14/E14) -> #VALUE! | K14: =IF(G14="","",G14/F14) -> #VALUE! | AC14: 他勘定振替高 | AD14: ='財務諸表（入力）'!E121 -> 0 | AE14: ='財務諸表（入力）'!G121 -> 0 | AF14: ='財務諸表（入力）'!J121 -> 0
A15: 変動費比率 | E15: =IF(E7*E6=0,"",E7/E6) | F15: =IF(F7*F6=0,"",F7/F6) | G15: =IF(G7*G6=0,"",G7/G6) | AC15: 合計 | AD15: =SUM(AD7:AD13)-AD14 -> 0 | AE15: =SUM(AE7:AE13)-AE14 -> 0 | AF15: =SUM(AF7:AF13)-AF14 -> 0
A16: 固定費比率 | E16: =IF(E10*E6=0,"",E10/E6) | F16: =IF(F10*F6=0,"",F10/F6) | G16: =IF(G10*G6=0,"",G10/G6)
D17: 照合（０でOK) | E17: ='財務諸表（入力）'!E166-E11 -> 0 | F17: ='財務諸表（入力）'!G166-F11 -> 0 | G17: ='財務諸表（入力）'!J166-G11 -> 0
A18: ◆変動費（Ｖ）・固定費（Ｆ）の分類は製造原価報告書・損益計算書を参照
A22: ２．バランスシート分析（貸借対照表の構成比率）
A24: （１）ＢＳの資産・負債・純資産構成
E25: ='財務諸表（入力）'!$E$5 -> 前々期 | F25: ='財務諸表（入力）'!$G$5 -> 前期 | G25: ='財務諸表（入力）'!$J$5 -> 今期
A26: 流動資産 | E26: ='財務諸表（入力）'!F28 | F26: =IF('財務諸表（入力）'!H28=0,"",'財務諸表（入力）'!H28) | G26: =IF('財務諸表（入力）'!K28=0,"",'財務諸表（入力）'!K28)
A27: 固定資産 | E27: ='財務諸表（入力）'!F49 | F27: =IF('財務諸表（入力）'!H49=0,"",'財務諸表（入力）'!H49) | G27: =IF('財務諸表（入力）'!K49=0,"",'財務諸表（入力）'!K49)
A28: 流動負債 | E28: ='財務諸表（入力）'!F61 | F28: =IF('財務諸表（入力）'!H61=0,"",'財務諸表（入力）'!H61) | G28: =IF('財務諸表（入力）'!K61=0,"",'財務諸表（入力）'!K61)
A29: 固定負債 | E29: ='財務諸表（入力）'!F69 | F29: =IF('財務諸表（入力）'!H69=0,"",'財務諸表（入力）'!H69) | G29: =IF('財務諸表（入力）'!K69=0,"",'財務諸表（入力）'!K69)
A30: 純資産 | E30: ='財務諸表（入力）'!F79 | F30: =IF('財務諸表（入力）'!H79=0,"",'財務諸表（入力）'!H79) | G30: =IF('財務諸表（入力）'!K79=0,"",'財務諸表（入力）'!K79)
A31: 総資本 | E31: ='財務諸表（入力）'!F80 -> #VALUE! | F31: =IF('財務諸表（入力）'!H80=0,"",'財務諸表（入力）'!H80) -> #VALUE! | G31: =IF('財務諸表（入力）'!K80=0,"",'財務諸表（入力）'!K80) -> #VALUE!
A33: （２）売上と主要ＢＳ科目の推移
E34: ='財務諸表（入力）'!$E$5 -> 前々期 | F34: ='財務諸表（入力）'!$G$5 -> 前期 | G34: ='財務諸表（入力）'!$J$5 -> 今期
A35: 売上高 | E35: =IF('財務諸表（入力）'!E129="","",'財務諸表（入力）'!E129/'財務諸表（入力）'!$E$129) | F35: =IF('財務諸表（入力）'!G129="","",'財務諸表（入力）'!G129/'財務諸表（入力）'!$E$129) | G35: =IF('財務諸表（入力）'!J129="","",'財務諸表（入力）'!J129/'財務諸表（入力）'!$E$129)
A36: 現預金 | E36: =IF('財務諸表（入力）'!E6="","",'財務諸表（入力）'!E6/'財務諸表（入力）'!$E$6) | F36: =IF('財務諸表（入力）'!G6="","",'財務諸表（入力）'!G6/'財務諸表（入力）'!$E$6) | G36: =IF('財務諸表（入力）'!J6="","",'財務諸表（入力）'!J6/'財務諸表（入力）'!$E$6)
A37: 売上債権 | E37: =IF(('財務諸表（入力）'!E9+'財務諸表（入力）'!E8+'財務諸表（入力）'!E83+'財務諸表（入力）'!E84)="","",('財務諸表（入力）'!E9+'財務諸表（入力）'!E8+'財務諸表（入力）'!E83+'財務諸表（入力）'!E84)/('財務諸表（入力）'!$E$9+'財務諸表（入力）'!$E$8+'財務諸表（入力）'!$E$83+'財務諸表（入力）'!$E$84)) -> #DIV/0! | F37: =IF(('財務諸表（入力）'!G9+'財務諸表（入力）'!G8+'財務諸表（入力）'!G83+'財務諸表（入力）'!G84)="","",('財務諸表（入力）'!G9+'財務諸表（入力）'!G8+'財務諸表（入力）'!G83+'財務諸表（入力）'!G84)/('財務諸表（入力）'!$E$9+'財務諸表（入力）'!$E$8+'財務諸表（入力）'!$E$83+'財務諸表（入力）'!$E$84)) -> #DIV/0! | G37: =IF(('財務諸表（入力）'!J9+'財務諸表（入力）'!J8+'財務諸表（入力）'!J83+'財務諸表（入力）'!J84)="","",('財務諸表（入力）'!J9+'財務諸表（入力）'!J8+'財務諸表（入力）'!J83+'財務諸表（入力）'!J84)/('財務諸表（入力）'!$E$9+'財務諸表（入力）'!$E$8+'財務諸表（入力）'!$E$83+'財務諸表（入力）'!$E$84)) -> #DIV/0!
A38: 棚卸資産 | E38: =IF('財務諸表（入力）'!E16="","",('財務諸表（入力）'!E16/'財務諸表（入力）'!$E$16)) -> #DIV/0! | F38: =IF('財務諸表（入力）'!G16="","",('財務諸表（入力）'!G16/'財務諸表（入力）'!$E$16)) -> #DIV/0! | G38: =IF('財務諸表（入力）'!J16="","",('財務諸表（入力）'!J16/'財務諸表（入力）'!$E$16)) -> #DIV/0!
A39: 買入債務 | E39: =IF(('財務諸表（入力）'!E51+'財務諸表（入力）'!E52+'財務諸表（入力）'!E84)="","",(('財務諸表（入力）'!E51+'財務諸表（入力）'!E52+'財務諸表（入力）'!E84)/('財務諸表（入力）'!$E$51+'財務諸表（入力）'!$E$52+'財務諸表（入力）'!$E$84))) -> #DIV/0! | F39: =IF(('財務諸表（入力）'!G51+'財務諸表（入力）'!G52+'財務諸表（入力）'!G84)="","",(('財務諸表（入力）'!G51+'財務諸表（入力）'!G52+'財務諸表（入力）'!G84)/('財務諸表（入力）'!$E$51+'財務諸表（入力）'!$E$52+'財務諸表（入力）'!$E$84))) -> #DIV/0! | G39: =IF(('財務諸表（入力）'!J51+'財務諸表（入力）'!J52+'財務諸表（入力）'!J84)="","",(('財務諸表（入力）'!J51+'財務諸表（入力）'!J52+'財務諸表（入力）'!J84)/('財務諸表（入力）'!$E$51+'財務諸表（入力）'!$E$52+'財務諸表（入力）'!$E$84))) -> #DIV/0!
A40: 有形固定資産 | E40: =IF('財務諸表（入力）'!E37="","",('財務諸表（入力）'!E37/'財務諸表（入力）'!$E$37)) -> #DIV/0! | F40: =IF('財務諸表（入力）'!G37="","",('財務諸表（入力）'!G37/'財務諸表（入力）'!$E$37)) -> #DIV/0! | G40: =IF('財務諸表（入力）'!J37="","",('財務諸表（入力）'!J37/'財務諸表（入力）'!$E$37)) -> #DIV/0!
A41: 投資等 | E41: =IF('財務諸表（入力）'!E47="","",('財務諸表（入力）'!E47/'財務諸表（入力）'!$E$47)) -> #DIV/0! | F41: =IF('財務諸表（入力）'!G47="","",('財務諸表（入力）'!G47/'財務諸表（入力）'!$E$47)) -> #DIV/0! | G41: =IF('財務諸表（入力）'!J47="","",('財務諸表（入力）'!J47/'財務諸表（入力）'!$E$47)) -> #DIV/0!
A42: 借入金 | E42: =IF(('財務諸表（入力）'!E53+'財務諸表（入力）'!E62+'財務諸表（入力）'!E63+'財務諸表（入力）'!E83)="","",('財務諸表（入力）'!E53+'財務諸表（入力）'!E62+'財務諸表（入力）'!E63+'財務諸表（入力）'!E83)/('財務諸表（入力）'!$E$53+'財務諸表（入力）'!$E$62+'財務諸表（入力）'!$E$63+'財務諸表（入力）'!$E$83)) -> #DIV/0! | F42: =IF(('財務諸表（入力）'!G53+'財務諸表（入力）'!G62+'財務諸表（入力）'!G63+'財務諸表（入力）'!G83)="","",('財務諸表（入力）'!G53+'財務諸表（入力）'!G62+'財務諸表（入力）'!G63+'財務諸表（入力）'!G83)/('財務諸表（入力）'!$E$53+'財務諸表（入力）'!$E$62+'財務諸表（入力）'!$E$63+'財務諸表（入力）'!$E$83)) -> #DIV/0! | G42: =IF(('財務諸表（入力）'!J53+'財務諸表（入力）'!J62+'財務諸表（入力）'!J63+'財務諸表（入力）'!J83)="","",('財務諸表（入力）'!J53+'財務諸表（入力）'!J62+'財務諸表（入力）'!J63+'財務諸表（入力）'!J83)/('財務諸表（入力）'!$E$53+'財務諸表（入力）'!$E$62+'財務諸表（入力）'!$E$63+'財務諸表（入力）'!$E$83)) -> #DIV/0!
A43: 純資産 | E43: =IF('財務諸表（入力）'!E79="","",('財務諸表（入力）'!E79/'財務諸表（入力）'!$E$79)) -> #DIV/0! | F43: =IF('財務諸表（入力）'!G79="","",('財務諸表（入力）'!G79/'財務諸表（入力）'!$E$79)) -> #DIV/0! | G43: =IF('財務諸表（入力）'!J79="","",('財務諸表（入力）'!J79/'財務諸表（入力）'!$E$79)) -> #DIV/0!
A44: =CONCATENATE("（",E34,"の各科目の数値を１００とした場合の",F34,"及び",G34,"の推移）") -> （前々期の各科目の数値を１００とした場合の前期及び今期の推移）
A49: ３．運転資金の増減分析
A51: （１）回転期間の変化
G52: 単位：千円 | J52: 増減率
E53: ='財務諸表（入力）'!$E$5 -> 前々期 | F53: ='財務諸表（入力）'!$G$5 -> 前期 | G53: ='財務諸表（入力）'!$J$5 -> 今期 | H53: 算式 | J53: =F53 -> 前期 | K53: =G53 -> 今期 | AC53: 固定費の内訳
A54: 平均月商 | E54: =E6/12 -> 0 | F54: =IF(F6=0,"",F6/12) | G54: =IF(G6=0,"",G6/12) | J54: =IF(F54="","",F54/E54) | K54: =IF(G54="","",G54/F54) | AD54: ='財務諸表（入力）'!$E$5 -> 前々期 | AE54: ='財務諸表（入力）'!$G$5 -> 前期 | AF54: ='財務諸表（入力）'!$J$5 -> 今期
A55: 売上債権回転期間 | E55: =('財務諸表（入力）'!E9+'財務諸表（入力）'!E8+'財務諸表（入力）'!E83+'財務諸表（入力）'!E84)/E54 -> #DIV/0! | F55: =IF(F6=0,"",('財務諸表（入力）'!G9+'財務諸表（入力）'!G8+'財務諸表（入力）'!G83+'財務諸表（入力）'!G84)/F54) | G55: =IF(G6=0,"",('財務諸表（入力）'!J9+'財務諸表（入力）'!J8+'財務諸表（入力）'!J83+'財務諸表（入力）'!J84)/G54) | H55: 売上債権額÷月商＝（A） | J55: =IF(F55="","",F55/E55) | K55: =IF(G55="","",G55/F55) | AC55: 労務費 | AD55: =SUMIF('財務諸表（入力）'!$C$97:$C$100,"F",'財務諸表（入力）'!$E$97:$E$100) -> 0 | AE55: =SUMIF('財務諸表（入力）'!$C$97:$C$100,"F",'財務諸表（入力）'!$G$97:$G$100) -> 0 | AF55: =SUMIF('財務諸表（入力）'!$C$97:$C$100,"F",'財務諸表（入力）'!$J$97:$J$100) -> 0
A56: 棚卸資産回転期間 | E56: ='財務諸表（入力）'!E16/E54 -> #DIV/0! | F56: =IF(F6=0,"",'財務諸表（入力）'!G16/F54) | G56: =IF(G6=0,"",'財務諸表（入力）'!J16/G54) | H56: 棚卸資産額÷月商＝（B） | J56: =IF(F56="","",F56/E56) | K56: =IF(G56="","",G56/F56) | AC56: 製造原価製造原価 | AD56: =SUMIF('財務諸表（入力）'!$C$102:$C$116,"F",'財務諸表（入力）'!$E$102:$E$116) -> 0 | AE56: =SUMIF('財務諸表（入力）'!$C$102:$C$116,"F",'財務諸表（入力）'!$G$102:$G$116) -> 0 | AF56: =SUMIF('財務諸表（入力）'!$C$102:$C$116,"F",'財務諸表（入力）'!$J$102:$J$116) -> 0
A57: 買入債務回転期間 | E57: =('財務諸表（入力）'!E51+'財務諸表（入力）'!E52+'財務諸表（入力）'!E84)/E54 -> #DIV/0! | F57: =IF(F6=0,"",('財務諸表（入力）'!G51+'財務諸表（入力）'!G52+'財務諸表（入力）'!G84)/F54) | G57: =IF(G6=0,"",('財務諸表（入力）'!J51+'財務諸表（入力）'!J52+'財務諸表（入力）'!J84)/G54) | H57: 買入債務額÷月商＝（C） | J57: =IF(F57="","",F57/E57) | K57: =IF(G57="","",G57/F57) | AC57: 販売管理費 | AD57: =SUMIF('財務諸表（入力）'!$C$138:$C$155,"F",'財務諸表（入力）'!$E$138:$E$155) -> 0 | AE57: =SUMIF('財務諸表（入力）'!$C$138:$C$155,"F",'財務諸表（入力）'!$G$138:$G$155) -> 0 | AF57: =SUMIF('財務諸表（入力）'!$C$138:$C$155,"F",'財務諸表（入力）'!$J$138:$J$155) -> 0
A58: 回転期間合計 | E58: =E55+E56-E57 -> #DIV/0! | F58: =IF(F6=0,"",F55+F56-F57) | G58: =IF(G6=0,"",G55+G56-G57) | H58: （A）+（B）-（C） | J58: =IF(F58="","",F58/E58) | K58: =IF(G58="","",G58/F58) | AC58: 営業外支出 | AD58: =+'財務諸表（入力）'!E165 -> 0 | AE58: =+'財務諸表（入力）'!G165 -> 0 | AF58: =+'財務諸表（入力）'!J165 -> 0
A59: 所要運転資金 | E59: =E54*E58 -> #DIV/0! | F59: =IF(F6=0,"",F54*F58) | G59: =IF(G6=0,"",G54*G58) | H59: 平均月商×回転期間合計 | J59: =IF(F59="","",F59/E59) | K59: =IF(G59="","",G59/F59) | AC59: 営業外収入 | AD59: ='財務諸表（入力）'!E162 -> 0 | AE59: ='財務諸表（入力）'!G162 -> 0 | AF59: ='財務諸表（入力）'!J162 -> 0
A60: 所要運転資金の増減額 | E60: - | F60: =IF(F6=0,"",F59-E59) | G60: =IF(G6=0,"",G59-F59) | J60: - | K60: - | AC60: 合計 | AD60: =AD55+AD57+AD58-AD59 -> 0 | AE60: =AE55+AE57+AE58-AE59 -> 0 | AF60: =AF55+AF57+AF58-AF59 -> 0
A61: 受取手形の内割引・裏書分 | E61: =('財務諸表（入力）'!E83+'財務諸表（入力）'!E84)/'財務諸表（入力）'!E8 -> #DIV/0! | F61: =('財務諸表（入力）'!G83+'財務諸表（入力）'!G84)/'財務諸表（入力）'!G8 -> #DIV/0! | G61: =('財務諸表（入力）'!J83+'財務諸表（入力）'!J84)/'財務諸表（入力）'!J8 -> #DIV/0! | J61: =IF(E61*F61=0,"",F61/E61) -> #DIV/0! | K61: =IF(F61*G61=0,"",G61/F61) -> #DIV/0!
A65: （２）各期の運転資金変動要因
I66: =CONCATENATE("※前期基準＝回転期間が前期同水準の場合の",G68,"の見込額") -> ※前期基準＝回転期間が前期同水準の場合の前期の見込額
A67: =CONCATENATE("■ ",E68,"→",G68,"") -> ■ 前々期→前期 | M67: 単位：千円
E68: =F104 -> 前々期 | G68: =G104 -> 前期 | I68: 所要運転資金 増減 【B】-【A】 | J68: 前期基準※ 【C】 | L68: 月商増減の 影響 【C】-【A】 | M68: 回転期間 変化の影響 【B】-【C】 | AB68: =CONCATENATE("",$E$68,"→",$G$68,"") -> 前々期→前期 | AC68: =CONCATENATE("",$E$84,"→",$G$84,"") -> 前期→今期
E69: 金額【A】 | F69: 回転期間（月） | G69: 金額【B】 | H69: 回転期間（月） | AA69: 所要運転資金の増減額 | AB69: =I81 -> 0 | AC69: =I97 -> 0
A70: 平均月商 | E70: =E54 -> 0 | F70: - | G70: =F54 | H70: - | I70: =G70-E70 -> #VALUE! | J70: - | L70: - | M70: - | AA70: うち月商増減の影響 | AB70: =L81 -> #VALUE! | AC70: =L97 -> #VALUE!
A71: 受取手形 | E71: ='財務諸表（入力）'!E8+'財務諸表（入力）'!E83+'財務諸表（入力）'!E84 -> 0 | F71: =E71/E54 -> #DIV/0! | G71: ='財務諸表（入力）'!G8+'財務諸表（入力）'!G83+'財務諸表（入力）'!G84 -> 0 | H71: =IF(F$54=0,"",G71/F$54) -> #VALUE! | I71: =G71-E71 -> 0 | J71: =G$70*F71 -> #VALUE! | L71: =J71-E71 -> #VALUE! | M71: =G71-J71 -> #VALUE! | AA71: うち回転期間の変化の影響 | AB71: =M81 -> #VALUE! | AC71: =M97 -> #VALUE!
A72: 売掛金 | E72: ='財務諸表（入力）'!E9 -> 0 | F72: =E72/E54 -> #DIV/0! | G72: ='財務諸表（入力）'!G9 -> 0 | H72: =IF(F$54=0,"",G72/F$54) -> #VALUE! | I72: =G72-E72 -> 0 | J72: =G$70*F72 -> #VALUE! | L72: =J72-E72 -> #VALUE! | M72: =G72-J72 -> #VALUE!
A73: 製品・商品 | E73: ='財務諸表（入力）'!E12 -> 0 | F73: =E73/E54 -> #DIV/0! | G73: ='財務諸表（入力）'!G12 -> 0 | H73: =IF(F$54=0,"",G73/F$54) -> #VALUE! | I73: =G73-E73 -> 0 | J73: =G$70*F73 -> #VALUE! | L73: =J73-E73 -> #VALUE! | M73: =G73-J73 -> #VALUE!
A74: 原材料 | E74: ='財務諸表（入力）'!E13 -> 0 | F74: =E74/E54 -> #DIV/0! | G74: ='財務諸表（入力）'!G13 -> 0 | H74: =IF(F$54=0,"",G74/F$54) -> #VALUE! | I74: =G74-E74 -> 0 | J74: =G$70*F74 -> #VALUE! | L74: =J74-E74 -> #VALUE! | M74: =G74-J74 -> #VALUE! | AB74: =CONCATENATE("",$E$68,"→",$G$68,"") -> 前々期→前期 | AC74: =CONCATENATE("",$E$84,"→",$G$84,"") -> 前期→今期
A75: 仕掛品 | E75: ='財務諸表（入力）'!E14 -> 0 | F75: =E75/E54 -> #DIV/0! | G75: ='財務諸表（入力）'!G14 -> 0 | H75: =IF(F$54=0,"",G75/F$54) -> #VALUE! | I75: =G75-E75 -> 0 | J75: =G$70*F75 -> #VALUE! | L75: =J75-E75 -> #VALUE! | M75: =G75-J75 -> #VALUE! | AA75: 回転期間変化による増減額 | AB75: =AB71 -> #VALUE! | AC75: =AC71 -> #VALUE!
A76: 貯蔵品他 | E76: ='財務諸表（入力）'!E15 -> 0 | F76: =E76/E54 -> #DIV/0! | G76: ='財務諸表（入力）'!G15 -> 0 | H76: =IF(F$54=0,"",G76/F$54) -> #VALUE! | I76: =G76-E76 -> 0 | J76: =G$70*F76 -> #VALUE! | L76: =J76-E76 -> #VALUE! | M76: =G76-J76 -> #VALUE! | AA76: うち売上債権分 | AB76: =M71+M72 -> #VALUE! | AC76: =M87+M88 -> #VALUE!
A77: 需要合計 | E77: =SUM(E71:E76) -> 0 | F77: =SUM(F71:F76) -> #DIV/0! | G77: =SUM(G71:G76) -> 0 | H77: =SUM(H71:H76) -> #VALUE! | I77: =G77-E77 -> 0 | J77: =SUM(J71:J76) -> #VALUE! | L77: =SUM(L71:L76) -> #VALUE! | M77: =SUM(M71:M76) -> #VALUE! | AA77: うち買入債務分 | AB77: =(M78+M79)*-1 -> #VALUE! | AC77: =(M94+M95)*-1 -> #VALUE!
A78: 支払手形 | E78: ='財務諸表（入力）'!E51 -> 0 | F78: =E78/E54 -> #DIV/0! | G78: ='財務諸表（入力）'!G51 -> 0 | H78: =IF(F$54=0,"",G78/F$54) -> #VALUE! | I78: =G78-E78 -> 0 | J78: =G$70*F78 -> #VALUE! | L78: =J78-E78 -> #VALUE! | M78: =G78-J78 -> #VALUE! | AA78: うち棚卸資産分 | AB78: =M73+M74+M75+M76 -> #VALUE! | AC78: =M89+M90+M91+M92 -> #VALUE!
A79: 買掛金 | E79: ='財務諸表（入力）'!E52+'財務諸表（入力）'!E84 -> 0 | F79: =E79/E54 -> #DIV/0! | G79: ='財務諸表（入力）'!G52+'財務諸表（入力）'!G84 -> 0 | H79: =IF(F$54=0,"",G79/F$54) -> #VALUE! | I79: =G79-E79 -> 0 | J79: =G$70*F79 -> #VALUE! | L79: =J79-E79 -> #VALUE! | M79: =G79-J79 -> #VALUE!
A80: 調達合計 | E80: =SUM(E78:E79) -> 0 | F80: =SUM(F78:F79) -> #DIV/0! | G80: =SUM(G78:G79) -> 0 | H80: =SUM(H78:H79) -> #VALUE! | I80: =G80-E80 -> 0 | J80: =SUM(J78:J79) -> #VALUE! | L80: =SUM(L78:L79) -> #VALUE! | M80: =SUM(M78:M79) -> #VALUE!
A81: 所要運転資金 | E81: =E77-E80 -> 0 | F81: =F77-F80 -> #DIV/0! | G81: =G77-G80 -> 0 | H81: =H77-H80 -> #VALUE! | I81: =G81-E81 -> 0 | J81: =J77-J80 -> #VALUE! | L81: =L77-L80 -> #VALUE! | M81: =M77-M80 -> #VALUE!
A83: =CONCATENATE("■ ",E84,"→",G84,"") -> ■ 前期→今期
E84: =G68 -> 前期 | G84: ='財務諸表（入力）'!J5 -> 今期 | I84: 所要運転資金 増減 【B】-【A】 | J84: 前期基準※ 【C】 | L84: 月商増減の 影響 【C】-【A】 | M84: 回転期間 変化の影響 【B】-【C】
E85: 金額【A】 | F85: 回転期間（月） | G85: 金額【B】 | H85: 回転期間（月）
A86: 平均月商 | E86: =G70 | F86: - | G86: =G54 | H86: - | I86: =G86-E86 -> #VALUE! | J86: - | L86: - | M86: - | O86: =CONCATENATE("■ ",E68,"→",G68,"内訳") -> ■ 前々期→前期内訳
A87: 受取手形 | E87: =G71 -> 0 | F87: =IF(F$54=0,"",E87/F$54) -> #VALUE! | G87: ='財務諸表（入力）'!J8+'財務諸表（入力）'!J83+'財務諸表（入力）'!J84 -> 0 | H87: =IF(G$54=0,"",G87/G$54) -> #VALUE! | I87: =G87-E87 -> 0 | J87: =G$86*F87 -> #VALUE! | L87: =J87-E87 -> #VALUE! | M87: =G87-J87 -> #VALUE! | O87: =IF(R87<0,"売上債権の回転期間短縮による、運転資金の減少＝","売上債権の回転期間長期化による、運転資金の増加＝") -> #VALUE! | R87: =M71+M72 -> #VALUE!
A88: 売掛金 | E88: =G72 -> 0 | F88: =IF(F$54=0,"",E88/F$54) -> #VALUE! | G88: ='財務諸表（入力）'!J9 -> 0 | H88: =IF(G$54=0,"",G88/G$54) -> #VALUE! | I88: =G88-E88 -> 0 | J88: =G$86*F88 -> #VALUE! | L88: =J88-E88 -> #VALUE! | M88: =G88-J88 -> #VALUE! | O88: =IF(R88<0,"買入債務の回転期間長期化による、運転資金の減少＝","買入債務の回転期間短縮による、運転資金の増加＝") -> #VALUE! | R88: =(M78+M79)*-1 -> #VALUE!
A89: 製品・商品 | E89: =G73 -> 0 | F89: =IF(F$54=0,"",E89/F$54) -> #VALUE! | G89: ='財務諸表（入力）'!J12 -> 0 | H89: =IF(G$54=0,"",G89/G$54) -> #VALUE! | I89: =G89-E89 -> 0 | J89: =G$86*F89 -> #VALUE! | L89: =J89-E89 -> #VALUE! | M89: =G89-J89 -> #VALUE! | O89: =IF(R89<0,"棚卸資産の回転期間短縮による、運転資金の減少＝","棚卸資産の回転期間長期化による、運転資金の増加＝") -> #VALUE! | R89: =M73+M74+M75+M76 -> #VALUE!
A90: 原材料 | E90: =G74 -> 0 | F90: =IF(F$54=0,"",E90/F$54) -> #VALUE! | G90: ='財務諸表（入力）'!J13 -> 0 | H90: =IF(G$54=0,"",G90/G$54) -> #VALUE! | I90: =G90-E90 -> 0 | J90: =G$86*F90 -> #VALUE! | L90: =J90-E90 -> #VALUE! | M90: =G90-J90 -> #VALUE! | R90: =SUM(R87:R89) -> #VALUE!
A91: 仕掛品 | E91: =G75 -> 0 | F91: =IF(F$54=0,"",E91/F$54) -> #VALUE! | G91: ='財務諸表（入力）'!J14 -> 0 | H91: =IF(G$54=0,"",G91/G$54) -> #VALUE! | I91: =G91-E91 -> 0 | J91: =G$86*F91 -> #VALUE! | L91: =J91-E91 -> #VALUE! | M91: =G91-J91 -> #VALUE!
A92: 貯蔵品他 | E92: =G76 -> 0 | F92: =IF(F$54=0,"",E92/F$54) -> #VALUE! | G92: ='財務諸表（入力）'!J15 -> 0 | H92: =IF(G$54=0,"",G92/G$54) -> #VALUE! | I92: =G92-E92 -> 0 | J92: =G$86*F92 -> #VALUE! | L92: =J92-E92 -> #VALUE! | M92: =G92-J92 -> #VALUE! | O92: =CONCATENATE("■ ",E84,"→",G84,"内訳") -> ■ 前期→今期内訳
A93: 需要合計 | E93: =SUM(E87:E92) -> 0 | F93: =SUM(F87:F92) -> #VALUE! | G93: =SUM(G87:G92) -> 0 | H93: =SUM(H87:H92) -> #VALUE! | I93: =G93-E93 -> 0 | J93: =SUM(J87:J92) -> #VALUE! | L93: =SUM(L87:L92) -> #VALUE! | M93: =SUM(M87:M92) -> #VALUE! | O93: =IF(R93<0,"売上債権の回転期間短縮による、運転資金の減少＝","売上債権の回転期間長期化による、運転資金の増加＝") -> #VALUE! | R93: =M87+M88 -> #VALUE!
A94: 支払手形 | E94: =G78 -> 0 | F94: =IF(F$54=0,"",E94/F$54) -> #VALUE! | G94: ='財務諸表（入力）'!J51 -> 0 | H94: =IF(G$54=0,"",G94/G$54) -> #VALUE! | I94: =G94-E94 -> 0 | J94: =G$86*F94 -> #VALUE! | L94: =J94-E94 -> #VALUE! | M94: =G94-J94 -> #VALUE! | O94: =IF(R94<0,"買入債務の回転期間長期化による、運転資金の減少＝","買入債務の回転期間短縮による、運転資金の増加＝") -> #VALUE! | R94: =(M94+M95)*-1 -> #VALUE!
A95: 買掛金 | E95: =G79 -> 0 | F95: =IF(F$54=0,"",E95/F$54) -> #VALUE! | G95: ='財務諸表（入力）'!J52+'財務諸表（入力）'!J84 -> 0 | H95: =IF(G$54=0,"",G95/G$54) -> #VALUE! | I95: =G95-E95 -> 0 | J95: =G$86*F95 -> #VALUE! | L95: =J95-E95 -> #VALUE! | M95: =G95-J95 -> #VALUE! | O95: =IF(R95<0,"棚卸資産の回転期間短縮による、運転資金の減少＝","棚卸資産の回転期間長期化による、運転資金の増加＝") -> #VALUE! | R95: =M89+M90+M91+M92 -> #VALUE!
A96: 調達合計 | E96: =SUM(E94:E95) -> 0 | F96: =SUM(F94:F95) -> #VALUE! | G96: =SUM(G94:G95) -> 0 | H96: =SUM(H94:H95) -> #VALUE! | I96: =G96-E96 -> 0 | J96: =SUM(J94:J95) -> #VALUE! | L96: =SUM(L94:L95) -> #VALUE! | M96: =SUM(M94:M95) -> #VALUE! | R96: =SUM(R93:R95) -> #VALUE!
A97: 所要運転資金 | E97: =E93-E96 -> 0 | F97: =F93-F96 -> #VALUE! | G97: =G93-G96 -> 0 | H97: =H93-H96 -> #VALUE! | I97: =G97-E97 -> 0 | J97: =J93-J96 -> #VALUE! | L97: =L93-L96 -> #VALUE! | M97: =M93-M96 -> #VALUE!
A100: ４．経営分析表 【ＴＫＣ経営指標基準】 | P100: ※業種分類 | Q100: 2899：その他電子部品・デバイス・電子回路製造業
P101: 業界平均値 引用 | Q101: 売上規模 | R101: 5億円～10億円
Q102: 対象企業数 | R102: 28
M103: 業界比較 ※TKCデータ | Q103: 平均従業員数 | R103: 67.1
F104: ='財務諸表（入力）'!$E$5 -> 前々期 | G104: ='財務諸表（入力）'!$G$5 -> 前期 | H104: 増減 | I104: ='財務諸表（入力）'!$J$5 -> 今期 | J104: 増減 | M104: ='財務諸表（入力）'!$J$5 -> 今期 | N104: 業界平均値 | Q104: １社あたり売上 | R104: 731759
A105: ◆収益性分析
A106: 総合 | B106: 総資本対営業利益率 | F106: =IF($E$6=0,"",'財務諸表（入力）'!E157/'財務諸表（入力）'!E50) | G106: =IF($F$6=0,"",'財務諸表（入力）'!G157/'財務諸表（入力）'!G50) | H106: =IF($E$6=0,"",G106-F106) | I106: =IF($G$6=0,"",'財務諸表（入力）'!J157/'財務諸表（入力）'!J50) | J106: =IF($E$6=0,"",I106-G106) | M106: =I106 | N106: 0.046
B107: 総資本経常利益率 | F107: =IF($E$6=0,"",'財務諸表（入力）'!E166/'財務諸表（入力）'!E50) | G107: =IF($F$6=0,"",'財務諸表（入力）'!G166/'財務諸表（入力）'!G50) | H107: =IF($E$6=0,"",G107-F107) | I107: =IF($G$6=0,"",'財務諸表（入力）'!J166/'財務諸表（入力）'!J50) | J107: =IF($E$6=0,"",I107-G107) | M107: =I107 | N107: 0.055
B108: 自己資本利益率（税引前） | F108: =IF($E$6=0,"",'財務諸表（入力）'!E169/'財務諸表（入力）'!E79) | G108: =IF($F$6=0,"",'財務諸表（入力）'!G169/'財務諸表（入力）'!G79) | H108: =IF($E$6=0,"",G108-F108) | I108: =IF($G$6=0,"",'財務諸表（入力）'!J169/'財務諸表（入力）'!J79) | J108: =IF($E$6=0,"",I108-G108) | M108: =I108 | N108: 0.102
A109: 資本回転率 | B109: 総資本回転率 | F109: =IF($E$6=0,"",'財務諸表（入力）'!E129/'財務諸表（入力）'!E50) | G109: =IF($F$6=0,"",'財務諸表（入力）'!G129/'財務諸表（入力）'!G50) | H109: =IF($E$6=0,"",G109-F109) | I109: =IF($G$6=0,"",'財務諸表（入力）'!J129/'財務諸表（入力）'!J50) | J109: =IF($E$6=0,"",I109-G109) | M109: =I109 | N109: 1.2
B110: 回転期間 | C110: 総資本 | F110: =IF($E$6=0,"",('財務諸表（入力）'!E50/'財務諸表（入力）'!$E$129)*365) | G110: =IF($F$6=0,"",('財務諸表（入力）'!G50/'財務諸表（入力）'!$G$129)*365) | H110: =IF($E$6=0,"",G110-F110) | I110: =IF($G$6=0,"",('財務諸表（入力）'!J50/'財務諸表（入力）'!$J$129)*365) | J110: =IF($E$6=0,"",I110-G110) | M110: =I110 | N110: 314.1
C111: 流動資産 | F111: =IF($E$6=0,"",('財務諸表（入力）'!E28/'財務諸表（入力）'!$E$129)*365) | G111: =IF($F$6=0,"",('財務諸表（入力）'!G28/'財務諸表（入力）'!$G$129)*365) | H111: =IF($E$6=0,"",G111-F111) | I111: =IF($G$6=0,"",('財務諸表（入力）'!J28/'財務諸表（入力）'!$J$129)*365) | J111: =IF($E$6=0,"",I111-G111) | M111: =I111 | N111: 189.9
D112: 現金・預金 | F112: =IF($E$6=0,"",('財務諸表（入力）'!E6/'財務諸表（入力）'!$E$129)*365) | G112: =IF($F$6=0,"",('財務諸表（入力）'!G6/'財務諸表（入力）'!$G$129)*365) | H112: =IF($E$6=0,"",G112-F112) | I112: =IF($G$6=0,"",('財務諸表（入力）'!J6/'財務諸表（入力）'!$J$129)*365) | J112: =IF($E$6=0,"",I112-G112) | M112: =I112 | N112: 100.4
D113: 売上債権 | F113: =IF($E$6=0,"",(('財務諸表（入力）'!E9+'財務諸表（入力）'!E8+'財務諸表（入力）'!E83+'財務諸表（入力）'!E84)/'財務諸表（入力）'!$E$129)*365) | G113: =IF($F$6=0,"",(('財務諸表（入力）'!G9+'財務諸表（入力）'!G8+'財務諸表（入力）'!G83+'財務諸表（入力）'!G84)/'財務諸表（入力）'!$G$129)*365) | H113: =IF($E$6=0,"",G113-F113) | I113: =IF($G$6=0,"",(('財務諸表（入力）'!J9+'財務諸表（入力）'!J8+'財務諸表（入力）'!J83+'財務諸表（入力）'!J84)/'財務諸表（入力）'!$J$129)*365) | J113: =IF($E$6=0,"",I113-G113) | M113: =I113 | N113: 63.6
D114: 棚卸資産 | F114: =IF($E$6=0,"",('財務諸表（入力）'!E16/'財務諸表（入力）'!$E$129)*365) | G114: =IF($F$6=0,"",('財務諸表（入力）'!G16/'財務諸表（入力）'!$G$129)*365) | H114: =IF($E$6=0,"",G114-F114) | I114: =IF($G$6=0,"",('財務諸表（入力）'!J16/'財務諸表（入力）'!$J$129)*365) | J114: =IF($E$6=0,"",I114-G114) | M114: =I114 | N114: 16.3
D115: その他流動資産 | F115: =IF($E$6=0,"",(('財務諸表（入力）'!E28-'財務諸表（入力）'!E6-'財務諸表（入力）'!E9-'財務諸表（入力）'!E8-'財務諸表（入力）'!E83-'財務諸表（入力）'!E84-'財務諸表（入力）'!E16)/'財務諸表（入力）'!$E$129)*365) | G115: =IF($F$6=0,"",(('財務諸表（入力）'!G28-'財務諸表（入力）'!G6-'財務諸表（入力）'!G9-'財務諸表（入力）'!G8-'財務諸表（入力）'!G83-'財務諸表（入力）'!G84-'財務諸表（入力）'!G16)/'財務諸表（入力）'!$G$129)*365) | H115: =IF($E$6=0,"",G115-F115) | I115: =IF($G$6=0,"",(('財務諸表（入力）'!J28-'財務諸表（入力）'!J6-'財務諸表（入力）'!J9-'財務諸表（入力）'!J8-'財務諸表（入力）'!J83-'財務諸表（入力）'!J84-'財務諸表（入力）'!J16)/'財務諸表（入力）'!$J$129)*365) | J115: =IF($E$6=0,"",I115-G115) | M115: =I115 | N115: 9.6
C116: 固定・繰延資産 | F116: =IF($E$6=0,"",('財務諸表（入力）'!E49/'財務諸表（入力）'!$E$129)*365) | G116: =IF($F$6=0,"",('財務諸表（入力）'!G49/'財務諸表（入力）'!$G$129)*365) | H116: =IF($E$6=0,"",G116-F116) | I116: =IF($G$6=0,"",('財務諸表（入力）'!J49/'財務諸表（入力）'!$J$129)*365) | J116: =IF($E$6=0,"",I116-G116) | M116: =I116 | N116: 124.2
D117: 有形固定資産 | F117: =IF($E$6=0,"",('財務諸表（入力）'!E37/'財務諸表（入力）'!$E$129)*365) | G117: =IF($F$6=0,"",('財務諸表（入力）'!G37/'財務諸表（入力）'!$G$129)*365) | H117: =IF($E$6=0,"",G117-F117) | I117: =IF($G$6=0,"",('財務諸表（入力）'!J37/'財務諸表（入力）'!$J$129)*365) | J117: =IF($E$6=0,"",I117-G117) | M117: =I117 | N117: 89.5
...

Sheet 資金運用表
A1: ='財務諸表（入力）'!D1 -> 0 | S1: ='財務諸表（入力）'!A1 -> 企業名 : | U1: ='財務諸表（入力）'!D1 -> 0 | W1: ＊１ 固定資金は固定資産の増減、固定負債、資本の増減
A3: =CONCATENATE("■ ",F41," 資金運用表分析") -> ■ 前期 資金運用表分析
I5: 単位：千円 | S5: ='財務諸表（入力）'!J5 -> 今期 | W5: ＊２ 運転資金は現預金を除く流動資産の増減、短期借入金、割引手形を除く流動負債の増減
D6: 資金の運用 | G6: 資金の調達
A7: 固定資金 | D7: 法人税等支払い | F7: =L121 -> 0 | G7: 税引前当期利益① | I7: =M123 -> 0
D8: 配当金支払い | F8: =L119 -> 0 | G8: 減価償却費等② | I8: =M116 -> 0
D9: 役員賞与支払い | F9: =L120 -> 0 | G9: 増資等 | I9: =(M106+M107+M108)-(L106+L107+L108)+(M112+M113)-(L112+L113) -> 0
D10: 有形固定資産増加 | F10: =L72 -> 0 | G10: 有形固定資産減少 | I10: =M72 -> 0
D11: 長期借入金・社債の減少 | F11: =L97+L101 -> 0 | G11: 長期借入金・社債の増加 | I11: =M97+M101 -> 0
D12: 投資等の増加 | F12: =IF(SUM(L74:L81)>SUM(M74:M81),SUM(L74:L81)-SUM(M74:M81),0) -> 0 | G12: 投資等の減少 | I12: =IF(SUM(L74:L81)<SUM(M74:M81),SUM(M74:M81)-SUM(L74:L81),0) -> 0
D13: 無形・繰延資産増 | F13: =L73+L83 -> 0 | G13: 無形・繰延資産減 | I13: =M73+M83 -> 0
D14: 借入以外の固定負債減 | F14: =IF((SUM(L98:L103)-L101)-(SUM(M98:M103)-M101)>0,(SUM(L98:L103)-L101)-(SUM(M98:M103)-M101),0) -> 0 | G14: 借入以外の固定負債増 | I14: =IF((SUM(L98:L103)-L101)-(SUM(M98:M103)-M101)<0,(SUM(M98:M103)-M101)-(SUM(L98:L103)-L101),0) -> 0
D15: 資金の余剰 | F15: =L125 -> 0 | G15: 資金の不足 | I15: =M125 -> 0
D16: 合計 | F16: =SUM(F7:F15) -> 0 | G16: 合計 | I16: =SUM(I7:I15) -> 0
D17: 照合（０でOK) | F17: =F16-I16 -> 0 | G17: ＣＦ（①＋②） | I17: =I7+I8 -> 0
A19: 運転資金 | D19: 売上債権の増加 | F19: =IF(N43+N44-O43-O44>0,N43+N44-O43-O44,0) -> 0 | G19: 買入債務の増加 | I19: =IF(N86+N87-O86-O87<0,O86+O87-N86-N87,0) -> 0
D20: 棚卸資産の増加 | F20: =N51 -> 0 | G20: 貸倒引当増加 | I20: =IF(N57+N79-O57-O79<0,O57+O79-N57-N79,0) -> 0
D21: その他流動資産増 | F21: =IF(SUM(N52,N53,N54,N55,N56,N58,N59,N60,N61)-SUM(O52,O53,O54,O55,O56,O58,O59,O60,O61)>0,SUM(N52,N53,N54,N55,N56,N58,N59,N60,N61)-SUM(O52,O53,O54,O55,O56,O58,O59,O60,O61),0) -> 0 | G21: その他流動負債増 | I21: =IF(SUM(N89:N95)-SUM(O89:O95)<0,SUM(O89:O95)-SUM(N89:N95),0) -> 0
D22: 買入債務減少 | F22: =IF(N86+N87-O86-O87>0,N86+N87-O86-O87,0) -> 0 | G22: 売上債権の減少 | I22: =IF(N43+N44-O43-O44<0,O43+O44-N43-N44,0) -> 0
D23: その他流動負債減 | F23: =IF(SUM(N89:N95)-SUM(O89:O95)>0,SUM(N89:N95)-SUM(O89:O95),0) -> 0 | G23: 棚卸資産の減少 | I23: =O51 -> 0
D24: 貸倒引当減少 | F24: =IF(N57+N79-O57-O79>0,N57+N79-O57-O79,0) -> 0 | G24: その他流動資産減 | I24: =IF(SUM(N52,N53,N54,N55,N56,N58,N59,N60,N61)-SUM(O52,O53,O54,O55,O56,O58,O59,O60,O61)<0,SUM(O52,O53,O54,O55,O56,O58,O59,O60,O61)-SUM(N52,N53,N54,N55,N56,N58,N59,N60,N61),0) -> 0
D25: 有価証券等の増加 | F25: =N45 -> 0 | G25: 有価証券等の減少 | I25: =O45 -> 0
D26: 資金の余剰 | F26: =N125 -> 0 | G26: 資金の不足 | I26: =O125 -> 0
D27: 合計 | F27: =SUM(F19:F26) -> 0 | G27: 合計 | I27: =SUM(I19:I26) -> 0
D28: 照合（０でOK) | F28: =I27-F27 -> 0
A30: 財務資金 | D30: 現預金増加 | F30: =P42 -> 0 | G30: 短期借入金増加 | I30: =Q88 -> 0
D31: 短期借入金減少 | F31: =P88 -> 0 | G31: 割引手形等増加 | I31: =Q117 -> 0
D32: 割引手形等減少 | F32: =P117 -> 0 | G32: 現預金減少 | I32: =Q42 -> 0
D33: 固定資金の不足 | F33: =I15 -> 0 | G33: 固定資金の余剰 | I33: =F15 -> 0
D34: 運転資金の不足 | F34: =I26 -> 0 | G34: 運転資金の余剰 | I34: =F26 -> 0
D35: 合計 | F35: =SUM(F30:F34) -> 0 | G35: 合計 | I35: =SUM(I30:I34) -> 0
D36: 照合（０でOK) | F36: =I35-F35 -> 0
D37: 精算表と照合 | F37: =F35-P126 -> 0 | I37: =I35-Q126 -> 0
A39: 【精算表】
A40: ='財務諸表（入力）'!A4 -> 項目 | E40: ='財務諸表（入力）'!E4 -> 2020年2月1日～ 2021年1月31日 | F40: ='財務諸表（入力）'!G4 -> 2021年2月1日～2022年1月31日 | G40: 増減 | H40: 増減仕訳 | J40: 修正 | L40: 固定資金 | N40: 運転資金 | P40: 財務資金
E41: ='財務諸表（入力）'!E5 -> 前々期 | F41: ='財務諸表（入力）'!G5 -> 前期 | H41: 借方 | I41: 貸方 | J41: 借方 | K41: 貸方 | L41: 運用 | M41: 調達 | N41: 運用 | O41: 調達 | P41: 運用 | Q41: 調達
A42: 資産の部 | B42: 流動資産 | C42: 当座資産 | D42: ='財務諸表（入力）'!D6 -> 現金・預金 | E42: ='財務諸表（入力）'!E6 -> 0 | F42: ='財務諸表（入力）'!G6 -> 0 | G42: =F42-E42 -> 0 | H42: =IF(G42>1,SUM(G42:G42),0) -> 0 | I42: =IF(G42<1,SUM(G42:G42)*-1,0) -> 0 | N42: - | O42: - | P42: =H42 -> 0 | Q42: =I42 -> 0
D43: ='財務諸表（入力）'!D9 -> 売掛金 | E43: ='財務諸表（入力）'!E9 -> 0 | F43: ='財務諸表（入力）'!G9 -> 0 | G43: =F43-E43 -> 0 | H43: =IF(G43>1,SUM(G43:G43),0) -> 0 | I43: =IF(G43<1,SUM(G43:G43)*-1,0) -> 0 | N43: =H43 -> 0 | O43: =I43 -> 0
D44: ='財務諸表（入力）'!D8 -> 受取手形 | E44: ='財務諸表（入力）'!E8 -> 0 | F44: ='財務諸表（入力）'!G8 -> 0 | G44: =F44-E44 -> 0 | H44: =IF(G44>1,SUM(G44:G44),0) -> 0 | I44: =IF(G44<1,SUM(G44:G44)*-1,0) -> 0 | J44: =K117 -> 0 | K44: =J117 -> 0 | N44: =H44+J44 -> 0 | O44: =I44+K44 -> 0
D45: ='財務諸表（入力）'!D10 -> 0 | E45: ='財務諸表（入力）'!E10 -> 0 | F45: ='財務諸表（入力）'!G10 -> 0 | G45: =F45-E45 -> 0 | H45: =IF(G45>1,SUM(G45:G45),0) -> 0 | I45: =IF(G45<1,SUM(G45:G45)*-1,0) -> 0 | N45: =H45 -> 0 | O45: =I45 -> 0
C46: 当座資産小計 | E46: =SUM(E42:E45) -> 0 | F46: =SUM(F42:F45) -> 0 | G46: =SUM(G42:G45) -> 0 | H46: =SUM(H42:H45) -> 0 | I46: =SUM(I42:I45) -> 0 | N46: - | O46: -
C47: 棚卸資産 | D47: ='財務諸表（入力）'!D12 -> 製品・商品 | E47: ='財務諸表（入力）'!E12 -> 0 | F47: ='財務諸表（入力）'!G12 -> 0 | G47: =F47-E47 -> 0 | H47: =IF(G47>1,SUM(G47:G47),0) -> 0 | I47: =IF(G47<1,SUM(G47:G47)*-1,0) -> 0 | N47: - | O47: -
D48: ='財務諸表（入力）'!D13 -> 原材料 | E48: ='財務諸表（入力）'!E13 -> 0 | F48: ='財務諸表（入力）'!G13 -> 0 | G48: =F48-E48 -> 0 | H48: =IF(G48>1,SUM(G48:G48),0) -> 0 | I48: =IF(G48<1,SUM(G48:G48)*-1,0) -> 0 | N48: - | O48: -
D49: ='財務諸表（入力）'!D14 -> 仕掛品 | E49: ='財務諸表（入力）'!E14 -> 0 | F49: ='財務諸表（入力）'!G14 -> 0 | G49: =F49-E49 -> 0 | H49: =IF(G49>1,SUM(G49:G49),0) -> 0 | I49: =IF(G49<1,SUM(G49:G49)*-1,0) -> 0 | N49: - | O49: -
D50: ='財務諸表（入力）'!D15 | E50: ='財務諸表（入力）'!E15 -> 0 | F50: ='財務諸表（入力）'!G15 -> 0 | G50: =F50-E50 -> 0 | H50: =IF(G50>1,SUM(G50:G50),0) -> 0 | I50: =IF(G50<1,SUM(G50:G50)*-1,0) -> 0 | N50: - | O50: -
C51: 棚卸資産小計 | E51: =SUM(E47:E50) -> 0 | F51: =SUM(F47:F50) -> 0 | G51: =SUM(G47:G50) -> 0 | H51: =SUM(H47:H50) -> 0 | I51: =SUM(I47:I50) -> 0 | N51: =IF(H51-I51>0,H51-I51,0) -> 0 | O51: =IF(H51-I51<0,I51-H51,0) -> 0
C52: その他流動資産 | D52: ='財務諸表（入力）'!D17 -> 0 | E52: ='財務諸表（入力）'!E17 -> 0 | F52: ='財務諸表（入力）'!G17 -> 0 | G52: =F52-E52 -> 0 | H52: =IF(G52>1,SUM(G52:G52),0) -> 0 | I52: =IF(G52<1,SUM(G52:G52)*-1,0) -> 0 | N52: =H52 -> 0 | O52: =I52 -> 0
D53: ='財務諸表（入力）'!D22 -> 0 | E53: ='財務諸表（入力）'!E22 -> 0 | F53: ='財務諸表（入力）'!G22 -> 0 | G53: =F53-E53 -> 0 | H53: =IF(G53>1,SUM(G53:G53),0) -> 0 | I53: =IF(G53<1,SUM(G53:G53)*-1,0) -> 0 | N53: =H53 -> 0 | O53: =I53 -> 0
D54: ='財務諸表（入力）'!D18 -> 0 | E54: ='財務諸表（入力）'!E18 -> 0 | F54: ='財務諸表（入力）'!G18 -> 0 | G54: =F54-E54 -> 0 | H54: =IF(G54>1,SUM(G54:G54),0) -> 0 | I54: =IF(G54<1,SUM(G54:G54)*-1,0) -> 0 | N54: =H54 -> 0 | O54: =I54 -> 0
D55: ='財務諸表（入力）'!D23 -> 0 | E55: ='財務諸表（入力）'!E23 -> 0 | F55: ='財務諸表（入力）'!G23 -> 0 | G55: =F55-E55 -> 0 | H55: =IF(G55>1,SUM(G55:G55),0) -> 0 | I55: =IF(G55<1,SUM(G55:G55)*-1,0) -> 0 | N55: =H55 -> 0 | O55: =I55 -> 0
D56: ='財務諸表（入力）'!D19 -> 0 | E56: ='財務諸表（入力）'!E19 -> 0 | F56: ='財務諸表（入力）'!G19 -> 0 | G56: =F56-E56 -> 0 | H56: =IF(G56>1,SUM(G56:G56),0) -> 0 | I56: =IF(G56<1,SUM(G56:G56)*-1,0) -> 0 | N56: =H56 -> 0 | O56: =I56 -> 0
D57: ='財務諸表（入力）'!D25 -> 貸倒引当金（▲） | E57: ='財務諸表（入力）'!E25 -> 0 | F57: ='財務諸表（入力）'!G25 -> 0 | G57: =F57-E57 -> 0 | H57: =IF(G57>1,SUM(G57:G57),0) -> 0 | I57: =IF(G57<1,SUM(G57:G57)*-1,0) -> 0 | N57: =H57 -> 0 | O57: =I57 -> 0
D58: ='財務諸表（入力）'!D24 -> 0 | E58: ='財務諸表（入力）'!E24 -> 0 | F58: ='財務諸表（入力）'!G24 -> 0 | G58: =F58-E58 -> 0 | H58: =IF(G58>1,SUM(G58:G58),0) -> 0 | I58: =IF(G58<1,SUM(G58:G58)*-1,0) -> 0 | N58: =H58 -> 0 | O58: =I58 -> 0
D59: ='財務諸表（入力）'!D20 -> 0 | E59: ='財務諸表（入力）'!E20 -> 0 | F59: ='財務諸表（入力）'!G20 -> 0 | G59: =F59-E59 -> 0 | H59: =IF(G59>1,SUM(G59:G59),0) -> 0 | I59: =IF(G59<1,SUM(G59:G59)*-1,0) -> 0 | N59: =H59 -> 0 | O59: =I59 -> 0
D60: ='財務諸表（入力）'!D21 -> 0 | E60: ='財務諸表（入力）'!E21 -> 0 | F60: ='財務諸表（入力）'!G21 -> 0 | G60: =F60-E60 -> 0 | H60: =IF(G60>1,SUM(G60:G60),0) -> 0 | I60: =IF(G60<1,SUM(G60:G60)*-1,0) -> 0 | N60: =H60 -> 0 | O60: =I60 -> 0
D61: ='財務諸表（入力）'!D26 -> 0 | E61: ='財務諸表（入力）'!E26 -> 0 | F61: ='財務諸表（入力）'!G26 -> 0 | G61: =F61-E61 -> 0 | H61: =IF(G61>1,SUM(G61:G61),0) -> 0 | I61: =IF(G61<1,SUM(G61:G61)*-1,0) -> 0 | N61: =H61 -> 0 | O61: =I61 -> 0
C62: その他流動資産小計 | E62: =SUM(E52:E61) -> 0 | F62: =SUM(F52:F61) -> 0 | G62: =F62-E62 -> 0 | H62: =SUM(H52:H61) -> 0 | I62: =SUM(I52:I61) -> 0 | N62: - | O62: -
B63: 流動資産合計 | E63: =E46+E51+E62 -> 0 | F63: =F46+F51+F62 -> 0 | G63: =F63-E63 -> 0 | H63: =SUM(H46+H51+H62) -> 0 | I63: =SUM(I46+I51+I62) -> 0 | N63: - | O63: -
B64: 固定資産 | C64: 有形固定資産 | D64: ='財務諸表（入力）'!D29 -> 建物付属設備 | E64: ='財務諸表（入力）'!E29 -> 0 | F64: ='財務諸表（入力）'!G29 -> 0 | G64: =F64-E64 -> 0 | H64: =IF(G64>1,SUM(G64:G64),0) -> 0 | I64: =IF(G64<1,SUM(G64:G64)*-1,0) -> 0 | L64: - | M64: -
D65: ='財務諸表（入力）'!D30 -> 構築物 | E65: ='財務諸表（入力）'!E30 -> 0 | F65: ='財務諸表（入力）'!G30 -> 0 | G65: =F65-E65 -> 0 | H65: =IF(G65>1,SUM(G65:G65),0) -> 0 | I65: =IF(G65<1,SUM(G65:G65)*-1,0) -> 0 | L65: - | M65: -
D66: ='財務諸表（入力）'!D31 -> 機械装置 | E66: ='財務諸表（入力）'!E31 -> 0 | F66: ='財務諸表（入力）'!G31 -> 0 | G66: =F66-E66 -> 0 | H66: =IF(G66>1,SUM(G66:G66),0) -> 0 | I66: =IF(G66<1,SUM(G66:G66)*-1,0) -> 0 | L66: - | M66: -
D67: ='財務諸表（入力）'!D32 -> 車両運搬具 | E67: ='財務諸表（入力）'!E32 -> 0 | F67: ='財務諸表（入力）'!G32 -> 0 | G67: =F67-E67 -> 0 | H67: =IF(G67>1,SUM(G67:G67),0) -> 0 | I67: =IF(G67<1,SUM(G67:G67)*-1,0) -> 0 | L67: - | M67: -
D68: ='財務諸表（入力）'!D33 -> 什器・備品 | E68: ='財務諸表（入力）'!E33 -> 0 | F68: ='財務諸表（入力）'!G33 -> 0 | G68: =F68-E68 -> 0 | H68: =IF(G68>1,SUM(G68:G68),0) -> 0 | I68: =IF(G68<1,SUM(G68:G68)*-1,0) -> 0 | L68: - | M68: -
D69: ='財務諸表（入力）'!D34 -> 土地 | E69: ='財務諸表（入力）'!E34 -> 0 | F69: ='財務諸表（入力）'!G34 -> 0 | G69: =F69-E69 -> 0 | H69: =IF(G69>1,SUM(G69:G69),0) -> 0 | I69: =IF(G69<1,SUM(G69:G69)*-1,0) -> 0 | L69: - | M69: -
D70: ='財務諸表（入力）'!D35 -> 建設仮勘定 | E70: ='財務諸表（入力）'!E35 -> 0 | F70: ='財務諸表（入力）'!G35 -> 0 | G70: =F70-E70 -> 0 | H70: =IF(G70>1,SUM(G70:G70),0) -> 0 | I70: =IF(G70<1,SUM(G70:G70)*-1,0) -> 0 | L70: - | M70: -
D71: ='財務諸表（入力）'!D36 -> リース資産 | E71: ='財務諸表（入力）'!E36 -> 0 | F71: ='財務諸表（入力）'!G36 -> 0 | G71: =F71-E71 -> 0 | H71: =IF(G71>1,SUM(G71:G71),0) -> 0 | I71: =IF(G71<1,SUM(G71:G71)*-1,0) -> 0 | L71: - | M71: -
C72: 有形固定資産小計 | E72: =SUM(E64:E71) -> 0 | F72: =SUM(F64:F71) -> 0 | G72: =F72-E72 -> 0 | H72: =SUM(H64:H71) -> 0 | I72: =SUM(I64:I71) -> 0 | J72: =K116 -> 0 | L72: =IF(H72+J72-I72>0,H72+J72-I72,0) -> 0 | M72: =IF(H72+J72-I72<0,I72-H72-J72,0) -> 0
C73: 無形固定資産 | E73: ='財務諸表（入力）'!E38 -> 0 | F73: ='財務諸表（入力）'!G38 -> 0 | G73: =F73-E73 -> 0 | H73: =IF(G73>1,SUM(G73:G73),0) -> 0 | I73: =IF(G73<1,SUM(G73:G73)*-1,0) -> 0 | L73: =H73 -> 0 | M73: =I73 -> 0
C74: 投資等 | D74: ='財務諸表（入力）'!D39 -> 投資有価証券 | E74: ='財務諸表（入力）'!E39 -> 0 | F74: ='財務諸表（入力）'!G39 -> 0 | G74: =F74-E74 -> 0 | H74: =IF(G74>1,SUM(G74:G74),0) -> 0 | I74: =IF(G74<1,SUM(G74:G74)*-1,0) -> 0 | L74: =H74 -> 0 | M74: =I74 -> 0
D75: ='財務諸表（入力）'!D40 -> 出資金 | E75: ='財務諸表（入力）'!E40 -> 0 | F75: ='財務諸表（入力）'!G40 -> 0 | G75: =F75-E75 -> 0 | H75: =IF(G75>1,SUM(G75:G75),0) -> 0 | I75: =IF(G75<1,SUM(G75:G75)*-1,0) -> 0 | L75: =H75 -> 0 | M75: =I75 -> 0
D76: ='財務諸表（入力）'!D41 -> 保証金他 | E76: ='財務諸表（入力）'!E41 -> 0 | F76: ='財務諸表（入力）'!G41 -> 0 | G76: =F76-E76 -> 0 | H76: =IF(G76>1,SUM(G76:G76),0) -> 0 | I76: =IF(G76<1,SUM(G76:G76)*-1,0) -> 0 | L76: =H76 -> 0 | M76: =I76 -> 0
D77: ='財務諸表（入力）'!D42 -> 敷金 | E77: ='財務諸表（入力）'!E42 -> 0 | F77: ='財務諸表（入力）'!G42 -> 0 | G77: =F77-E77 -> 0 | H77: =IF(G77>1,SUM(G77:G77),0) -> 0 | I77: =IF(G77<1,SUM(G77:G77)*-1,0) -> 0 | L77: =H77 -> 0 | M77: =I77 -> 0
D78: ='財務諸表（入力）'!D44 -> 保険積立金 | E78: ='財務諸表（入力）'!E44 -> 0 | F78: ='財務諸表（入力）'!G44 -> 0 | G78: =F78-E78 -> 0 | H78: =IF(G78>1,SUM(G78:G78),0) -> 0 | I78: =IF(G78<1,SUM(G78:G78)*-1,0) -> 0 | L78: =H78 -> 0 | M78: =I78 -> 0
D79: ='財務諸表（入力）'!D45 -> 貸倒引当金（▲） | E79: ='財務諸表（入力）'!E45 -> 0 | F79: ='財務諸表（入力）'!G45 -> 0 | G79: =F79-E79 -> 0 | H79: =IF(G79>1,SUM(G79:G79),0) -> 0 | I79: =IF(G79<1,SUM(G79:G79)*-1,0) -> 0 | N79: =H79 -> 0 | O79: =I79 -> 0
D80: ='財務諸表（入力）'!D43 -> 関係会社株式 | E80: ='財務諸表（入力）'!E43 -> 0 | F80: ='財務諸表（入力）'!G43 -> 0 | G80: =F80-E80 -> 0 | H80: =IF(G80>1,SUM(G80:G80),0) -> 0 | I80: =IF(G80<1,SUM(G80:G80)*-1,0) -> 0 | L80: =H80 -> 0 | M80: =I80 -> 0
D81: ='財務諸表（入力）'!D46 -> 長期前払費用 | E81: ='財務諸表（入力）'!E46 -> 0 | F81: ='財務諸表（入力）'!G46 -> 0 | G81: =F81-E81 -> 0 | H81: =IF(G81>1,SUM(G81:G81),0) -> 0 | I81: =IF(G81<1,SUM(G81:G81)*-1,0) -> 0 | L81: =H81 -> 0 | M81: =I81 -> 0
C82: 投資等小計 | E82: =SUM(E74:E81) -> 0 | F82: =SUM(F74:F81) -> 0 | G82: =F82-E82 -> 0 | H82: =SUM(H74:H81) -> 0 | I82: =SUM(I74:I81) -> 0 | L82: - | M82: -
C83: ='財務諸表（入力）'!C48 -> 繰延資産 | E83: ='財務諸表（入力）'!E48 -> 0 | F83: ='財務諸表（入力）'!G48 -> 0 | G83: =F83-E83 -> 0 | H83: =IF(G83>1,SUM(G83:G83),0) -> 0 | I83: =IF(G83<1,SUM(G83:G83)*-1,0) -> 0 | L83: =H83 -> 0 | M83: =I83 -> 0
B84: ='財務諸表（入力）'!B49 -> 固定資産合計 | E84: =E72+E73+E82+E83 -> 0 | F84: =F72+F73+F82+F83 -> 0 | G84: =F84-E84 -> 0 | H84: =H72+H73+H82+H83 -> 0 | I84: =I72+I73+I82+I83 -> 0 | L84: - | M84: -
A85: ='財務諸表（入力）'!A50 -> 資産合計 | E85: =E63+E84 -> 0 | F85: =F63+F84 -> 0 | G85: =F85-E85 -> 0 | H85: =H63+H84 -> 0 | I85: =I63+I84 -> 0
A86: 負債の部 | B86: 流動負債 | D86: ='財務諸表（入力）'!D51 -> 支払手形 | E86: ='財務諸表（入力）'!E51 -> 0 | F86: ='財務諸表（入力）'!G51 -> 0 | G86: =F86-E86 -> 0 | H86: =IF(G86<1,SUM(G86:G86)*-1,0) -> 0 | I86: =IF(G86>1,SUM(G86:G86),0) -> 0 | N86: =H86 -> 0 | O86: =I86 -> 0
D87: ='財務諸表（入力）'!D52 -> 買掛金 | E87: ='財務諸表（入力）'!E52 -> 0 | F87: ='財務諸表（入力）'!G52 -> 0 | G87: =F87-E87 -> 0 | H87: =IF(G87<1,SUM(G87:G87)*-1,0) -> 0 | I87: =IF(G87>1,SUM(G87:G87),0) -> 0 | N87: =H87 -> 0 | O87: =I87 -> 0
D88: ='財務諸表（入力）'!D53 -> 短期借入金 | E88: ='財務諸表（入力）'!E53 -> 0 | F88: ='財務諸表（入力）'!G53 -> 0 | G88: =F88-E88 -> 0 | H88: =IF(G88<1,SUM(G88:G88)*-1,0) -> 0 | I88: =IF(G88>1,SUM(G88:G88),0) -> 0 | P88: =H88 -> 0 | Q88: =I88 -> 0
D89: ='財務諸表（入力）'!D54 -> 未払金 | E89: ='財務諸表（入力）'!E54 -> 0 | F89: ='財務諸表（入力）'!G54 -> 0 | G89: =F89-E89 -> 0 | H89: =IF(G89<1,SUM(G89:G89)*-1,0) -> 0 | I89: =IF(G89>1,SUM(G89:G89),0) -> 0 | N89: =H89 -> 0 | O89: =I89 -> 0
D90: ='財務諸表（入力）'!D55 -> 未払費用 | E90: ='財務諸表（入力）'!E55 -> 0 | F90: ='財務諸表（入力）'!G55 -> 0 | G90: =F90-E90 -> 0 | H90: =IF(G90<1,SUM(G90:G90)*-1,0) -> 0 | I90: =IF(G90>1,SUM(G90:G90),0) -> 0 | N90: =H90 -> 0 | O90: =I90 -> 0
D91: ='財務諸表（入力）'!D57 -> 預り金 | E91: ='財務諸表（入力）'!E57 -> 0 | F91: ='財務諸表（入力）'!G57 -> 0 | G91: =F91-E91 -> 0 | H91: =IF(G91<1,SUM(G91:G91)*-1,0) -> 0 | I91: =IF(G91>1,SUM(G91:G91),0) -> 0 | N91: =H91 -> 0 | O91: =I91 -> 0
D92: ='財務諸表（入力）'!D58 -> 未払法人税等 | E92: ='財務諸表（入力）'!E58 -> 0 | F92: ='財務諸表（入力）'!G58 -> 0 | G92: =F92-E92 -> 0 | H92: =IF(G92<1,SUM(G92:G92)*-1,0) -> 0 | I92: =IF(G92>1,SUM(G92:G92),0) -> 0 | J92: =I92 -> 0 | K92: =H92 -> 0 | N92: - | O92: -
D93: ='財務諸表（入力）'!D59 -> 未払消費税 | E93: ='財務諸表（入力）'!E59 -> 0 | F93: ='財務諸表（入力）'!G59 -> 0 | G93: =F93-E93 -> 0 | H93: =IF(G93<1,SUM(G93:G93)*-1,0) -> 0 | I93: =IF(G93>1,SUM(G93:G93),0) -> 0 | N93: =H93 -> 0 | O93: =I93 -> 0
D94: ='財務諸表（入力）'!D56 -> 前受金 | E94: ='財務諸表（入力）'!E56 -> 0 | F94: ='財務諸表（入力）'!G56 -> 0 | G94: =F94-E94 -> 0 | H94: =IF(G94<1,SUM(G94:G94)*-1,0) -> 0 | I94: =IF(G94>1,SUM(G94:G94),0) -> 0 | N94: =H94 -> 0 | O94: =I94 -> 0
D95: ='財務諸表（入力）'!D60 -> 預り保証金他 | E95: ='財務諸表（入力）'!E60 -> 0 | F95: ='財務諸表（入力）'!G60 -> 0 | G95: =F95-E95 -> 0 | H95: =IF(G95<1,SUM(G95:G95)*-1,0) -> 0 | I95: =IF(G95>1,SUM(G95:G95),0) -> 0 | N95: =H95 -> 0 | O95: =I95 -> 0
B96: ='財務諸表（入力）'!B61 -> 流動負債合計 | E96: =SUM(E86:E95) -> 0 | F96: =SUM(F86:F95) -> 0 | G96: =F96-E96 -> 0 | H96: =SUM(H86:H95) -> 0 | I96: =SUM(I86:I95) -> 0 | N96: - | O96: -
B97: 固定負債 | D97: ='財務諸表（入力）'!D62 -> 長期借入金 | E97: ='財務諸表（入力）'!E62 -> 0 | F97: ='財務諸表（入力）'!G62 -> 0 | G97: =F97-E97 -> 0 | H97: =IF(G97<1,SUM(G97:G97)*-1,0) -> 0 | I97: =IF(G97>1,SUM(G97:G97),0) -> 0 | L97: =H97 -> 0 | M97: =I97 -> 0
D98: ='財務諸表（入力）'!D64 -> 設備支払手形 | E98: ='財務諸表（入力）'!E64 -> 0 | F98: ='財務諸表（入力）'!G64 -> 0 | G98: =F98-E98 -> 0 | H98: =IF(G98<1,SUM(G98:G98)*-1,0) -> 0 | I98: =IF(G98>1,SUM(G98:G98),0) -> 0 | L98: =H98 -> 0 | M98: =I98 -> 0
D99: ='財務諸表（入力）'!D65 -> リース債務 | E99: ='財務諸表（入力）'!E65 -> 0 | F99: ='財務諸表（入力）'!G65 -> 0 | G99: =F99-E99 -> 0 | H99: =IF(G99<1,SUM(G99:G99)*-1,0) -> 0 | I99: =IF(G99>1,SUM(G99:G99),0) -> 0 | L99: =H99 -> 0 | M99: =I99 -> 0
D100: ='財務諸表（入力）'!D66 -> 0 | E100: ='財務諸表（入力）'!E66 -> 0 | F100: ='財務諸表（入力）'!G66 -> 0 | G100: =F100-E100 -> 0 | H100: =IF(G100<1,SUM(G100:G100)*-1,0) -> 0 | I100: =IF(G100>1,SUM(G100:G100),0) -> 0 | L100: =H100 -> 0 | M100: =I100 -> 0
D101: ='財務諸表（入力）'!D63 -> 社債 | E101: ='財務諸表（入力）'!E63 -> 0 | F101: ='財務諸表（入力）'!G63 -> 0 | G101: =F101-E101 -> 0 | H101: =IF(G101<1,SUM(G101:G101)*-1,0) -> 0 | I101: =IF(G101>1,SUM(G101:G101),0) -> 0 | L101: =H101 -> 0 | M101: =I101 -> 0
D102: ='財務諸表（入力）'!D67 -> 0 | E102: ='財務諸表（入力）'!E67 -> 0 | F102: ='財務諸表（入力）'!G67 -> 0 | G102: =F102-E102 -> 0 | H102: =IF(G102<1,SUM(G102:G102)*-1,0) -> 0 | I102: =IF(G102>1,SUM(G102:G102),0) -> 0 | L102: =H102 -> 0 | M102: =I102 -> 0
D103: ='財務諸表（入力）'!D68 -> 0 | E103: ='財務諸表（入力）'!E68 -> 0 | F103: ='財務諸表（入力）'!G68 -> 0 | G103: =F103-E103 -> 0 | H103: =IF(G103<1,SUM(G103:G103)*-1,0) -> 0 | I103: =IF(G103>1,SUM(G103:G103),0) -> 0 | L103: =H103 -> 0 | M103: =I103 -> 0
B104: ='財務諸表（入力）'!B69 -> 固定負債合計 | E104: =SUM(E97:E103) -> 0 | F104: =SUM(F97:F103) -> 0 | G104: =F104-E104 -> 0 | H104: =SUM(H97:H103) -> 0 | I104: =SUM(I97:I103) -> 0 | L104: - | M104: -
A105: ='財務諸表（入力）'!A70 -> 負債合計 | E105: =E96+E104 -> 0 | F105: =F96+F104 -> 0 | G105: =F105-E105 -> 0 | H105: =H96+H104 -> 0 | I105: =I96+I104 -> 0
...

Sheet 資金移動表
A1: ='財務諸表（入力）'!D1 -> 0
A3: ■ 資金移動表分析
A5: ='財務諸表（入力）'!G5 -> 前期 | I5: ='財務諸表（入力）'!J5 -> 今期
A7: 経常収支 | B7: 支出 | E7: 収入 | I7: 経常収支 | J7: 支出 | M7: 収入
B8: 当期売上原価 | C8: の支出 | D8: ='財務諸表（入力）'!G136 -> 0 | E8: 当期売上高 | F8: の収入 | G8: ='財務諸表（入力）'!G129 -> 0 | J8: 当期売上原価 | K8: の支出 | L8: ='財務諸表（入力）'!J136 -> 0 | M8: 当期売上高 | N8: の収入 | O8: ='財務諸表（入力）'!J129 -> 0
B9: 棚卸資産小計 | C9: の増加 | D9: ='財務諸表（入力）'!M16 -> 0 | E9: ='財務諸表（入力）'!D54 -> 未払金 | F9: の増加 | G9: ='財務諸表（入力）'!M54 -> 0 | J9: 棚卸資産小計 | K9: の増加 | L9: ='財務諸表（入力）'!N16 -> 0 | M9: ='財務諸表（入力）'!D54 -> 未払金 | N9: の増加 | O9: ='財務諸表（入力）'!N54 -> 0
B10: ='財務諸表（入力）'!D17 -> 0 | C10: の増加 | D10: ='財務諸表（入力）'!M17 -> 0 | E10: ='財務諸表（入力）'!D55 -> 未払費用 | F10: の増加 | G10: ='財務諸表（入力）'!M55 -> 0 | J10: ='財務諸表（入力）'!D17 -> 0 | K10: の増加 | L10: ='財務諸表（入力）'!N17 -> 0 | M10: ='財務諸表（入力）'!D55 -> 未払費用 | N10: の増加 | O10: ='財務諸表（入力）'!N55 -> 0
B11: ='財務諸表（入力）'!D18 -> 0 | C11: の増加 | D11: ='財務諸表（入力）'!M18 -> 0 | E11: ='財務諸表（入力）'!D56 -> 前受金 | F11: の増加 | G11: ='財務諸表（入力）'!M56 -> 0 | J11: ='財務諸表（入力）'!D18 -> 0 | K11: の増加 | L11: ='財務諸表（入力）'!N18 -> 0 | M11: ='財務諸表（入力）'!D56 -> 前受金 | N11: の増加 | O11: ='財務諸表（入力）'!N56 -> 0
B12: ='財務諸表（入力）'!D19 -> 0 | C12: の増加 | D12: ='財務諸表（入力）'!M19 -> 0 | E12: ='財務諸表（入力）'!D57 -> 預り金 | F12: の増加 | G12: ='財務諸表（入力）'!M57 -> 0 | J12: ='財務諸表（入力）'!D19 -> 0 | K12: の増加 | L12: ='財務諸表（入力）'!N19 -> 0 | M12: ='財務諸表（入力）'!D57 -> 預り金 | N12: の増加 | O12: ='財務諸表（入力）'!N57 -> 0
B13: ='財務諸表（入力）'!D20 -> 0 | C13: の増加 | D13: ='財務諸表（入力）'!M20 -> 0 | E13: ='財務諸表（入力）'!D60 -> 預り保証金他 | F13: の増加 | G13: ='財務諸表（入力）'!M60 -> 0 | J13: ='財務諸表（入力）'!D20 -> 0 | K13: の増加 | L13: ='財務諸表（入力）'!N20 -> 0 | M13: ='財務諸表（入力）'!D60 -> 預り保証金他 | N13: の増加 | O13: ='財務諸表（入力）'!N60 -> 0
B14: ='財務諸表（入力）'!D21 -> 0 | C14: の増加 | D14: ='財務諸表（入力）'!M21 -> 0 | J14: ='財務諸表（入力）'!D21 -> 0 | K14: の増加 | L14: ='財務諸表（入力）'!N21 -> 0
B15: ='財務諸表（入力）'!D22 -> 0 | C15: の増加 | D15: ='財務諸表（入力）'!M22 -> 0 | E15: 貸倒引当金 | F15: の増加 | G15: =('財務諸表（入力）'!M25+'財務諸表（入力）'!M45)*-1 -> 0 | J15: ='財務諸表（入力）'!D22 -> 0 | K15: の増加 | L15: ='財務諸表（入力）'!N22 -> 0 | M15: 貸倒引当金 | N15: の増加 | O15: =('財務諸表（入力）'!N25+'財務諸表（入力）'!N45)*-1 -> 0
B16: ='財務諸表（入力）'!D23 -> 0 | C16: の増加 | D16: ='財務諸表（入力）'!M23 -> 0 | J16: ='財務諸表（入力）'!D23 -> 0 | K16: の増加 | L16: ='財務諸表（入力）'!N23 -> 0
B17: ='財務諸表（入力）'!D24 -> 0 | C17: の増加 | D17: ='財務諸表（入力）'!M24 -> 0 | E17: 売上債権 | F17: の減少 | G17: =('財務諸表（入力）'!M9+'財務諸表（入力）'!M8+'財務諸表（入力）'!M83+'財務諸表（入力）'!M84)*-1 -> 0 | J17: ='財務諸表（入力）'!D24 -> 0 | K17: の増加 | L17: ='財務諸表（入力）'!N24 -> 0 | M17: 売上債権 | N17: の減少 | O17: =('財務諸表（入力）'!N9+'財務諸表（入力）'!N8+'財務諸表（入力）'!N83+'財務諸表（入力）'!N84)*-1 -> 0
B18: ='財務諸表（入力）'!D26 -> 0 | C18: の増加 | D18: ='財務諸表（入力）'!M26 -> 0 | J18: ='財務諸表（入力）'!D26 -> 0 | K18: の増加 | L18: ='財務諸表（入力）'!N26 -> 0
B19: ='財務諸表（入力）'!D10 -> 0 | C19: の増加 | D19: ='財務諸表（入力）'!M10 -> 0 | J19: ='財務諸表（入力）'!D10 -> 0 | K19: の増加 | L19: ='財務諸表（入力）'!N10 -> 0
B20: 販売管理費 | C20: の支出 | D20: ='財務諸表（入力）'!G156 -> 0 | J20: 販売管理費 | K20: の支出 | L20: ='財務諸表（入力）'!J156 -> 0
B21: 買入債務 | C21: の減少 | D21: =('財務諸表（入力）'!M51+'財務諸表（入力）'!M52)*-1 -> 0 | J21: 買入債務 | K21: の減少 | L21: =('財務諸表（入力）'!N51+'財務諸表（入力）'!N52)*-1 -> 0
B22: 減価償却費 | C22: の支出（▲要因） | D22: =('財務諸表（入力）'!G102+'財務諸表（入力）'!G142)*-1 -> 0 | J22: 減価償却費 | K22: の支出（▲要因） | L22: =('財務諸表（入力）'!J102+'財務諸表（入力）'!J142)*-1 -> 0
B23: 営業支出計 | D23: =SUM(D8:D20)+D21+D22 -> 0 | E23: 営業収入計 | G23: =SUM(G8:G15)+G17 -> 0 | J23: 営業支出計 | L23: =SUM(L8:L20)+L21+L22 -> 0 | M23: 営業収入計 | O23: =SUM(O8:O15)+O17 -> 0
B24: 支払利息割引料 | C24: の支出 | D24: ='財務諸表（入力）'!G163 -> 0 | E24: 営業外収益 | F24: の収入 | G24: ='財務諸表（入力）'!G162 -> 0 | J24: 支払利息割引料 | K24: の支出 | L24: ='財務諸表（入力）'!J163 -> 0 | M24: 営業外収益 | N24: の収入 | O24: ='財務諸表（入力）'!J162 -> 0
B25: ='財務諸表（入力）'!D164 -> その他 | C25: の支出 | D25: ='財務諸表（入力）'!G164 -> 0 | J25: ='財務諸表（入力）'!D164 -> その他 | K25: の支出 | L25: ='財務諸表（入力）'!J164 -> 0
B26: 営業外支出計 | D26: =SUM(D24:D25) -> 0 | E26: 営業外収入計 | G26: =SUM(G24:G25) -> 0 | J26: 営業外支出計 | L26: =SUM(L24:L25) -> 0 | M26: 営業外収入計 | O26: =SUM(O24:O25) -> 0
B27: 経常支出計 | D27: =D23+D26 -> 0 | E27: 経常収入計 | G27: =G23+G26 -> 0 | J27: 経常支出計 | L27: =L23+L26 -> 0 | M27: 経常収入計 | O27: =O23+O26 -> 0
B28: 経常収入超過 | D28: =IF(D23+D26-G23-G26<0,G23+G26-D23-D26,0) -> 0 | E28: 経常支出の超過 | G28: =IF(D23+D26-G23-G26>0,D23+D26-G23-G26,0) -> 0 | J28: 経常収入超過 | L28: =IF(L23+L26-O23-O26<0,O23+O26-L23-L26,0) -> 0 | M28: 経常支出の超過 | O28: =IF(L23+L26-O23-O26>0,L23+L26-O23-O26,0) -> 0
B29: 合計 | D29: =D23+D26+D28 -> 0 | E29: 合計 | G29: =G23+G26+G28 -> 0 | J29: 合計 | L29: =L23+L26+L28 -> 0 | M29: 合計 | O29: =O23+O26+O28 -> 0
E30: 照合（０でOK) | G30: =G29-D29 -> 0 | M30: 照合（０でOK) | O30: =O29-L29 -> 0
D32: 経常収支比率 （経常収入÷経常支出） | G32: =G27/D27 -> #DIV/0! | L32: 経常収支比率 （経常収入÷経常支出） | O32: =O27/L27 -> #DIV/0!
A34: 固定収支 | B34: 支出 | E34: 収入 | I34: 固定収支 | J34: 支出 | M34: 収入
B35: 配当金 | C35: の支出 | D35: ='財務諸表（入力）'!G173 -> 0 | E35: 特別利益 | F35: の収入 | G35: ='財務諸表（入力）'!G167 -> 0 | J35: 配当金 | K35: の支出 | L35: ='財務諸表（入力）'!J173 -> 0 | M35: 特別利益 | N35: の収入 | O35: ='財務諸表（入力）'!J167 -> 0
B36: 役員賞与 | C36: の支出 | D36: ='財務諸表（入力）'!G174 -> 0 | E36: 増資 | F36: の収入 | G36: =資金運用表!I9 -> 0 | J36: 役員賞与 | K36: の支出 | L36: ='財務諸表（入力）'!J174 -> 0 | M36: 増資 | N36: の収入 | O36: =資金運用表!I137 -> 0
B37: 利益処分支出計 | D37: =SUM(D35:D36) -> 0 | E37: ='財務諸表（入力）'!D65 -> リース債務 | F37: の増加 | G37: ='財務諸表（入力）'!M65 -> 0 | J37: 利益処分支出計 | L37: =SUM(L35:L36) -> 0 | M37: ='財務諸表（入力）'!D65 -> リース債務 | N37: の増加 | O37: ='財務諸表（入力）'!N65 -> 0
B38: 法人税等 | C38: の支出 | D38: ='財務諸表（入力）'!G170 -> 0 | E38: ='財務諸表（入力）'!D66 -> 0 | F38: の増加 | G38: ='財務諸表（入力）'!M66 -> 0 | J38: 法人税等 | K38: の支出 | L38: ='財務諸表（入力）'!J170 -> 0 | M38: ='財務諸表（入力）'!D66 -> 0 | N38: の増加 | O38: ='財務諸表（入力）'!N66 -> 0
B39: 未払法人税等 | C39: の減少 | D39: ='財務諸表（入力）'!M58 -> 0 | E39: ='財務諸表（入力）'!D67 -> 0 | F39: の増加 | G39: ='財務諸表（入力）'!M67 -> 0 | J39: 未払法人税等 | K39: の減少 | L39: ='財務諸表（入力）'!N58 -> 0 | M39: ='財務諸表（入力）'!D67 -> 0 | N39: の増加 | O39: ='財務諸表（入力）'!N67 -> 0
B40: 未払消費税 | C40: の減少 | D40: ='財務諸表（入力）'!M59 -> 0 | E40: ='財務諸表（入力）'!D68 -> 0 | F40: の増加 | G40: ='財務諸表（入力）'!M68 -> 0 | J40: 未払消費税 | K40: の減少 | L40: ='財務諸表（入力）'!N59 -> 0 | M40: ='財務諸表（入力）'!D68 -> 0 | N40: の増加 | O40: ='財務諸表（入力）'!N68 -> 0
B41: 税金支出計 | D41: =D38-D39-D40 -> 0 | E41: 特別収入 | G41: =SUM(G35:G40) -> 0 | J41: 税金支出計 | L41: =L38-L39-L40 -> 0 | M41: 特別収入 | O41: =SUM(O35:O40) -> 0
B42: 有形固定資産 | C42: の増加 | D42: ='財務諸表（入力）'!M37+'財務諸表（入力）'!G182 -> 0 | J42: 有形固定資産 | K42: の増加 | L42: ='財務諸表（入力）'!N37+'財務諸表（入力）'!J182 -> 0
B43: 投資等 | C43: の増加 | D43: =SUM('財務諸表（入力）'!M39:M44)+'財務諸表（入力）'!M46 -> 0 | J43: 投資等 | K43: の増加 | L43: =SUM('財務諸表（入力）'!N39:N44)+'財務諸表（入力）'!N46 -> 0
B44: 無形固定資産 | C44: の増加 | D44: ='財務諸表（入力）'!M38 -> 0 | J44: 無形固定資産 | K44: の増加 | L44: ='財務諸表（入力）'!N38 -> 0
B45: 繰延資産 | C45: の増加 | D45: ='財務諸表（入力）'!M48 -> 0 | J45: 繰延資産 | K45: の増加 | L45: ='財務諸表（入力）'!N48 -> 0
B46: 固定資産支出計 | D46: =SUM(D42:D45) -> 0 | J46: 固定資産支出計 | L46: =SUM(L42:L45) -> 0
B47: 特別損失 | C47: の支出 | D47: ='財務諸表（入力）'!G168 -> 0 | J47: 特別損失 | K47: の支出 | L47: ='財務諸表（入力）'!J168 -> 0
B48: 特別支出計 | D48: =D47 -> 0 | J48: 特別支出計 | L48: =L47 -> 0
B49: 固定支出計 | D49: =D37+D41+D46+D48 -> 0 | E49: 固定収入計 | G49: =G41 -> 0 | J49: 固定支出計 | L49: =L37+L41+L46+L48 -> 0 | M49: 固定収入計 | O49: =O41 -> 0
B50: 固定収入超過 | D50: =IF(D37+D41+D46+D48-G41<0,G41-D37-D41-D46-D48,0) -> 0 | E50: 固定支出超過 | G50: =IF(D37+D41+D46+D48-G41>0,D37+D41+D46+D48-G41,0) -> 0 | J50: 固定収入超過 | L50: =IF(L37+L41+L46+L48-O41<0,O41-L37-L41-L46-L48,0) -> 0 | M50: 固定支出超過 | O50: =IF(L37+L41+L46+L48-O41>0,L37+L41+L46+L48-O41,0) -> 0
B51: 合計 | D51: =D37+D41+D46+D48+D50 -> 0 | E51: 合計 | G51: =G41+G50 -> 0 | J51: 合計 | L51: =L37+L41+L46+L48+L50 -> 0 | M51: 合計 | O51: =O41+O50 -> 0
E52: 照合（０でOK) | G52: =G51-D51 -> 0 | M52: 照合（０でOK) | O52: =O51-L51 -> 0
A54: 財務収支 | B54: 支出 | E54: 収入 | I54: 財務収支 | J54: 支出 | M54: 収入
B55: 経常支出 | C55: の超過 | D55: =G28 -> 0 | E55: 経常収入 | F55: の超過 | G55: =D28 -> 0 | J55: 経常支出 | K55: の超過 | L55: =O28 -> 0 | M55: 経常収入 | N55: の超過 | O55: =L28 -> 0
B56: 固定支出 | C56: の超過 | D56: =G50 -> 0 | E56: 固定収入 | F56: の超過 | G56: =D50 -> 0 | J56: 固定支出 | K56: の超過 | L56: =O50 -> 0 | M56: 固定収入 | N56: の超過 | O56: =L50 -> 0
B57: 長期借入金・社債 | C57: の減少 | D57: =IF('財務諸表（入力）'!M62+'財務諸表（入力）'!M63<0,('財務諸表（入力）'!M62+'財務諸表（入力）'!M63)*-1,0) -> 0 | E57: 長期借入金・社債 | F57: の増加 | G57: =IF('財務諸表（入力）'!M62+'財務諸表（入力）'!M63>0,('財務諸表（入力）'!M62+'財務諸表（入力）'!M63),0) -> 0 | J57: 長期借入金・社債 | K57: の減少 | L57: =IF('財務諸表（入力）'!N62+'財務諸表（入力）'!N63<0,('財務諸表（入力）'!N62+'財務諸表（入力）'!N63)*-1,0) -> 0 | M57: 長期借入金・社債 | N57: の増加 | O57: =IF('財務諸表（入力）'!N62+'財務諸表（入力）'!N63>0,('財務諸表（入力）'!N62+'財務諸表（入力）'!N63),0) -> 0
B58: 短期借入金 | C58: の減少 | D58: =IF('財務諸表（入力）'!M53<0,'財務諸表（入力）'!M53*-1,0) -> 0 | E58: 短期借入金 | F58: の増加 | G58: =IF('財務諸表（入力）'!M53>0,'財務諸表（入力）'!M53,0) -> 0 | J58: 短期借入金 | K58: の減少 | L58: =IF('財務諸表（入力）'!N53<0,'財務諸表（入力）'!N53*-1,0) -> 0 | M58: 短期借入金 | N58: の増加 | O58: =IF('財務諸表（入力）'!N53>0,'財務諸表（入力）'!N53,0) -> 0
B59: 割引・裏書手形 | C59: の減少 | D59: =IF('財務諸表（入力）'!M83+'財務諸表（入力）'!M84<0,('財務諸表（入力）'!M83+'財務諸表（入力）'!M84)*-1,0) -> 0 | E59: 割引・裏書手形 | F59: の増加 | G59: =IF('財務諸表（入力）'!M83+'財務諸表（入力）'!M84>0,'財務諸表（入力）'!M83+'財務諸表（入力）'!M84,0) -> 0 | J59: 割引・裏書手形 | K59: の減少 | L59: =IF('財務諸表（入力）'!N83+'財務諸表（入力）'!N84<0,('財務諸表（入力）'!N83+'財務諸表（入力）'!N84)*-1,0) -> 0 | M59: 割引・裏書手形 | N59: の増加 | O59: =IF('財務諸表（入力）'!N83+'財務諸表（入力）'!N84>0,'財務諸表（入力）'!N83+'財務諸表（入力）'!N84,0) -> 0
B60: 設備支払手形 | C60: の減少 | D60: =IF('財務諸表（入力）'!M64<0,'財務諸表（入力）'!M64*-1,0) -> 0 | E60: 設備支払手形 | F60: の増加 | G60: =IF('財務諸表（入力）'!M64>0,'財務諸表（入力）'!M64,0) -> 0 | J60: 設備支払手形 | K60: の減少 | L60: =IF('財務諸表（入力）'!N64<0,'財務諸表（入力）'!N64*-1,0) -> 0 | M60: 設備支払手形 | N60: の増加 | O60: =IF('財務諸表（入力）'!N64>0,'財務諸表（入力）'!N64,0) -> 0
B61: 現金・預金 | C61: の増加 | D61: =IF('財務諸表（入力）'!M6>0,'財務諸表（入力）'!M6,0) -> 0 | E61: 現金・預金 | F61: の減少 | G61: =IF('財務諸表（入力）'!M6<0,'財務諸表（入力）'!M6*-1,0) -> 0 | J61: 現金・預金 | K61: の増加 | L61: =IF('財務諸表（入力）'!N6>0,'財務諸表（入力）'!N6,0) -> 0 | M61: 現金・預金 | N61: の減少 | O61: =IF('財務諸表（入力）'!N6<0,'財務諸表（入力）'!N6*-1,0) -> 0
B62: 合計 | D62: =SUM(D55:D61) -> 0 | E62: 合計 | G62: =SUM(G55:G61) -> 0 | J62: 合計 | L62: =SUM(L55:L61) -> 0 | M62: 合計 | O62: =SUM(O55:O61) -> 0
E63: 照合（０でOK) | G63: =G62-D62 -> 0 | M63: 照合（０でOK) | O63: =O62-L62 -> 0
B65: 【現預金増減との検証】 | E65: 【各収支の内訳】 | J65: 【現預金増減との検証】 | M65: 【各収支の内訳】
B66: 前期現預金残高 | C66: ='財務諸表（入力）'!E6 -> 0 | E66: 経常収支 | F66: =(G23+G26)-(D23+D26) -> 0 | J66: 前期現預金残高 | K66: ='財務諸表（入力）'!G6 -> 0 | M66: 経常収支 | N66: =(O23+O26)-(L23+L26) -> 0
B67: 収入合計 | C67: =G23+G26+G41+G57+G58+G59+G60 -> 0 | E67: 固定収支 | F67: =G41-D37-D41-D46-D48 -> 0 | J67: 収入合計 | K67: =O23+O26+O41+O57+O58+O59+O60 -> 0 | M67: 固定収支 | N67: =O41-L37-L41-L46-L48 -> 0
B68: 支出合計 | C68: =D23+D26+D37+D41+D46+D48+D57+D58+D59+D60 -> 0 | E68: 財務収支 | F68: =(G57+G58+G59+G60)-(D57+D58+D59+D60) -> 0 | J68: 支出合計 | K68: =L23+L26+L37+L41+L46+L48+L57+L58+L59+L60 -> 0 | M68: 財務収支 | N68: =(O57+O58+O59+O60)-(L57+L58+L59+L60) -> 0
B69: 収支差額 | C69: =C67-C68 -> 0 | F69: =SUM(F66:F68) -> 0 | J69: 収支差額 | K69: =K67-K68 -> 0 | N69: =SUM(N66:N68) -> 0
B70: 期末現預金残高 | C70: =C66+C69 -> 0 | J70: 期末現預金残高 | K70: =K66+K69 -> 0
B72: 当期BS現預金残 | C72: =資金運用表!F42 -> 0 | J72: 当期BS現預金残 | K72: ='財務諸表（入力）'!J6 -> 0
B73: 照合（０でOK） | C73: =C70-C72 -> 0 | J73: 照合（０でOK） | K73: =K70-K72 -> 0
B82: 【コメント】 | J82: 【コメント】

Sheet 変動PL＆BEP
A1: ■ 変動ＰＬによる将来シミュレーション
P2: 単位：千円
E3: 直近期実績 | G3: 計画
G4: 計画1期 | I4: 計画2期 | K4: 計画3期 | M4: 計画4期 | O4: 計画5期
E5: ='財務諸表（入力）'!J4 -> 2022年2月1日～2023年1月31日 | F5: 売上比 | H5: 売上比 | J5: 売上比 | L5: 売上比 | N5: 売上比 | P5: 売上比
A6: 売上高 | E6: ='財務諸表（入力）'!J129 -> 0 | F6: =IF(E6=0,"",E6/E$6) | G6: =IF(E6="","",E6*(1+G51)) -> 0 | H6: =IF(G6="","",G6/G$6) -> #DIV/0! | I6: =IF(G6="","",G6*(1+I51)) -> 0 | J6: =IF(I6="","",I6/I$6) -> #DIV/0! | K6: =IF(I6="","",I6*(1+K51)) -> 0 | L6: =IF(K6="","",K6/K$6) -> #DIV/0! | M6: =IF(K6="","",K6*(1+M51)) -> 0 | N6: =IF(M6="","",M6/M$6) -> #DIV/0! | O6: =IF(M6="","",M6*(1+O51)) -> 0 | P6: =IF(O6="","",O6/O$6) -> #DIV/0!
A7: 変動費 | E7: =SUM(E8:E14) -> 0 | F7: =IF(E7=0,"",E7/E$6) | G7: =SUM(G8:G14) -> 0 | H7: =IF(G7=0,"",G7/G$6) | I7: =SUM(I8:I14) -> 0 | J7: =IF(I7=0,"",I7/I$6) | K7: =SUM(K8:K14) -> 0 | L7: =IF(K7=0,"",K7/K$6) | M7: =SUM(M8:M14) -> 0 | N7: =IF(M7=0,"",M7/M$6) | O7: =SUM(O8:O14) -> 0 | P7: =IF(O7=0,"",O7/O$6) | S7: =E5 -> 2022年2月1日～2023年1月31日 | T7: =G4 -> 計画1期 | U7: =I4 -> 計画2期 | V7: =K4 -> 計画3期 | W7: =M4 -> 計画4期 | X7: =O4 -> 計画5期
B8: 売上原価 | C8: 製造原価 | D8: 材料費 | E8: ='財務諸表（入力）'!J96 -> 0 | F8: =IF(E8=0,"",E8/E$6) | G8: =IF(E8=0,0,G$6*H8) -> 0 | H8: =H54 | I8: =IF(G8=0,0,I$6*J8) -> 0 | J8: =J54 | K8: =IF(I8=0,0,K$6*L8) -> 0 | L8: =L54 | M8: =IF(K8=0,0,M$6*N8) -> 0 | N8: =N54 | O8: =IF(M8=0,0,O$6*P8) -> 0 | P8: =P54 | R8: 売上高 | S8: =E6 -> 0 | T8: =G6 -> 0 | U8: =I6 -> 0 | V8: =K6 -> 0 | W8: =M6 -> 0 | X8: =O6 -> 0
D9: 変動労務費 | E9: =SUMIF('財務諸表（入力）'!C97:D100,"V",'財務諸表（入力）'!D97:D100) -> 0 | F9: =IF(E9=0,"",E9/E$6) | G9: =IF(E9=0,0,G6*H65) -> 0 | H9: =H65 | I9: =IF(G9=0,0,I6*J65) -> 0 | J9: =J65 | K9: =IF(I9=0,0,K6*L65) -> 0 | L9: =L65 | M9: =IF(K9=0,0,M6*N65) -> 0 | N9: =N65 | O9: =IF(M9=0,0,O6*P65) -> 0 | P9: =P65 | R9: 損益分岐点売上高 | S9: =E33 -> #VALUE! | T9: =G33 -> #VALUE! | U9: =I33 -> #VALUE! | V9: =K33 -> #VALUE! | W9: =M33 -> #VALUE! | X9: =O33 -> #VALUE!
D10: 外注費 | E10: ='財務諸表（入力）'!J103 -> 0 | F10: =IF(E10=0,"",E10/E$6) | G10: =IF(E10=0,0,G$6*H10) -> 0 | H10: =H55 | I10: =IF(G10=0,0,I$6*J10) -> 0 | J10: =J55 | K10: =IF(I10=0,0,K$6*L10) -> 0 | L10: =L55 | M10: =IF(K10=0,0,M$6*N10) -> 0 | N10: =N55 | O10: =IF(M10=0,0,O$6*P10) -> 0 | P10: =P55 | R10: 変動費 | S10: =E7 -> 0 | T10: =G7 -> 0 | U10: =I7 -> 0 | V10: =K7 -> 0 | W10: =M7 -> 0 | X10: =O7 -> 0
D11: 経費他 | E11: =SUMIF('財務諸表（入力）'!C104:C116,"V",'財務諸表（入力）'!J104:J116)-'財務諸表（入力）'!J121 -> 0 | F11: =IF(E11=0,"",E11/E$6) | G11: =IF(E11=0,0,G$6*H11) -> 0 | H11: =H56 | I11: =IF(G11=0,0,I$6*J11) -> 0 | J11: =J56 | K11: =IF(I11=0,0,K$6*L11) -> 0 | L11: =L56 | M11: =IF(K11=0,0,M$6*N11) -> 0 | N11: =N56 | O11: =IF(M11=0,0,O$6*P11) -> 0 | P11: =P56 | R11: 固定費 | S11: =E16 -> 0 | T11: =G16 -> 0 | U11: =I16 -> 0 | V11: =K16 -> 0 | W11: =M16 -> 0 | X11: =O16 -> 0
C12: 商品仕入 | E12: ='財務諸表（入力）'!J131 -> 0 | F12: =IF(E12=0,"",E12/E$6) | G12: =IF(E12=0,0,G$6*H12) -> 0 | H12: =H57 | I12: =IF(G12=0,0,I$6*J12) -> 0 | J12: =J57 | K12: =IF(I12=0,0,K$6*L12) -> 0 | L12: =L57 | M12: =IF(K12=0,0,M$6*N12) -> 0 | N12: =N57 | O12: =IF(M12=0,0,O$6*P12) -> 0 | P12: =P57 | R12: 限界利益率 | S12: =F15 | T12: =H15 | U12: =J15 | V12: =L15 | W12: =N15 | X12: =P15
C13: 棚卸資産増減 | E13: ='財務諸表（入力）'!J130-'財務諸表（入力）'!J134-'財務諸表（入力）'!J133+'財務諸表（入力）'!J118-'財務諸表（入力）'!J120-'財務諸表（入力）'!J121 -> 0 | F13: =IF(E13=0,"",E13/E$6) | G13: =E61-G61 -> 0 | H13: =IF(G13="","",G13/G$6) -> #DIV/0! | I13: =G61-I61 -> 0 | J13: =IF(I13="","",I13/I$6) -> #DIV/0! | K13: =I61-K61 -> 0 | L13: =IF(K13="","",K13/K$6) -> #DIV/0! | M13: =K61-M61 -> 0 | N13: =IF(M13="","",M13/M$6) -> #DIV/0! | O13: =M61-O61 -> 0 | P13: =IF(O13="","",O13/O$6) -> #DIV/0! | R13: 損益分岐点比率 | S13: =F33 -> #VALUE! | T13: =H33 -> #VALUE! | U13: =J33 -> #VALUE! | V13: =L33 -> #VALUE! | W13: =N33 -> #VALUE! | X13: =P33 -> #VALUE!
B14: 販売管理費 | E14: =SUMIF('財務諸表（入力）'!C144:C155,"V",'財務諸表（入力）'!J144:J155) -> 0 | F14: =IF(E14=0,"",E14/E$6) | G14: =IF(E14=0,0,G$6*H14) -> 0 | H14: =H58 | I14: =IF(G14=0,0,I$6*J14) -> 0 | J14: =J58 | K14: =IF(I14=0,0,K$6*L14) -> 0 | L14: =L58 | M14: =IF(K14=0,0,M$6*N14) -> 0 | N14: =N58 | O14: =IF(M14=0,0,O$6*P14) -> 0 | P14: =P58
A15: 限界利益 | E15: =E6-E7 -> 0 | F15: =IF(E15=0,"",E15/E$6) | G15: =G6-G7 -> 0 | H15: =IF(G15=0,"",G15/G$6) | I15: =I6-I7 -> 0 | J15: =IF(I15=0,"",I15/I$6) | K15: =K6-K7 -> 0 | L15: =IF(K15=0,"",K15/K$6) | M15: =M6-M7 -> 0 | N15: =IF(M15=0,"",M15/M$6) | O15: =O6-O7 -> 0 | P15: =IF(O15=0,"",O15/O$6)
A16: 固定費 | E16: =SUM(E17:E23) -> 0 | F16: =IF(E16=0,"",E16/E$6) | G16: =SUM(G17:G23) -> 0 | H16: =IF(G16=0,"",G16/G$6) | I16: =SUM(I17:I23) -> 0 | J16: =IF(I16=0,"",I16/I$6) | K16: =SUM(K17:K23) -> 0 | L16: =IF(K16=0,"",K16/K$6) | M16: =SUM(M17:M23) -> 0 | N16: =IF(M16=0,"",M16/M$6) | O16: =SUM(O17:O23) -> 0 | P16: =IF(O16=0,"",O16/O$6)
B17: 固定労務費 | E17: =SUMIF('財務諸表（入力）'!C97:C100,"F",'財務諸表（入力）'!J97:J100) -> 0 | F17: =IF(E17=0,"",E17/E$6) | G17: =E17+G67 -> 0 | H17: =IF(G17=0,"",G17/G$6) | I17: =G17+I67 -> 0 | J17: =IF(I17=0,"",I17/I$6) | K17: =I17+K67 -> 0 | L17: =IF(K17=0,"",K17/K$6) | M17: =K17+M67 -> 0 | N17: =IF(M17=0,"",M17/M$6) | O17: =M17+O67 -> 0 | P17: =IF(O17=0,"",O17/O$6)
B18: 減価償却費 | E18: ='財務諸表（入力）'!J102+'財務諸表（入力）'!J142 -> 0 | F18: =IF(E18=0,"",E18/E$6) | H18: =IF(G18=0,"",G18/G$6) | J18: =IF(I18=0,"",I18/I$6) | L18: =IF(K18=0,"",K18/K$6) | N18: =IF(M18=0,"",M18/M$6) | P18: =IF(O18=0,"",O18/O$6)
B19: 経費他 | E19: =SUMIF('財務諸表（入力）'!C104:C116,"F",'財務諸表（入力）'!J104:J116) -> 0 | F19: =IF(E19=0,"",E19/E$6) | G19: =E19+G71 -> 0 | H19: =IF(G19=0,"",G19/G$6) | I19: =G19+I71 -> 0 | J19: =IF(I19=0,"",I19/I$6) | K19: =I19+K71 -> 0 | L19: =IF(K19=0,"",K19/K$6) | M19: =K19+M71 -> 0 | N19: =IF(M19=0,"",M19/M$6) | O19: =M19+O71 -> 0 | P19: =IF(O19=0,"",O19/O$6)
B20: 販管人件費 | E20: =SUM('財務諸表（入力）'!J138:J141) -> 0 | F20: =IF(E20=0,"",E20/E$6) | G20: =E20+G68 -> 0 | H20: =IF(G20=0,"",G20/G$6) | I20: =G20+I68 -> 0 | J20: =IF(I20=0,"",I20/I$6) | K20: =I20+K68 -> 0 | L20: =IF(K20=0,"",K20/K$6) | M20: =K20+M68 -> 0 | N20: =IF(M20=0,"",M20/M$6) | O20: =M20+O68 -> 0 | P20: =IF(O20=0,"",O20/O$6)
B21: その他販管費 | E21: =SUMIF('財務諸表（入力）'!C144:C155,"F",'財務諸表（入力）'!J144:J155) -> 0 | F21: =IF(E21=0,"",E21/E$6) | G21: =E21+G72 -> 0 | H21: =IF(G21=0,"",G21/G$6) | I21: =G21+I72 -> 0 | J21: =IF(I21=0,"",I21/I$6) | K21: =I21+K72 -> 0 | L21: =IF(K21=0,"",K21/K$6) | M21: =K21+M72 -> 0 | N21: =IF(M21=0,"",M21/M$6) | O21: =M21+O72 -> 0 | P21: =IF(O21=0,"",O21/O$6)
B22: 営業外 | C22: 支払利息 | E22: ='財務諸表（入力）'!J163 -> 0 | F22: =IF(E22=0,"",E22/E$6) | H22: =IF(G22=0,"",G22/G$6) | J22: =IF(I22=0,"",I22/I$6) | L22: =IF(K22=0,"",K22/K$6) | N22: =IF(M22=0,"",M22/M$6) | P22: =IF(O22=0,"",O22/O$6)
C23: その他収支 | E23: ='財務諸表（入力）'!J164-'財務諸表（入力）'!J162 -> 0 | F23: =IF(E23=0,"",E23/E$6) | G23: =E23+G73 -> 0 | H23: =IF(G23=0,"",G23/G$6) | I23: =G23+I73 -> 0 | J23: =IF(I23=0,"",I23/I$6) | K23: =I23+K73 -> 0 | L23: =IF(K23=0,"",K23/K$6) | M23: =K23+M73 -> 0 | N23: =IF(M23=0,"",M23/M$6) | O23: =M23+O73 -> 0 | P23: =IF(O23=0,"",O23/O$6)
A24: 経常利益 | E24: =E15-E16 -> 0 | F24: =IF(E24=0,"",E24/E$6) | G24: =G15-G16 -> 0 | H24: =IF(G24=0,"",G24/G$6) | I24: =I15-I16 -> 0 | J24: =IF(I24=0,"",I24/I$6) | K24: =K15-K16 -> 0 | L24: =IF(K24=0,"",K24/K$6) | M24: =M15-M16 -> 0 | N24: =IF(M24=0,"",M24/M$6) | O24: =O15-O16 -> 0 | P24: =IF(O24=0,"",O24/O$6)
B25: 特別利益 | E25: ='財務諸表（入力）'!J167 -> 0 | F25: =IF(E25=0,"",E25/E$6) | H25: =IF(G25=0,"",G25/G$6) | J25: =IF(I25=0,"",I25/I$6) | L25: =IF(K25=0,"",K25/K$6) | N25: =IF(M25=0,"",M25/M$6) | P25: =IF(O25=0,"",O25/O$6)
B26: 特別損失 | E26: ='財務諸表（入力）'!J168 -> 0 | F26: =IF(E26=0,"",E26/E$6) | H26: =IF(G26=0,"",G26/G$6) | J26: =IF(I26=0,"",I26/I$6) | L26: =IF(K26=0,"",K26/K$6) | N26: =IF(M26=0,"",M26/M$6) | P26: =IF(O26=0,"",O26/O$6)
A27: 税引前利益 | E27: =E24+E25-E26 -> 0 | F27: =IF(E27=0,"",E27/E$6) | G27: =G24+G25-G26 -> 0 | H27: =IF(G27=0,"",G27/G$6) | I27: =I24+I25-I26 -> 0 | J27: =IF(I27=0,"",I27/I$6) | K27: =K24+K25-K26 -> 0 | L27: =IF(K27=0,"",K27/K$6) | M27: =M24+M25-M26 -> 0 | N27: =IF(M27=0,"",M27/M$6) | O27: =O24+O25-O26 -> 0 | P27: =IF(O27=0,"",O27/O$6)
B28: 法人税等 | E28: ='財務諸表（入力）'!J170 -> 0 | F28: =IF(E28=0,"",E28/E$6) | G28: =IF(G27<0,"0",G27*0.4-G29) -> 0 | H28: =IF(G28=0,"",G28/G$6) | I28: =IF(I27<0,"0",I27*0.4-I29) -> 0 | J28: =IF(I28=0,"",I28/I$6) | K28: =IF(K27<0,"0",K27*0.4-K29) -> 0 | L28: =IF(K28=0,"",K28/K$6) | M28: =IF(M27<0,"0",M27*0.4-M29) -> 0 | N28: =IF(M28=0,"",M28/M$6) | O28: =IF(O27<0,"0",O27*0.4-O29) -> 0 | P28: =IF(O28=0,"",O28/O$6)
B29: 法人税等調整額 | F29: =IF(E29=0,"",E29/E$6) | H29: =IF(G29=0,"",G29/G$6) | J29: =IF(I29=0,"",I29/I$6) | L29: =IF(K29=0,"",K29/K$6) | N29: =IF(M29=0,"",M29/M$6) | P29: =IF(O29=0,"",O29/O$6)
A30: 税引後利益 | E30: =E27-E28-E29 -> 0 | F30: =IF(E30=0,"",E30/E$6) | G30: =G27-G28-G29 -> 0 | H30: =IF(G30=0,"",G30/G$6) | I30: =I27-I28-I29 -> 0 | J30: =IF(I30=0,"",I30/I$6) | K30: =K27-K28-K29 -> 0 | L30: =IF(K30=0,"",K30/K$6) | M30: =M27-M28-M29 -> 0 | N30: =IF(M30=0,"",M30/M$6) | O30: =O27-O28-O29 -> 0 | P30: =IF(O30=0,"",O30/O$6)
A31: キャッシュフロー | E31: =E18+E30 -> 0 | F31: =IF(E31=0,"",E31/E$6) | G31: =G18+G30 -> 0 | H31: =IF(G31=0,"",G31/G$6) | I31: =I18+I30 -> 0 | J31: =IF(I31=0,"",I31/I$6) | K31: =K18+K30 -> 0 | L31: =IF(K31=0,"",K31/K$6) | M31: =M18+M30 -> 0 | N31: =IF(M31=0,"",M31/M$6) | O31: =O18+O30 -> 0 | P31: =IF(O31=0,"",O31/O$6)
A33: 損益分岐点売上高／比率 （経常利益ベース） | E33: =E16/F15 -> #VALUE! | F33: =E33/E6 -> #VALUE! | G33: =G16/H15 -> #VALUE! | H33: =G33/G6 -> #VALUE! | I33: =I16/J15 -> #VALUE! | J33: =I33/I6 -> #VALUE! | K33: =K16/L15 -> #VALUE! | L33: =K33/K6 -> #VALUE! | M33: =M16/N15 -> #VALUE! | N33: =M33/M6 -> #VALUE! | O33: =O16/P15 -> #VALUE! | P33: =O33/O6 -> #VALUE!
A35: 【限界利益率・損益分岐点比率の推移】
A48: ■ 入力項目
A50: 【売上予測】 | G50: (増減率）
A51: 売上高 | E51: =E6 -> 0 | F51: - | H51: - | J51: - | L51: - | N51: - | P51: -
A53: 【変動費率調整】 | G53: （増減率）
A54: 材料費 | E54: =E8 -> 0 | F54: =F8 | H54: =IF(G54="",F54,F54+G54) | J54: =IF(I54="",H54,H54+I54) | L54: =IF(K54="",J54,J54+K54) | N54: =IF(M54="",L54,L54+M54) | P54: =IF(O54="",N54,N54+O54)
A55: 外注費 | E55: =E10 -> 0 | F55: =F10 | H55: =IF(G55="",F55,F55+G55) | J55: =IF(I55="",H55,H55+I55) | L55: =IF(K55="",J55,J55+K55) | N55: =IF(M55="",L55,L55+M55) | P55: =IF(O55="",N55,N55+O55)
A56: 経費他 | E56: =E11 -> 0 | F56: =F11 | H56: =IF(G56="",F56,F56+G56) | J56: =IF(I56="",H56,H56+I56) | L56: =IF(K56="",J56,J56+K56) | N56: =IF(M56="",L56,L56+M56) | P56: =IF(O56="",N56,N56+O56)
A57: 商品仕入 | E57: =E12 -> 0 | F57: =F12 | H57: =IF(G57="",F57,F57+G57) | J57: =IF(I57="",H57,H57+I57) | L57: =IF(K57="",J57,J57+K57) | N57: =IF(M57="",L57,L57+M57) | P57: =IF(O57="",N57,N57+O57)
A58: 販売管理費 | E58: =E14 -> 0 | F58: =F14 | H58: =IF(G58="",F58,F58+G58) | J58: =IF(I58="",H58,H58+I58) | L58: =IF(K58="",J58,J58+K58) | N58: =IF(M58="",L58,L58+M58) | P58: =IF(O58="",N58,N58+O58)
A60: 【棚卸資産増減】 | G60: （回転月数）
A61: 棚卸資産残高 | E61: ='財務諸表（入力）'!J16 -> 0 | G61: =G6/12*G62 -> 0 | I61: =I6/12*I62 -> 0 | K61: =K6/12*K62 -> 0 | M61: =M6/12*M62 -> 0 | O61: =O6/12*O62 -> 0
A62: 棚卸資産回転期間（月） | E62: =E61/(E6/12) -> #DIV/0!
A64: 【労務費・人件費】 | G64: （増減率）
A65: 変動労務費 | E65: =E9 -> 0 | F65: =F9 | H65: =IF(G65="",F65,F65+G65) | J65: =IF(I65="",H65,H65+I65) | L65: =IF(K65="",J65,J65+K65) | N65: =IF(M65="",L65,L65+M65) | P65: =IF(O65="",N65,N65+O65)
G66: （増減金額）
A67: 固定労務費 | E67: =E17 -> 0 | F67: =F17 | H67: - | J67: - | L67: - | N67: - | P67: -
A68: 販管人件費 | E68: =E20 -> 0 | F68: =F20 | H68: - | J68: - | L68: - | N68: - | P68: -
A70: 【その他固定費】 | G70: （増減金額）
A71: 経費他 | E71: =E19 -> 0 | F71: =F19 | H71: - | J71: - | L71: - | N71: - | P71: -
A72: その他販管費 | E72: =E21 -> 0 | F72: =F21 | H72: - | J72: - | L72: - | N72: - | P72: -
A73: その他収支 | E73: =E23 -> 0 | F73: =F23 | H73: - | J73: - | L73: - | N73: - | P73: -

Sheet 【総合所見】
A3: 【財務分析結果のまとめ】
A5: １．収益面 （総資本利益率、売上利益率、資産回転期間（効率性）、損益分岐点分析等）
A15: ２．資金面 （運転資金分析、資金運用表＆移動表、長期借入返済能力等）
A25: ３．財務バランス、安全性等 （流動・固定のバランス、自己資本比率、債務償還年数等）
A35: ４．その他 （成長性、生産性、その他全般）
A45: ５．所見 （業界比での特徴、３期の推移傾向、長所・リスクの把握、課題（仮説）の検証等）

Sheet 部門別売上sim
A1: ='財務諸表（入力）'!D1 -> 0
A3: １．直近期の部門別売上・利益推定
E5: 直近期実績 | G5: 部門別売上構成 [上段：部門・商品等区分、中段：売上構成比、下段：人員概算] ← ヒアリングに基づき設定
E6: ='財務諸表（入力）'!J4 -> 2022年2月1日～2023年1月31日 | F6: 売上比 | H6: 売上比 | J6: 売上比 | L6: 売上比 | N6: 売上比 | P6: 売上比 | R6: 合計 | S6: 売上比
R7: =G7+I7+K7+M7+O7 -> 0
R8: =G8+I8+K8+M8+O8 -> 0
A9: 売上高 | E9: ='財務諸表（入力）'!J129 -> 0 | F9: =IF(E9=0,"",E9/E$9) | G9: =$E$9*G7 -> 0 | H9: =IF(G9=0,"",G9/G$9) | I9: =$E$9*I7 -> 0 | J9: =IF(I9=0,"",I9/I$9) | K9: =$E$9*K7 -> 0 | L9: =IF(K9=0,"",K9/K$9) | M9: =$E$9*M7 -> 0 | N9: =IF(M9=0,"",M9/M$9) | O9: =$E$9*O7 -> 0 | P9: =IF(O9=0,"",O9/O$9) | R9: =G9+I9+K9+M9+O9 -> 0 | S9: =IF(R9=0,"",R9/R$9)
A10: 売上原価 | B10: 変動費 | E10: ='財務諸表（入力）'!J96+SUMIF('財務諸表（入力）'!$C$97:$C$116,"V",'財務諸表（入力）'!$J$97:$J$116)+'財務諸表（入力）'!J122+'財務諸表（入力）'!J131+'財務諸表（入力）'!J135-'財務諸表（入力）'!$J121 -> 0 | F10: =IF(E10=0,"",E10/E$9) | G10: =G13-G11-G12 -> #DIV/0! | H10: =IF(G10=0,"",G10/G$9) -> #DIV/0! | I10: =I13-I11-I12 -> #DIV/0! | J10: =IF(I10=0,"",I10/I$9) -> #DIV/0! | K10: =K13-K11-K12 -> #DIV/0! | L10: =IF(K10=0,"",K10/K$9) -> #DIV/0! | M10: =M13-M11-M12 -> #DIV/0! | N10: =IF(M10=0,"",M10/M$9) -> #DIV/0! | O10: =O13-O11-O12 -> #DIV/0! | P10: =IF(O10=0,"",O10/O$9) -> #DIV/0! | R10: =G10+I10+K10+M10+O10 -> #DIV/0! | S10: =IF(R10=0,"",R10/R$9) -> #DIV/0!
B11: 固定費 | C11: 労務費 | E11: =SUMIF('財務諸表（入力）'!$C$97:$C$100,"F",'財務諸表（入力）'!$J$97:$J$100) -> 0 | F11: =IF(E11=0,"",E11/E$9) | G11: =$E11*G8/$R8 -> #DIV/0! | H11: =IF(G11=0,"",G11/G$9) -> #DIV/0! | I11: =$E11*I8/$R8 -> #DIV/0! | J11: =IF(I11=0,"",I11/I$9) -> #DIV/0! | K11: =$E11*K8/$R8 -> #DIV/0! | L11: =IF(K11=0,"",K11/K$9) -> #DIV/0! | M11: =$E11*M8/$R8 -> #DIV/0! | N11: =IF(M11=0,"",M11/M$9) -> #DIV/0! | O11: =$E11*O8/$R8 -> #DIV/0! | P11: =IF(O11=0,"",O11/O$9) -> #DIV/0! | R11: =G11+I11+K11+M11+O11 -> #DIV/0! | S11: =IF(R11=0,"",R11/R$9) -> #DIV/0!
C12: 経費 | E12: =SUMIF('財務諸表（入力）'!$C$102:$C$116,"F",'財務諸表（入力）'!$J$102:$J$116) -> 0 | F12: =IF(E12=0,"",E12/E$9) | G12: =$E12*G7 -> 0 | H12: =IF(G12=0,"",G12/G$9) | I12: =$E12*I7 -> 0 | J12: =IF(I12=0,"",I12/I$9) | K12: =$E12*K7 -> 0 | L12: =IF(K12=0,"",K12/K$9) | M12: =$E12*M7 -> 0 | N12: =IF(M12=0,"",M12/M$9) | O12: =$E12*O7 -> 0 | P12: =IF(O12=0,"",O12/O$9) | R12: =G12+I12+K12+M12+O12 -> 0 | S12: =IF(R12=0,"",R12/R$9)
A13: 合計 | E13: =E10+E11+E12 -> 0 | F13: =IF(E13=0,"",E13/E$9) | G13: =G9-G14 -> 0 | H13: =IF(G13=0,"",G13/G$9) | I13: =I9-I14 -> 0 | J13: =IF(I13=0,"",I13/I$9) | K13: =K9-K14 -> 0 | L13: =IF(K13=0,"",K13/K$9) | M13: =M9-M14 -> 0 | N13: =IF(M13=0,"",M13/M$9) | O13: =O9-O14 -> 0 | P13: =IF(O13=0,"",O13/O$9) | R13: =G13+I13+K13+M13+O13 -> 0 | S13: =IF(R13=0,"",R13/R$9) | T13: （差異）
A14: 売上総利益 | E14: =E9-E13 -> 0 | F14: =IF(E14=0,"",E14/E$9) | G14: =G9*H14 -> 0 | I14: =I9*J14 -> 0 | K14: =K9*L14 -> 0 | M14: =M9*N14 -> 0 | O14: =O9*P14 -> 0 | R14: =G14+I14+K14+M14+O14 -> 0 | S14: =IF(R14=0,"",R14/R$9) | T14: =R14-E14 -> 0 | U14: =S14-F14 -> #VALUE!
A15: 販管費 | B15: 変動費 | E15: =SUMIF('財務諸表（入力）'!$C$143:$C$155,"V",'財務諸表（入力）'!$J$143:$J$155) -> 0 | F15: =IF(E15=0,"",E15/E$9) | G15: =$E15*G$7 -> 0 | H15: =IF(G15=0,"",G15/G$9) | I15: =$E15*I$7 -> 0 | J15: =IF(I15=0,"",I15/I$9) | K15: =$E15*K$7 -> 0 | L15: =IF(K15=0,"",K15/K$9) | M15: =$E15*M$7 -> 0 | N15: =IF(M15=0,"",M15/M$9) | O15: =$E15*O$7 -> 0 | P15: =IF(O15=0,"",O15/O$9) | R15: =G15+I15+K15+M15+O15 -> 0 | S15: =IF(R15=0,"",R15/R$9)
B16: 固定費 | C16: 人件費 | E16: =SUM('財務諸表（入力）'!J138:J141) -> 0 | F16: =IF(E16=0,"",E16/E$9) | G16: =$E16*G8/$R8 -> #DIV/0! | H16: =IF(G16=0,"",G16/G$9) -> #DIV/0! | I16: =$E16*I8/$R8 -> #DIV/0! | J16: =IF(I16=0,"",I16/I$9) -> #DIV/0! | K16: =$E16*K8/$R8 -> #DIV/0! | L16: =IF(K16=0,"",K16/K$9) -> #DIV/0! | M16: =$E16*M8/$R8 -> #DIV/0! | N16: =IF(M16=0,"",M16/M$9) -> #DIV/0! | O16: =$E16*O8/$R8 -> #DIV/0! | P16: =IF(O16=0,"",O16/O$9) -> #DIV/0! | R16: =G16+I16+K16+M16+O16 -> #DIV/0! | S16: =IF(R16=0,"",R16/R$9) -> #DIV/0!
C17: 減価償却費 | E17: ='財務諸表（入力）'!J142 -> 0 | F17: =IF(E17=0,"",E17/E$9) | G17: =$E17*G$7 -> 0 | H17: =IF(G17=0,"",G17/G$9) | I17: =$E17*I$7 -> 0 | J17: =IF(I17=0,"",I17/I$9) | K17: =$E17*K$7 -> 0 | L17: =IF(K17=0,"",K17/K$9) | M17: =$E17*M$7 -> 0 | N17: =IF(M17=0,"",M17/M$9) | O17: =$E17*O$7 -> 0 | P17: =IF(O17=0,"",O17/O$9) | R17: =G17+I17+K17+M17+O17 -> 0 | S17: =IF(R17=0,"",R17/R$9)
C18: その他 | E18: =SUMIF('財務諸表（入力）'!$C$143:$C$155,"F",'財務諸表（入力）'!$J$143:$J$155) -> 0 | F18: =IF(E18=0,"",E18/E$9) | G18: =$E18*G$7 -> 0 | H18: =IF(G18=0,"",G18/G$9) | I18: =$E18*I$7 -> 0 | J18: =IF(I18=0,"",I18/I$9) | K18: =$E18*K$7 -> 0 | L18: =IF(K18=0,"",K18/K$9) | M18: =$E18*M$7 -> 0 | N18: =IF(M18=0,"",M18/M$9) | O18: =$E18*O$7 -> 0 | P18: =IF(O18=0,"",O18/O$9) | R18: =G18+I18+K18+M18+O18 -> 0 | S18: =IF(R18=0,"",R18/R$9)
D19: 合計 | E19: =E15+E16+E17+E18 -> 0 | F19: =IF(E19=0,"",E19/E$9) | G19: =G15+G16+G17+G18 -> #DIV/0! | H19: =IF(G19=0,"",G19/G$9) -> #DIV/0! | I19: =I15+I16+I17+I18 -> #DIV/0! | J19: =IF(I19=0,"",I19/I$9) -> #DIV/0! | K19: =K15+K16+K17+K18 -> #DIV/0! | L19: =IF(K19=0,"",K19/K$9) -> #DIV/0! | M19: =M15+M16+M17+M18 -> #DIV/0! | N19: =IF(M19=0,"",M19/M$9) -> #DIV/0! | O19: =O15+O16+O17+O18 -> #DIV/0! | P19: =IF(O19=0,"",O19/O$9) -> #DIV/0! | R19: =G19+I19+K19+M19+O19 -> #DIV/0! | S19: =IF(R19=0,"",R19/R$9) -> #DIV/0!
A20: 営業利益 | E20: =E14-E19 -> 0 | F20: =IF(E20=0,"",E20/E$9) | G20: =G14-G19 -> #DIV/0! | H20: =IF(G20=0,"",G20/G$9) -> #DIV/0! | I20: =I14-I19 -> #DIV/0! | J20: =IF(I20=0,"",I20/I$9) -> #DIV/0! | K20: =K14-K19 -> #DIV/0! | L20: =IF(K20=0,"",K20/K$9) -> #DIV/0! | M20: =M14-M19 -> #DIV/0! | N20: =IF(M20=0,"",M20/M$9) -> #DIV/0! | O20: =O14-O19 -> #DIV/0! | P20: =IF(O20=0,"",O20/O$9) -> #DIV/0! | R20: =G20+I20+K20+M20+O20 -> #DIV/0! | S20: =IF(R20=0,"",R20/R$9) -> #DIV/0!
A21: 営業外 | B21: 営業外収入 | E21: ='財務諸表（入力）'!J162 -> 0 | F21: =IF(E21=0,"",E21/E$9) | G21: =$E21*G$7 -> 0 | H21: =IF(G21=0,"",G21/G$9) | I21: =$E21*I$7 -> 0 | J21: =IF(I21=0,"",I21/I$9) | K21: =$E21*K$7 -> 0 | L21: =IF(K21=0,"",K21/K$9) | M21: =$E21*M$7 -> 0 | N21: =IF(M21=0,"",M21/M$9) | O21: =$E21*O$7 -> 0 | P21: =IF(O21=0,"",O21/O$9) | R21: =G21+I21+K21+M21+O21 -> 0 | S21: =IF(R21=0,"",R21/R$9)
B22: 営業外費用 | E22: ='財務諸表（入力）'!J165 -> 0 | F22: =IF(E22=0,"",E22/E$9) | G22: =$E22*G$7 -> 0 | H22: =IF(G22=0,"",G22/G$9) | I22: =$E22*I$7 -> 0 | J22: =IF(I22=0,"",I22/I$9) | K22: =$E22*K$7 -> 0 | L22: =IF(K22=0,"",K22/K$9) | M22: =$E22*M$7 -> 0 | N22: =IF(M22=0,"",M22/M$9) | O22: =$E22*O$7 -> 0 | P22: =IF(O22=0,"",O22/O$9) | R22: =G22+I22+K22+M22+O22 -> 0 | S22: =IF(R22=0,"",R22/R$9)
A23: 経常利益 | E23: =E20+E21-E22 -> 0 | F23: =IF(E23=0,"",E23/E$9) | G23: =G20+G21-G22 -> #DIV/0! | H23: =IF(G23=0,"",G23/G$9) -> #DIV/0! | I23: =I20+I21-I22 -> #DIV/0! | J23: =IF(I23=0,"",I23/I$9) -> #DIV/0! | K23: =K20+K21-K22 -> #DIV/0! | L23: =IF(K23=0,"",K23/K$9) -> #DIV/0! | M23: =M20+M21-M22 -> #DIV/0! | N23: =IF(M23=0,"",M23/M$9) -> #DIV/0! | O23: =O20+O21-O22 -> #DIV/0! | P23: =IF(O23=0,"",O23/O$9) -> #DIV/0! | R23: =G23+I23+K23+M23+O23 -> #DIV/0! | S23: =IF(R23=0,"",R23/R$9) -> #DIV/0!
A25: BEP | B25: 損益分岐点売上高・率 | E25: =(E11+E12+E16+E17+E18+E22-E21)/F26 -> #VALUE! | F25: =IF(E25=0,"",E25/E$9) -> #VALUE! | G25: =(G11+G12+G16+G17+G18+G22-G21)/H26 -> #DIV/0! | H25: =IF(G25=0,"",G25/G$9) -> #DIV/0! | I25: =(I11+I12+I16+I17+I18+I22-I21)/J26 -> #DIV/0! | J25: =IF(I25=0,"",I25/I$9) -> #DIV/0! | K25: =(K11+K12+K16+K17+K18+K22-K21)/L26 -> #DIV/0! | L25: =IF(K25=0,"",K25/K$9) -> #DIV/0! | M25: =(M11+M12+M16+M17+M18+M22-M21)/N26 -> #DIV/0! | N25: =IF(M25=0,"",M25/M$9) -> #DIV/0! | O25: =(O11+O12+O16+O17+O18+O22-O21)/P26 -> #DIV/0! | P25: =IF(O25=0,"",O25/O$9) -> #DIV/0!
B26: 限界利益額・率 | E26: =E9-E10-E15 -> 0 | F26: =IF(E26=0,"",E26/E$9) | G26: =G9-G10-G15 -> #DIV/0! | H26: =IF(G26=0,"",G26/G$9) -> #DIV/0! | I26: =I9-I10-I15 -> #DIV/0! | J26: =IF(I26=0,"",I26/I$9) -> #DIV/0! | K26: =K9-K10-K15 -> #DIV/0! | L26: =IF(K26=0,"",K26/K$9) -> #DIV/0! | M26: =M9-M10-M15 -> #DIV/0! | N26: =IF(M26=0,"",M26/M$9) -> #DIV/0! | O26: =O9-O10-O15 -> #DIV/0! | P26: =IF(O26=0,"",O26/O$9) -> #DIV/0!
B27: １人あたり人件費 （直接・間接全て） | E27: =(E11+E16)/R8 -> #DIV/0!
A29: ２．部門別売上・コストのシミュレーション
A30: [パターン①]
E31: 合計 上段：売上構成 下段：人員数 | F31: 売上比 | G31: =G6 -> 0 | H31: 売上比 | I31: =I6 -> 0 | J31: 売上比 | K31: =K6 -> 0 | L31: 売上比 | M31: =M6 -> 0 | N31: 売上比 | O31: =O6 -> 0 | P31: 売上比 | R31: 【コメント】
E32: =G32+I32+K32+M32+O32 -> 0
E33: =G33+I33+K33+M33+O33 -> 0
A34: 売上高 | F34: =IF(E34=0,"",E34/E$34) | G34: =$E$34*G32 -> 0 | H34: =IF(G34=0,"",G34/G$34) | I34: =$E$34*I32 -> 0 | J34: =IF(I34=0,"",I34/I$34) | K34: =$E$34*K32 -> 0 | L34: =IF(K34=0,"",K34/K$34) | M34: =$E$34*M32 -> 0 | N34: =IF(M34=0,"",M34/M$34) | O34: =$E$34*O32 -> 0 | P34: =IF(O34=0,"",O34/O$34) | V34: =G34+I34+K34+M34+O34 -> 0
A35: 売上原価 | B35: 変動費 | E35: =G35+I35+K35+M35+O35 -> #DIV/0! | F35: =IF(E35=0,"",E35/E$34) -> #DIV/0! | G35: =G34*H35 -> #DIV/0! | H35: =H10 -> #DIV/0! | I35: =I34*J35 -> #DIV/0! | J35: =J10 -> #DIV/0! | K35: =K34*L35 -> #DIV/0! | L35: =L10 -> #DIV/0! | M35: =M34*N35 -> #DIV/0! | N35: =N10 -> #DIV/0! | O35: =O34*P35 -> #DIV/0! | P35: =P10 -> #DIV/0! | V35: =G35+I35+K35+M35+O35 -> #DIV/0!
B36: 固定費 | C36: 労務費 | E36: =E11 -> 0 | F36: =IF(E36=0,"",E36/E$34) | G36: =$E36*G33/$E33 -> #DIV/0! | H36: =IF(G36=0,"",G36/G$34) -> #DIV/0! | I36: =$E36*I33/$E33 -> #DIV/0! | J36: =IF(I36=0,"",I36/I$34) -> #DIV/0! | K36: =$E36*K33/$E33 -> #DIV/0! | L36: =IF(K36=0,"",K36/K$34) -> #DIV/0! | M36: =$E36*M33/$E33 -> #DIV/0! | N36: =IF(M36=0,"",M36/M$34) -> #DIV/0! | O36: =$E36*O33/$E33 -> #DIV/0! | P36: =IF(O36=0,"",O36/O$34) -> #DIV/0! | V36: =G36+I36+K36+M36+O36 -> #DIV/0!
C37: 経費 | E37: =E12 -> 0 | F37: =IF(E37=0,"",E37/E$34) | G37: =$E37*G32 -> 0 | H37: =IF(G37=0,"",G37/G$34) | I37: =$E37*I32 -> 0 | J37: =IF(I37=0,"",I37/I$34) | K37: =$E37*K32 -> 0 | L37: =IF(K37=0,"",K37/K$34) | M37: =$E37*M32 -> 0 | N37: =IF(M37=0,"",M37/M$34) | O37: =$E37*O32 -> 0 | P37: =IF(O37=0,"",O37/O$34) | V37: =G37+I37+K37+M37+O37 -> 0
A38: 合計 | E38: =SUM(E35:E37) -> #DIV/0! | F38: =IF(E38=0,"",E38/E$34) -> #DIV/0! | G38: =SUM(G35:G37) -> #DIV/0! | H38: =IF(G38=0,"",G38/G$34) -> #DIV/0! | I38: =SUM(I35:I37) -> #DIV/0! | J38: =IF(I38=0,"",I38/I$34) -> #DIV/0! | K38: =SUM(K35:K37) -> #DIV/0! | L38: =IF(K38=0,"",K38/K$34) -> #DIV/0! | M38: =SUM(M35:M37) -> #DIV/0! | N38: =IF(M38=0,"",M38/M$34) -> #DIV/0! | O38: =SUM(O35:O37) -> #DIV/0! | P38: =IF(O38=0,"",O38/O$34) -> #DIV/0! | V38: =G38+I38+K38+M38+O38 -> #DIV/0!
A39: 売上総利益 | E39: =E34-E38 -> #DIV/0! | F39: =IF(E39=0,"",E39/E$34) -> #DIV/0! | G39: =G34-G38 -> #DIV/0! | H39: =IF(G39=0,"",G39/G$34) -> #DIV/0! | I39: =I34-I38 -> #DIV/0! | J39: =IF(I39=0,"",I39/I$34) -> #DIV/0! | K39: =K34-K38 -> #DIV/0! | L39: =IF(K39=0,"",K39/K$34) -> #DIV/0! | M39: =M34-M38 -> #DIV/0! | N39: =IF(M39=0,"",M39/M$34) -> #DIV/0! | O39: =O34-O38 -> #DIV/0! | P39: =IF(O39=0,"",O39/O$34) -> #DIV/0! | V39: =G39+I39+K39+M39+O39 -> #DIV/0!
A40: 販管費 | B40: 変動費 | E40: =G40+I40+K40+M40+O40 -> 0 | F40: =IF(E40=0,"",E40/E$34) | G40: =IF(H40="",0,G34*H40) -> 0 | H40: =H15 | I40: =IF(J40="",0,I34*J40) -> 0 | J40: =J15 | K40: =IF(L40="",0,K34*L40) -> 0 | L40: =L15 | M40: =IF(N40="",0,M34*N40) -> 0 | N40: =N15 | O40: =IF(P40="",0,O34*P40) -> 0 | P40: =P15
B41: 固定費 | C41: 人件費 | E41: =G41+I41+K41+M41+O41 -> #DIV/0! | F41: =IF(E41=0,"",E41/E$34) -> #DIV/0! | G41: =$E16*G33/$E33 -> #DIV/0! | H41: =IF(G41=0,"",G41/G$34) -> #DIV/0! | I41: =$E16*I33/$E33 -> #DIV/0! | J41: =IF(I41=0,"",I41/I$34) -> #DIV/0! | K41: =$E16*K33/$E33 -> #DIV/0! | L41: =IF(K41=0,"",K41/K$34) -> #DIV/0! | M41: =$E16*M33/$E33 -> #DIV/0! | N41: =IF(M41=0,"",M41/M$34) -> #DIV/0! | O41: =$E16*O33/$E33 -> #DIV/0! | P41: =IF(O41=0,"",O41/O$34) -> #DIV/0! | V41: =G41+I41+K41+M41+O41 -> #DIV/0!
C42: 減価償却費 | E42: =G42+I42+K42+M42+O42 -> 0 | F42: =IF(E42=0,"",E42/E$34) | G42: =$E17*G$32 -> 0 | H42: =IF(G42=0,"",G42/G$34) | I42: =$E17*I$32 -> 0 | J42: =IF(I42=0,"",I42/I$34) | K42: =$E17*K$32 -> 0 | L42: =IF(K42=0,"",K42/K$34) | M42: =$E17*M$32 -> 0 | N42: =IF(M42=0,"",M42/M$34) | O42: =$E17*O$32 -> 0 | P42: =IF(O42=0,"",O42/O$34) | V42: =G42+I42+K42+M42+O42 -> 0
C43: その他 | E43: =G43+I43+K43+M43+O43 -> 0 | F43: =IF(E43=0,"",E43/E$34) | G43: =$E18*G$32 -> 0 | H43: =IF(G43=0,"",G43/G$34) | I43: =$E18*I$32 -> 0 | J43: =IF(I43=0,"",I43/I$34) | K43: =$E18*K$32 -> 0 | L43: =IF(K43=0,"",K43/K$34) | M43: =$E18*M$32 -> 0 | N43: =IF(M43=0,"",M43/M$34) | O43: =$E18*O$32 -> 0 | P43: =IF(O43=0,"",O43/O$34) | V43: =G43+I43+K43+M43+O43 -> 0
D44: 合計 | E44: =SUM(E40:E43) -> #DIV/0! | F44: =IF(E44=0,"",E44/E$34) -> #DIV/0! | G44: =SUM(G40:G43) -> #DIV/0! | H44: =IF(G44=0,"",G44/G$34) -> #DIV/0! | I44: =SUM(I40:I43) -> #DIV/0! | J44: =IF(I44=0,"",I44/I$34) -> #DIV/0! | K44: =SUM(K40:K43) -> #DIV/0! | L44: =IF(K44=0,"",K44/K$34) -> #DIV/0! | M44: =SUM(M40:M43) -> #DIV/0! | N44: =IF(M44=0,"",M44/M$34) -> #DIV/0! | O44: =SUM(O40:O43) -> #DIV/0! | P44: =IF(O44=0,"",O44/O$34) -> #DIV/0! | V44: =G44+I44+K44+M44+O44 -> #DIV/0!
A45: 営業利益 | E45: =E39-E44 -> #DIV/0! | F45: =IF(E45=0,"",E45/E$34) -> #DIV/0! | G45: =G39-G44 -> #DIV/0! | H45: =IF(G45=0,"",G45/G$34) -> #DIV/0! | I45: =I39-I44 -> #DIV/0! | J45: =IF(I45=0,"",I45/I$34) -> #DIV/0! | K45: =K39-K44 -> #DIV/0! | L45: =IF(K45=0,"",K45/K$34) -> #DIV/0! | M45: =M39-M44 -> #DIV/0! | N45: =IF(M45=0,"",M45/M$34) -> #DIV/0! | O45: =O39-O44 -> #DIV/0! | P45: =IF(O45=0,"",O45/O$34) -> #DIV/0! | V45: =G45+I45+K45+M45+O45 -> #DIV/0!
A46: 営業外 | B46: 営業外収入 | E46: =E21 -> 0 | F46: =IF(E46=0,"",E46/E$34) | G46: =$E46*G$32 -> 0 | H46: =IF(G46=0,"",G46/G$34) | I46: =$E46*I$32 -> 0 | J46: =IF(I46=0,"",I46/I$34) | K46: =$E46*K$32 -> 0 | L46: =IF(K46=0,"",K46/K$34) | M46: =$E46*M$32 -> 0 | N46: =IF(M46=0,"",M46/M$34) | O46: =$E46*O$32 -> 0 | P46: =IF(O46=0,"",O46/O$34)
B47: 営業外費用 | E47: =E22 -> 0 | F47: =IF(E47=0,"",E47/E$34) | G47: =$E47*G$32 -> 0 | H47: =IF(G47=0,"",G47/G$34) | I47: =$E47*I$32 -> 0 | J47: =IF(I47=0,"",I47/I$34) | K47: =$E47*K$32 -> 0 | L47: =IF(K47=0,"",K47/K$34) | M47: =$E47*M$32 -> 0 | N47: =IF(M47=0,"",M47/M$34) | O47: =$E47*O$32 -> 0 | P47: =IF(O47=0,"",O47/O$34)
A48: 経常利益 | E48: =E45+E46-E47 -> #DIV/0! | F48: =IF(E48=0,"",E48/E$34) -> #DIV/0! | G48: =G45+G46-G47 -> #DIV/0! | H48: =IF(G48=0,"",G48/G$34) -> #DIV/0! | I48: =I45+I46-I47 -> #DIV/0! | J48: =IF(I48=0,"",I48/I$34) -> #DIV/0! | K48: =K45+K46-K47 -> #DIV/0! | L48: =IF(K48=0,"",K48/K$34) -> #DIV/0! | M48: =M45+M46-M47 -> #DIV/0! | N48: =IF(M48=0,"",M48/M$34) -> #DIV/0! | O48: =O45+O46-O47 -> #DIV/0! | P48: =IF(O48=0,"",O48/O$34) -> #DIV/0!
A50: BEP | B50: 損益分岐点売上高・率 | E50: =(E36+E37+E41+E42+E43+E47-E46)/F51 -> #DIV/0! | F50: =IF(E50=0,"",E50/E$34) -> #DIV/0! | G50: =(G36+G37+G41+G42+G43+G47-G46)/H51 -> #DIV/0! | H50: =IF(G50=0,"",G50/G$34) -> #DIV/0! | I50: =(I36+I37+I41+I42+I43+I47-I46)/J51 -> #DIV/0! | J50: =IF(I50=0,"",I50/I$34) -> #DIV/0! | K50: =(K36+K37+K41+K42+K43+K47-K46)/L51 -> #DIV/0! | L50: =IF(K50=0,"",K50/K$34) -> #DIV/0! | M50: =(M36+M37+M41+M42+M43+M47-M46)/N51 -> #DIV/0! | N50: =IF(M50=0,"",M50/M$34) -> #DIV/0! | O50: =(O36+O37+O41+O42+O43+O47-O46)/P51 -> #DIV/0! | P50: =IF(O50=0,"",O50/O$34) -> #DIV/0!
B51: 限界利益額・率 | E51: =E34-E35-E40 -> #DIV/0! | F51: =IF(E51=0,"",E51/E$34) -> #DIV/0! | G51: =G34-G35-G40 -> #DIV/0! | H51: =IF(G51=0,"",G51/G$34) -> #DIV/0! | I51: =I34-I35-I40 -> #DIV/0! | J51: =IF(I51=0,"",I51/I$34) -> #DIV/0! | K51: =K34-K35-K40 -> #DIV/0! | L51: =IF(K51=0,"",K51/K$34) -> #DIV/0! | M51: =M34-M35-M40 -> #DIV/0! | N51: =IF(M51=0,"",M51/M$34) -> #DIV/0! | O51: =O34-O35-O40 -> #DIV/0! | P51: =IF(O51=0,"",O51/O$34) -> #DIV/0!
B52: １人あたり人件費 （直接・間接全て） | E52: =(E36+E41)/E33 -> #DIV/0!
A54: [パターン②]
E55: 合計 上段：売上構成 下段：人員数 | F55: 売上比 | G55: =G6 -> 0 | H55: 売上比 | I55: =I6 -> 0 | J55: 売上比 | K55: =K6 -> 0 | L55: 売上比 | M55: =M6 -> 0 | N55: 売上比 | O55: =O6 -> 0 | P55: 売上比 | R55: 【コメント】
E56: =G56+I56+K56+M56+O56 -> 0
E57: =G57+I57+K57+M57+O57 -> 0
A58: 売上高 | F58: =IF(E58=0,"",E58/E$58) | G58: =$E$58*G56 -> 0 | H58: =IF(G58=0,"",G58/G$58) | I58: =$E$58*I56 -> 0 | J58: =IF(I58=0,"",I58/I$58) | K58: =$E$58*K56 -> 0 | L58: =IF(K58=0,"",K58/K$58) | M58: =$E$58*M56 -> 0 | N58: =IF(M58=0,"",M58/M$58) | O58: =$E$58*O56 -> 0 | P58: =IF(O58=0,"",O58/O$58) | V58: =G58+I58+K58+M58+O58 -> 0
A59: 売上原価 | B59: 変動費 | E59: =G59+I59+K59+M59+O59 -> #DIV/0! | F59: =IF(E59=0,"",E59/E$58) -> #DIV/0! | G59: =G58*H59 -> #DIV/0! | H59: =H10 -> #DIV/0! | I59: =I58*J59 -> #DIV/0! | J59: =J10 -> #DIV/0! | K59: =K58*L59 -> #DIV/0! | L59: =L10 -> #DIV/0! | M59: =M58*N59 -> #DIV/0! | N59: =N10 -> #DIV/0! | O59: =O58*P59 -> #DIV/0! | P59: =P10 -> #DIV/0! | V59: =G59+I59+K59+M59+O59 -> #DIV/0!
B60: 固定費 | C60: 労務費 | E60: =E11 -> 0 | F60: =IF(E60=0,"",E60/E$58) | G60: =$E60*G57/$E57 -> #DIV/0! | H60: =IF(G60=0,"",G60/G$58) -> #DIV/0! | I60: =$E60*I57/$E57 -> #DIV/0! | J60: =IF(I60=0,"",I60/I$58) -> #DIV/0! | K60: =$E60*K57/$E57 -> #DIV/0! | L60: =IF(K60=0,"",K60/K$58) -> #DIV/0! | M60: =$E60*M57/$E57 -> #DIV/0! | N60: =IF(M60=0,"",M60/M$58) -> #DIV/0! | O60: =$E60*O57/$E57 -> #DIV/0! | P60: =IF(O60=0,"",O60/O$58) -> #DIV/0! | V60: =G60+I60+K60+M60+O60 -> #DIV/0!
C61: 経費 | E61: =E12 -> 0 | F61: =IF(E61=0,"",E61/E$58) | G61: =$E61*G56 -> 0 | H61: =IF(G61=0,"",G61/G$58) | I61: =$E61*I56 -> 0 | J61: =IF(I61=0,"",I61/I$58) | K61: =$E61*K56 -> 0 | L61: =IF(K61=0,"",K61/K$58) | M61: =$E61*M56 -> 0 | N61: =IF(M61=0,"",M61/M$58) | O61: =$E61*O56 -> 0 | P61: =IF(O61=0,"",O61/O$58) | V61: =G61+I61+K61+M61+O61 -> 0
A62: 合計 | E62: =SUM(E59:E61) -> #DIV/0! | F62: =IF(E62=0,"",E62/E$58) -> #DIV/0! | G62: =SUM(G59:G61) -> #DIV/0! | H62: =IF(G62=0,"",G62/G$58) -> #DIV/0! | I62: =SUM(I59:I61) -> #DIV/0! | J62: =IF(I62=0,"",I62/I$58) -> #DIV/0! | K62: =SUM(K59:K61) -> #DIV/0! | L62: =IF(K62=0,"",K62/K$58) -> #DIV/0! | M62: =SUM(M59:M61) -> #DIV/0! | N62: =IF(M62=0,"",M62/M$58) -> #DIV/0! | O62: =SUM(O59:O61) -> #DIV/0! | P62: =IF(O62=0,"",O62/O$58) -> #DIV/0! | V62: =G62+I62+K62+M62+O62 -> #DIV/0!
A63: 売上総利益 | E63: =E58-E62 -> #DIV/0! | F63: =IF(E63=0,"",E63/E$58) -> #DIV/0! | G63: =G58-G62 -> #DIV/0! | H63: =IF(G63=0,"",G63/G$58) -> #DIV/0! | I63: =I58-I62 -> #DIV/0! | J63: =IF(I63=0,"",I63/I$58) -> #DIV/0! | K63: =K58-K62 -> #DIV/0! | L63: =IF(K63=0,"",K63/K$58) -> #DIV/0! | M63: =M58-M62 -> #DIV/0! | N63: =IF(M63=0,"",M63/M$58) -> #DIV/0! | O63: =O58-O62 -> #DIV/0! | P63: =IF(O63=0,"",O63/O$58) -> #DIV/0! | V63: =G63+I63+K63+M63+O63 -> #DIV/0!
A64: 販管費 | B64: 変動費 | E64: =G64+I64+K64+M64+O64 -> 0 | F64: =IF(E64=0,"",E64/E$58) | G64: =IF(H64="",0,G58*H64) -> 0 | H64: =H15 | I64: =IF(J64="",0,I58*J64) -> 0 | J64: =J15 | K64: =IF(L64="",0,K58*L64) -> 0 | L64: =L15 | M64: =IF(N64="",0,M58*N64) -> 0 | N64: =N15 | O64: =IF(P64="",0,O58*P64) -> 0 | P64: =P15
B65: 固定費 | C65: 人件費 | E65: =G65+I65+K65+M65+O65 -> #DIV/0! | F65: =IF(E65=0,"",E65/E$58) -> #DIV/0! | G65: =$E16*G57/$E57 -> #DIV/0! | H65: =IF(G65=0,"",G65/G$58) -> #DIV/0! | I65: =$E16*I57/$E57 -> #DIV/0! | J65: =IF(I65=0,"",I65/I$58) -> #DIV/0! | K65: =$E16*K57/$E57 -> #DIV/0! | L65: =IF(K65=0,"",K65/K$58) -> #DIV/0! | M65: =$E16*M57/$E57 -> #DIV/0! | N65: =IF(M65=0,"",M65/M$58) -> #DIV/0! | O65: =$E16*O57/$E57 -> #DIV/0! | P65: =IF(O65=0,"",O65/O$58) -> #DIV/0! | V65: =G65+I65+K65+M65+O65 -> #DIV/0!
C66: 減価償却費 | E66: =G66+I66+K66+M66+O66 -> 0 | F66: =IF(E66=0,"",E66/E$34) | G66: =$E17*G$32 -> 0 | H66: =IF(G66=0,"",G66/G$58) | I66: =$E17*I$32 -> 0 | J66: =IF(I66=0,"",I66/I$58) | K66: =$E17*K$32 -> 0 | L66: =IF(K66=0,"",K66/K$58) | M66: =$E17*M$32 -> 0 | N66: =IF(M66=0,"",M66/M$58) | O66: =$E17*O$32 -> 0 | P66: =IF(O66=0,"",O66/O$58) | V66: =G66+I66+K66+M66+O66 -> 0
C67: その他 | E67: =G67+I67+K67+M67+O67 -> 0 | F67: =IF(E67=0,"",E67/E$34) | G67: =$E18*G$32 -> 0 | H67: =IF(G67=0,"",G67/G$58) | I67: =$E18*I$32 -> 0 | J67: =IF(I67=0,"",I67/I$58) | K67: =$E18*K$32 -> 0 | L67: =IF(K67=0,"",K67/K$58) | M67: =$E18*M$32 -> 0 | N67: =IF(M67=0,"",M67/M$58) | O67: =$E18*O$32 -> 0 | P67: =IF(O67=0,"",O67/O$58) | V67: =G67+I67+K67+M67+O67 -> 0
D68: 合計 | E68: =SUM(E64:E67) -> #DIV/0! | F68: =IF(E68=0,"",E68/E$58) -> #DIV/0! | G68: =SUM(G64:G67) -> #DIV/0! | H68: =IF(G68=0,"",G68/G$58) -> #DIV/0! | I68: =SUM(I64:I67) -> #DIV/0! | J68: =IF(I68=0,"",I68/I$58) -> #DIV/0! | K68: =SUM(K64:K67) -> #DIV/0! | L68: =IF(K68=0,"",K68/K$58) -> #DIV/0! | M68: =SUM(M64:M67) -> #DIV/0! | N68: =IF(M68=0,"",M68/M$58) -> #DIV/0! | O68: =SUM(O64:O67) -> #DIV/0! | P68: =IF(O68=0,"",O68/O$58) -> #DIV/0! | V68: =G68+I68+K68+M68+O68 -> #DIV/0!
A69: 営業利益 | E69: =E63-E68 -> #DIV/0! | F69: =IF(E69=0,"",E69/E$58) -> #DIV/0! | G69: =G63-G68 -> #DIV/0! | H69: =IF(G69=0,"",G69/G$58) -> #DIV/0! | I69: =I63-I68 -> #DIV/0! | J69: =IF(I69=0,"",I69/I$58) -> #DIV/0! | K69: =K63-K68 -> #DIV/0! | L69: =IF(K69=0,"",K69/K$58) -> #DIV/0! | M69: =M63-M68 -> #DIV/0! | N69: =IF(M69=0,"",M69/M$58) -> #DIV/0! | O69: =O63-O68 -> #DIV/0! | P69: =IF(O69=0,"",O69/O$58) -> #DIV/0! | V69: =G69+I69+K69+M69+O69 -> #DIV/0!
A70: 営業外 | B70: 営業外収入 | E70: =E21 -> 0 | F70: =IF(E70=0,"",E70/E$58) | G70: =$E70*G$56 -> 0 | H70: =IF(G70=0,"",G70/G$58) | I70: =$E70*I$56 -> 0 | J70: =IF(I70=0,"",I70/I$58) | K70: =$E70*K$56 -> 0 | L70: =IF(K70=0,"",K70/K$58) | M70: =$E70*M$56 -> 0 | N70: =IF(M70=0,"",M70/M$58) | O70: =$E70*O$56 -> 0 | P70: =IF(O70=0,"",O70/O$58)
B71: 営業外費用 | E71: =E22 -> 0 | F71: =IF(E71=0,"",E71/E$58) | G71: =$E71*G$56 -> 0 | H71: =IF(G71=0,"",G71/G$58) | I71: =$E71*I$56 -> 0 | J71: =IF(I71=0,"",I71/I$58) | K71: =$E71*K$56 -> 0 | L71: =IF(K71=0,"",K71/K$58) | M71: =$E71*M$56 -> 0 | N71: =IF(M71=0,"",M71/M$58) | O71: =$E71*O$56 -> 0 | P71: =IF(O71=0,"",O71/O$58)
A72: 経常利益 | E72: =E69+E70-E71 -> #DIV/0! | F72: =IF(E72=0,"",E72/E$58) -> #DIV/0! | G72: =G69+G70-G71 -> #DIV/0! | H72: =IF(G72=0,"",G72/G$58) -> #DIV/0! | I72: =I69+I70-I71 -> #DIV/0! | J72: =IF(I72=0,"",I72/I$58) -> #DIV/0! | K72: =K69+K70-K71 -> #DIV/0! | L72: =IF(K72=0,"",K72/K$58) -> #DIV/0! | M72: =M69+M70-M71 -> #DIV/0! | N72: =IF(M72=0,"",M72/M$58) -> #DIV/0! | O72: =O69+O70-O71 -> #DIV/0! | P72: =IF(O72=0,"",O72/O$58) -> #DIV/0!
A74: BEP | B74: 損益分岐点売上高・率 | E74: =(E60+E61+E65+E66+E67+E71-E70)/F75 -> #DIV/0! | F74: =IF(E74=0,"",E74/E$58) -> #DIV/0! | G74: =(G60+G61+G65+G66+G67+G71-G70)/H75 -> #DIV/0! | H74: =IF(G74=0,"",G74/G$58) -> #DIV/0! | I74: =(I60+I61+I65+I66+I67+I71-I70)/J75 -> #DIV/0! | J74: =IF(I74=0,"",I74/I$58) -> #DIV/0! | K74: =(K60+K61+K65+K66+K67+K71-K70)/L75 -> #DIV/0! | L74: =IF(K74=0,"",K74/K$58) -> #DIV/0! | M74: =(M60+M61+M65+M66+M67+M71-M70)/N75 -> #DIV/0! | N74: =IF(M74=0,"",M74/M$58) -> #DIV/0! | O74: =(O60+O61+O65+O66+O67+O71-O70)/P75 -> #DIV/0! | P74: =IF(O74=0,"",O74/O$58) -> #DIV/0!
B75: 限界利益額・率 | E75: =E58-E59-E64 -> #DIV/0! | F75: =IF(E75=0,"",E75/E$58) -> #DIV/0! | G75: =G58-G59-G64 -> #DIV/0! | H75: =IF(G75=0,"",G75/G$58) -> #DIV/0! | I75: =I58-I59-I64 -> #DIV/0! | J75: =IF(I75=0,"",I75/I$58) -> #DIV/0! | K75: =K58-K59-K64 -> #DIV/0! | L75: =IF(K75=0,"",K75/K$58) -> #DIV/0! | M75: =M58-M59-M64 -> #DIV/0! | N75: =IF(M75=0,"",M75/M$58) -> #DIV/0! | O75: =O58-O59-O64 -> #DIV/0! | P75: =IF(O75=0,"",O75/O$58) -> #DIV/0!
B76: １人あたり人件費 （直接・間接全て） | E76: =(E60+E65)/E57 -> #DIV/0!

Sheet CF計算書
B1: キャッシュ・フロー計算書（概算・参考）
B4: キャッシュ・フロー計算書
B5: ='財務諸表（入力）'!J4 -> 2022年2月1日～2023年1月31日
C6: =CFワークシート!J7 -> （単位：千円） | E6: （単位：百万円）
B7: 項 目 | C7: 金 額 | E7: （単位：千円）
B8: Ⅰ 営業活動によるキャッシュ・フロー | E8: （単位：円）
B9: （１）当期純利益（＋） | C9: =CFワークシート!D44 -> 0
B10: （２）非資金の費用項目
B11: １．減価償却費（＋） | C11: =CFワークシート!D48 -> 0
B12: ２．諸引当金の増加（＋）・減少（－）額 | C12: =CFワークシート!J13+CFワークシート!J18-CFワークシート!E16-CFワークシート!E25 -> 0
B13: （３）回収・支払サイト
B14: １．受取手形の増加（－）・減少（＋）額 | C14: =CFワークシート!E10*-1 -> 0
B15: ２．売掛金の増加（－）・減少（＋）額 | C15: =CFワークシート!E11*-1 -> 0
B16: ３．棚卸資産の増加（－）・減少（＋）額 | C16: =CFワークシート!E13*-1 -> 0
B17: ４．その他の流動資産の増加（－）・減少（＋）額 | C17: =CFワークシート!E15*-1 -> 0
B18: ５．支払手形の増加（＋）・減少（－）額 | C18: =CFワークシート!J9 -> 0
B19: ６．買掛金の増加（＋）・減少（－）額 | C19: =CFワークシート!J10 -> 0
B20: ７．前受金の増加（＋）・減少（－）額 | C20: =CFワークシート!J12 -> 0
B21: ８．その他の流動負債の増加（＋）・減少（－）額 | C21: =CFワークシート!J14 -> 0
B22: ９．その他の固定負債の増加（＋）・減少（－）額 | C22: =CFワークシート!J19 -> 0
B23: １０．利益処分による役員賞与の支払（－）額 | C23: =CFワークシート!F60 -> 0
B24: （Ⅰの計） | C24: =SUM(C9:C23) -> 0
B25: Ⅱ 投資活動によるキャッシュ・フロー
B26: １．有価証券の購入（－）・売却（＋）額 | C26: =CFワークシート!E12*-1 -> 0
B27: ２．短期貸付金の貸付（－）・回収（＋）額 | C27: =CFワークシート!E14*-1 -> 0
B28: ３．土地の購入（－）・売却（＋）額 | C28: =CFワークシート!E18*-1 -> 0
B29: ４．減価償却資産の増加（－）・減少（＋）額 | C29: =(CFワークシート!E19+CFワークシート!D48)*-1 -> 0
B30: ５．建設仮勘定の増加（－）・減少（＋）額 | C30: =CFワークシート!E20*-1 -> 0
B31: ６．無形固定資産の増加（－）・減少（＋）額 | C31: =CFワークシート!E21*-1 -> 0
B32: ７．投資有価証券の購入（－）・売却（＋）額 | C32: =CFワークシート!E22*-1 -> 0
B33: ８．長期貸付金の貸付（－）・回収（＋）額 | C33: =CFワークシート!E23*-1 -> 0
B34: ９．その他の固定資産の増加（－）・減少（＋）額 | C34: =CFワークシート!E24*-1 -> 0
B35: １０．繰延資産の増加（－）・減少（＋）額 | C35: =CFワークシート!E27*-1 -> 0
B36: （Ⅱの計） | C36: =SUM(C26:C35) -> 0
B37: フリーキャッシュ・フロー（Ⅰ＋Ⅱ） | C37: =C24+C36 -> 0
B38: Ⅲ 財務活動によるキャッシュ・フロー
B39: １．短期借入金の増加（＋）・減少（－）額 | C39: =CFワークシート!J11 -> 0
B40: ２．長期借入金の増加（＋）・減少（－）額 | C40: =CFワークシート!J16 -> 0
B41: ３．社債の増加（＋）・返済（－）額 | C41: =CFワークシート!J17 -> 0
B42: ４．増資（＋）額 | C42: =CFワークシート!J22+CFワークシート!J23 -> 0
B43: ５．自己株式の取得（－）・処分（＋）額 | C43: =CFワークシート!J25+CFワークシート!J26 -> 0
B44: ６．剰余金の配当の支払（－）額 | C44: =CFワークシート!F59 -> 0
B45: （Ⅲの計） | C45: =SUM(C39:C44) -> 0
B46: Ⅳ キャッシュの増加・減少額（Ⅰ＋Ⅱ＋Ⅲ） | C46: =C37+C45 -> 0
B47: Ⅴ キャッシュの期首残高 | C47: =CFワークシート!C9 -> 0
B48: Ⅵ キャッシュの期末残高（Ⅳ＋Ⅴ） | C48: =C46+C47 -> 0
B49: 検算（貸借対照表の現金及び預金） | C49: =CFワークシート!D9 -> 0
C50: =C48-C49 -> 0
B52: （照合）この欄が０でＯＫ

Sheet CF計算書②
B1: キャッシュ・フロー計算書（概算・参考）
B4: キャッシュ・フロー計算書②
B5: ='財務諸表（入力）'!G4 -> 2021年2月1日～2022年1月31日
C6: =CFワークシート!J7 -> （単位：千円） | E6: （単位：百万円）
B7: 項 目 | C7: 金 額 | E7: （単位：千円）
B8: Ⅰ 営業活動によるキャッシュ・フロー | E8: （単位：円）
B9: （１）当期純利益（＋） | C9: =CFワークシート②!D44 -> 0
B10: （２）非資金の費用項目
B11: １．減価償却費（＋） | C11: =CFワークシート②!D48 -> 0
B12: ２．諸引当金の増加（＋）・減少（－）額 | C12: =CFワークシート②!J13+CFワークシート②!J18-CFワークシート②!E16-CFワークシート②!E25 -> 0
B13: （３）回収・支払サイト
B14: １．受取手形の増加（－）・減少（＋）額 | C14: =CFワークシート②!E10*-1 -> 0
B15: ２．売掛金の増加（－）・減少（＋）額 | C15: =CFワークシート②!E11*-1 -> 0
B16: ３．棚卸資産の増加（－）・減少（＋）額 | C16: =CFワークシート②!E13*-1 -> 0
B17: ４．その他の流動資産の増加（－）・減少（＋）額 | C17: =CFワークシート②!E15*-1 -> 0
B18: ５．支払手形の増加（＋）・減少（－）額 | C18: =CFワークシート②!J9 -> 0
B19: ６．買掛金の増加（＋）・減少（－）額 | C19: =CFワークシート②!J10 -> 0
B20: ７．前受金の増加（＋）・減少（－）額 | C20: =CFワークシート②!J12 -> 0
B21: ８．その他の流動負債の増加（＋）・減少（－）額 | C21: =CFワークシート②!J14 -> 0
B22: ９．その他の固定負債の増加（＋）・減少（－）額 | C22: =CFワークシート②!J19 -> 0
B23: １０．利益処分による役員賞与の支払（－）額 | C23: =CFワークシート②!F60 -> 0
B24: （Ⅰの計） | C24: =SUM(C9:C23) -> 0
B25: Ⅱ 投資活動によるキャッシュ・フロー
B26: １．有価証券の購入（－）・売却（＋）額 | C26: =CFワークシート②!E12*-1 -> 0
B27: ２．短期貸付金の貸付（－）・回収（＋）額 | C27: =CFワークシート②!E14*-1 -> 0
B28: ３．土地の購入（－）・売却（＋）額 | C28: =CFワークシート②!E18*-1 -> 0
B29: ４．減価償却資産の増加（－）・減少（＋）額 | C29: =(CFワークシート②!E19+CFワークシート②!D48)*-1 -> 0
B30: ５．建設仮勘定の増加（－）・減少（＋）額 | C30: =CFワークシート②!E20*-1 -> 0
B31: ６．無形固定資産の増加（－）・減少（＋）額 | C31: =CFワークシート②!E21*-1 -> 0
B32: ７．投資有価証券の購入（－）・売却（＋）額 | C32: =CFワークシート②!E22*-1 -> 0
B33: ８．長期貸付金の貸付（－）・回収（＋）額 | C33: =CFワークシート②!E23*-1 -> 0
B34: ９．その他の固定資産の増加（－）・減少（＋）額 | C34: =CFワークシート②!E24*-1 -> 0
B35: １０．繰延資産の増加（－）・減少（＋）額 | C35: =CFワークシート②!E27*-1 -> 0
B36: （Ⅱの計） | C36: =SUM(C26:C35) -> 0
B37: フリーキャッシュ・フロー（Ⅰ＋Ⅱ） | C37: =C24+C36 -> 0
B38: Ⅲ 財務活動によるキャッシュ・フロー
B39: １．短期借入金の増加（＋）・減少（－）額 | C39: =CFワークシート②!J11 -> 0
B40: ２．長期借入金の増加（＋）・減少（－）額 | C40: =CFワークシート②!J16 -> 0
B41: ３．社債の増加（＋）・返済（－）額 | C41: =CFワークシート②!J17 -> 0
B42: ４．増資（＋）額 | C42: =CFワークシート②!J22+CFワークシート②!J23 -> 0
B43: ５．自己株式の取得（－）・処分（＋）額 | C43: =CFワークシート②!J25+CFワークシート②!J26 -> 0
B44: ６．剰余金の配当の支払（－）額 | C44: =CFワークシート②!F59 -> 0
B45: （Ⅲの計） | C45: =SUM(C39:C44) -> 0
B46: Ⅳ キャッシュの増加・減少額（Ⅰ＋Ⅱ＋Ⅲ） | C46: =C37+C45 -> 0
B47: Ⅴ キャッシュの期首残高 | C47: =CFワークシート②!C9 -> 0
B48: Ⅵ キャッシュの期末残高（Ⅳ＋Ⅴ） | C48: =C46+C47 -> 0
B49: 検算（貸借対照表の現金及び預金） | C49: =CFワークシート②!D9 -> 0
C50: =C48-C49 -> 0
B52: （照合）この欄が０でＯＫ

Sheet CFワークシート
B2: キャッシュ・フロー計算書のワークシート（入力用）
B7: １．貸借対照表の入力 | J7: （単位：千円） | L7: （単位：百万円）
B8: 項目 | C8: ='財務諸表（入力）'!G4 -> 2021年2月1日～2022年1月31日 | D8: ='財務諸表（入力）'!J4 -> 2022年2月1日～2023年1月31日 | E8: 増減 | F8: 項目 | H8: =C8 -> 2021年2月1日～2022年1月31日 | I8: =D8 -> 2022年2月1日～2023年1月31日 | J8: 増減 | L8: （単位：千円）
B9: 現金及び預金 | C9: ='財務諸表（入力）'!G6 -> 0 | D9: ='財務諸表（入力）'!J6 -> 0 | E9: =D9-C9 -> 0 | F9: 支払手形 | H9: ='財務諸表（入力）'!G51 -> 0 | I9: ='財務諸表（入力）'!J51 -> 0 | J9: =I9-H9 -> 0 | L9: （単位：円）
B10: 受取手形 | C10: ='財務諸表（入力）'!G8 -> 0 | D10: ='財務諸表（入力）'!J8 -> 0 | E10: =D10-C10 -> 0 | F10: 買掛金 | H10: ='財務諸表（入力）'!G52 -> 0 | I10: ='財務諸表（入力）'!J52 -> 0 | J10: =I10-H10 -> 0
B11: 売掛金 | C11: ='財務諸表（入力）'!G9 -> 0 | D11: ='財務諸表（入力）'!J9 -> 0 | E11: =D11-C11 -> 0 | F11: 短期借入金 | H11: ='財務諸表（入力）'!G53 -> 0 | I11: ='財務諸表（入力）'!J53 -> 0 | J11: =I11-H11 -> 0
B12: 有価証券 | E12: =D12-C12 -> 0 | F12: 前受金 | J12: =I12-H12 -> 0
B13: 棚卸資産 | C13: ='財務諸表（入力）'!G16 -> 0 | D13: ='財務諸表（入力）'!J16 -> 0 | E13: =D13-C13 -> 0 | F13: 引当金 | J13: =I13-H13 -> 0
B14: 短期貸付金 | E14: =D14-C14 -> 0 | F14: その他の流動負債 | H14: ='財務諸表（入力）'!G61-CFワークシート!H9-CFワークシート!H10-CFワークシート!H11-CFワークシート!H12-CFワークシート!H13 -> 0 | I14: ='財務諸表（入力）'!J61-CFワークシート!I9-CFワークシート!I10-CFワークシート!I11-CFワークシート!I12-CFワークシート!I13 -> 0 | J14: =I14-H14 -> 0
B15: その他の流動資産 | C15: ='財務諸表（入力）'!G28-CFワークシート!C9-CFワークシート!C10-CFワークシート!C11-CFワークシート!C12-CFワークシート!C13-CFワークシート!C14-CFワークシート!C16 -> 0 | D15: ='財務諸表（入力）'!J28-CFワークシート!D9-CFワークシート!D10-CFワークシート!D11-CFワークシート!D12-CFワークシート!D13-CFワークシート!D14-D16 -> 0 | E15: =D15-C15 -> 0 | F15: 流動負債合計 | H15: =SUM(H9:H14) -> 0 | I15: =SUM(I9:I14) -> 0 | J15: =I15-H15 -> 0
B16: 貸倒引当金 | C16: ='財務諸表（入力）'!G25 -> 0 | D16: ='財務諸表（入力）'!J25 -> 0 | E16: =D16-C16 -> 0 | F16: 長期借入金 | H16: ='財務諸表（入力）'!G62 -> 0 | I16: ='財務諸表（入力）'!J62 -> 0 | J16: =I16-H16 -> 0
B17: 流動資産合計 | C17: =SUM(C9:C16) -> 0 | D17: =SUM(D9:D16) -> 0 | E17: =D17-C17 -> 0 | F17: 社債 | H17: ='財務諸表（入力）'!G63 -> 0 | I17: ='財務諸表（入力）'!J63 -> 0 | J17: =I17-H17 -> 0
B18: 土地 | C18: ='財務諸表（入力）'!G34 -> 0 | D18: ='財務諸表（入力）'!J34 -> 0 | E18: =D18-C18 -> 0 | F18: 引当金 | J18: =I18-H18 -> 0
B19: 減価償却資産 | C19: ='財務諸表（入力）'!G37-'財務諸表（入力）'!G34-'財務諸表（入力）'!G35 -> 0 | D19: ='財務諸表（入力）'!J37-'財務諸表（入力）'!J34-'財務諸表（入力）'!J35 -> 0 | E19: =D19-C19 -> 0 | F19: その他の固定負債 | H19: ='財務諸表（入力）'!G69-CFワークシート!H16-CFワークシート!H17-CFワークシート!H18 -> 0 | I19: ='財務諸表（入力）'!J69-CFワークシート!I16-CFワークシート!I17-CFワークシート!I18 -> 0 | J19: =I19-H19 -> 0
B20: 建設仮勘定 | C20: ='財務諸表（入力）'!G35 -> 0 | D20: ='財務諸表（入力）'!J35 -> 0 | E20: =D20-C20 -> 0 | F20: 固定負債合計 | H20: =SUM(H16:H19) -> 0 | I20: =SUM(I16:I19) -> 0 | J20: =I20-H20 -> 0
B21: 無形固定資産 | C21: ='財務諸表（入力）'!G38 -> 0 | D21: ='財務諸表（入力）'!J38 -> 0 | E21: =D21-C21 -> 0 | F21: 負債合計 | H21: =H15+H20 -> 0 | I21: =I15+I20 -> 0 | J21: =I21-H21 -> 0
B22: 投資有価証券.子会社株式.出資金等 | E22: =D22-C22 -> 0 | F22: 資本金 | H22: ='財務諸表（入力）'!G71 -> 0 | I22: ='財務諸表（入力）'!J71 -> 0 | J22: =I22-H22 -> 0
B23: 長期貸付金 | E23: =D23-C23 -> 0 | F23: 資本剰余金 | H23: ='財務諸表（入力）'!G72 -> 0 | I23: ='財務諸表（入力）'!J72 -> 0 | J23: =I23-H23 -> 0
B24: その他の固定資産 | C24: ='財務諸表（入力）'!G47-CFワークシート!C22-CFワークシート!C23-CFワークシート!C25 -> 0 | D24: ='財務諸表（入力）'!J47-CFワークシート!D25-CFワークシート!D22-CFワークシート!D23 -> 0 | E24: =D24-C24 -> 0 | F24: 利益剰余金 | H24: ='財務諸表（入力）'!G73 -> 0 | I24: ='財務諸表（入力）'!J73 -> 0 | J24: =I24-H24 -> 0
B25: 貸倒引当金 | C25: ='財務諸表（入力）'!G45 -> 0 | D25: ='財務諸表（入力）'!J45 -> 0 | E25: =D25-C25 -> 0 | F25: 自己株式 | H25: ='財務諸表（入力）'!G77 -> 0 | I25: ='財務諸表（入力）'!J77 -> 0 | J25: =I25-H25 -> 0
B26: 固定資産合計 | C26: =SUM(C18:C25) -> 0 | D26: =SUM(D18:D25) -> 0 | E26: =D26-C26 -> 0 | F26: その他 | J26: =I26-H26 -> 0
B27: 繰延資産合計 | C27: ='財務諸表（入力）'!G48 -> 0 | D27: ='財務諸表（入力）'!J48 -> 0 | E27: =D27-C27 -> 0 | F27: 純資産合計 | H27: =SUM(H22:H26) -> 0 | I27: =SUM(I22:I26) -> 0 | J27: =I27-H27 -> 0
B28: 資産合計 | C28: =C17+C26+C27 -> 0 | D28: =D17+D26+D27 -> 0 | E28: =D28-C28 -> 0 | F28: 負債･純資産合計 | H28: =H21+H27 -> 0 | I28: =I21+I27 -> 0 | J28: =I28-H28 -> 0
B29: （注）有利子負債は、短期借入金又は長期借入金に含める。
B30: ２．損益計算書の入力 | E30: =J7 -> （単位：千円）
B31: 項目 | C31: =C8 -> 2021年2月1日～2022年1月31日 | D31: =D8 -> 2022年2月1日～2023年1月31日 | E31: 増減
B32: 売上高 | C32: ='財務諸表（入力）'!G129 -> 0 | D32: ='財務諸表（入力）'!J129 -> 0 | E32: =D32-C32 -> 0
B33: 売上原価 | C33: ='財務諸表（入力）'!G136 -> 0 | D33: ='財務諸表（入力）'!J136 -> 0 | E33: =D33-C33 -> 0
B34: 売上総利益 | C34: =C32-C33 -> 0 | D34: =D32-D33 -> 0 | E34: =D34-C34 -> 0
B35: 販売費及び一般管理費 | C35: ='財務諸表（入力）'!G156 -> 0 | D35: ='財務諸表（入力）'!J156 -> 0 | E35: =D35-C35 -> 0
B36: 営業利益 | C36: =C34-C35 -> 0 | D36: =D34-D35 -> 0 | E36: =D36-C36 -> 0
B37: 営業外収益 | C37: ='財務諸表（入力）'!G162 -> 0 | D37: ='財務諸表（入力）'!J162 -> 0 | E37: =D37-C37 -> 0
B38: 営業外費用 | C38: ='財務諸表（入力）'!G165 -> 0 | D38: ='財務諸表（入力）'!J165 -> 0 | E38: =D38-C38 -> 0
B39: 経常利益 | C39: =C36+C37-C38 -> 0 | D39: =D36+D37-D38 -> 0 | E39: =D39-C39 -> 0
B40: 特別利益 | C40: ='財務諸表（入力）'!G167 -> 0 | D40: ='財務諸表（入力）'!J167 -> 0 | E40: =D40-C40 -> 0
B41: 特別損失 | C41: ='財務諸表（入力）'!G168 -> 0 | D41: ='財務諸表（入力）'!J168 -> 0 | E41: =D41-C41 -> 0
B42: 税引前当期純利益 | C42: =C39+C40-C41 -> 0 | D42: =D39+D40-D41 -> 0 | E42: =D42-C42 -> 0
B43: 法人税、住民税及び事業税 | C43: ='財務諸表（入力）'!G170 -> 0 | D43: ='財務諸表（入力）'!J170 -> 0 | E43: =D43-C43 -> 0
B44: 当期純利益 | C44: =C42-C43 -> 0 | D44: =+D42-D43 -> 0 | E44: =D44-C44 -> 0
B46: ３．その他の入力 | E46: =J7 -> （単位：千円）
B47: 項目 | C47: =C8 -> 2021年2月1日～2022年1月31日 | D47: =D8 -> 2022年2月1日～2023年1月31日 | E47: 増減
B48: 減価償却費 | C48: ='財務諸表（入力）'!G182 -> 0 | D48: ='財務諸表（入力）'!J182 -> 0 | E48: =+D48-C48 -> 0
B49: 支払利息割引料 | C49: ='財務諸表（入力）'!G163 -> 0 | D49: ='財務諸表（入力）'!J163 -> 0 | E49: =+D49-C49 -> 0
B51: ４．株主資本等変動計算書の入力 | J51: =J7 -> （単位：千円）
B52: 項目 | C52: 株主資本 | I52: その他 | J52: 純資産合計
C53: 資本金 | D53: 資本剰余金 | E53: 利益剰余金 | G53: 自己株式 | H53: 株主資本合計
E54: 利益準備金 ××積立金 | F54: 繰越利益剰余金
B55: 前期首残高 | C55: =H22 -> 0 | D55: =H23 -> 0 | E55: ='財務諸表（入力）'!G74 -> 0 | F55: ='財務諸表（入力）'!G75 -> 0 | G55: =H25 -> 0 | H55: =SUM(C55:G55) -> 0 | I55: =H26 -> 0 | J55: =H55+I55 -> 0
B56: 当期変動額 | H56: =SUM(C56:G56) -> 0 | J56: =H56+I56 -> 0
B57: 目的積立金の積立て | F57: =E57*-1 -> 0 | H57: =SUM(C57:G57) -> 0 | J57: =H57+I57 -> 0
B58: 別途積立金の積立て | F58: =E58*-1 -> 0 | H58: =SUM(C58:G58) -> 0 | J58: =H58+I58 -> 0
B59: 剰余金の配当 | H59: =SUM(C59:G59) -> 0 | J59: =H59+I59 -> 0
B60: 役員賞与の支給（注） | H60: =SUM(C60:G60) -> 0 | J60: =H60+I60 -> 0
B61: 当期純利益 | F61: =D44 -> 0 | H61: =SUM(C61:G61) -> 0 | J61: =H61+I61 -> 0
B62: 自己株式の取得（又は処分） | G62: =G64 -> 0 | H62: =+G62 -> 0 | J62: =+H62 -> 0
B63: その他の当期変動額（純額） | H63: =SUM(C63:G63) -> 0 | I63: =I64 -> 0 | J63: =H63+I63 -> 0
B64: 当期変動額合計 | C64: =J22 -> 0 | D64: =J23 -> 0 | E64: =SUM(E57:E63) -> 0 | F64: =SUM(F57:F63) -> 0 | G64: =J25 -> 0 | H64: =SUM(C64:G64) -> 0 | I64: =J26 -> 0 | J64: =H64+I64 -> 0
B65: 当期末残高 | C65: =C55+C64 -> 0 | D65: =D55+D64 -> 0 | E65: =E55+E64 -> 0 | F65: =F55+F64 -> 0 | G65: =+I25 -> 0 | H65: =H55+H64 -> 0 | I65: =+I26 -> 0 | J65: =J55+J64 -> 0
B66: （注）会社法の施行により、従来、利益処分項目として計上されていた「役員賞与」が、発生した会計期間の費用として処理する方法に変わり、今後は原則として、 「販売費及び一般管理費」で計上されます。

Sheet CFワークシート②
B2: キャッシュ・フロー計算書のワークシート②（入力用）
B7: １．貸借対照表の入力 | J7: （単位：千円） | L7: （単位：百万円）
B8: 項目 | C8: ='財務諸表（入力）'!E4 -> 2020年2月1日～ 2021年1月31日 | D8: ='財務諸表（入力）'!G4 -> 2021年2月1日～2022年1月31日 | E8: 増減 | F8: 項目 | H8: =C8 -> 2020年2月1日～ 2021年1月31日 | I8: =D8 -> 2021年2月1日～2022年1月31日 | J8: 増減 | L8: （単位：千円）
B9: 現金及び預金 | C9: ='財務諸表（入力）'!E6 -> 0 | D9: ='財務諸表（入力）'!G6 -> 0 | E9: =D9-C9 -> 0 | F9: 支払手形 | H9: ='財務諸表（入力）'!E51 -> 0 | I9: ='財務諸表（入力）'!G51 -> 0 | J9: =I9-H9 -> 0 | L9: （単位：円）
B10: 受取手形 | C10: ='財務諸表（入力）'!E8 -> 0 | D10: ='財務諸表（入力）'!G8 -> 0 | E10: =D10-C10 -> 0 | F10: 買掛金 | H10: ='財務諸表（入力）'!E52 -> 0 | I10: ='財務諸表（入力）'!G52 -> 0 | J10: =I10-H10 -> 0
B11: 売掛金 | C11: ='財務諸表（入力）'!E9 -> 0 | D11: ='財務諸表（入力）'!G9 -> 0 | E11: =D11-C11 -> 0 | F11: 短期借入金 | H11: ='財務諸表（入力）'!E53 -> 0 | I11: ='財務諸表（入力）'!G53 -> 0 | J11: =I11-H11 -> 0
B12: 有価証券 | E12: =D12-C12 -> 0 | F12: 前受金 | J12: =I12-H12 -> 0
B13: 棚卸資産 | C13: ='財務諸表（入力）'!E16 -> 0 | D13: ='財務諸表（入力）'!G16 -> 0 | E13: =D13-C13 -> 0 | F13: 引当金 | J13: =I13-H13 -> 0
B14: 短期貸付金 | E14: =D14-C14 -> 0 | F14: その他の流動負債 | H14: ='財務諸表（入力）'!E61-CFワークシート②!H9-CFワークシート②!H10-CFワークシート②!H11-CFワークシート②!H12-CFワークシート②!H13 -> 0 | I14: ='財務諸表（入力）'!G61-CFワークシート②!I9-CFワークシート②!I10-CFワークシート②!I11-CFワークシート②!I12-CFワークシート②!I13 -> 0 | J14: =I14-H14 -> 0
B15: その他の流動資産 | C15: ='財務諸表（入力）'!E28-CFワークシート②!C9-CFワークシート②!C10-CFワークシート②!C11-CFワークシート②!C12-CFワークシート②!C13-CFワークシート②!C14-CFワークシート②!C16 -> 0 | D15: ='財務諸表（入力）'!G28-CFワークシート②!D9-CFワークシート②!D10-CFワークシート②!D11-CFワークシート②!D12-CFワークシート②!D13-CFワークシート②!D14-CFワークシート②!D16 -> 0 | E15: =D15-C15 -> 0 | F15: 流動負債合計 | H15: =SUM(H9:H14) -> 0 | I15: =SUM(I9:I14) -> 0 | J15: =I15-H15 -> 0
B16: 貸倒引当金 | C16: ='財務諸表（入力）'!E25 -> 0 | D16: ='財務諸表（入力）'!G25 -> 0 | E16: =D16-C16 -> 0 | F16: 長期借入金 | H16: ='財務諸表（入力）'!E62 -> 0 | I16: ='財務諸表（入力）'!G62 -> 0 | J16: =I16-H16 -> 0
B17: 流動資産合計 | C17: =SUM(C9:C16) -> 0 | D17: =SUM(D9:D16) -> 0 | E17: =D17-C17 -> 0 | F17: 社債 | H17: ='財務諸表（入力）'!E63 -> 0 | I17: ='財務諸表（入力）'!G63 -> 0 | J17: =I17-H17 -> 0
B18: 土地 | C18: ='財務諸表（入力）'!E34 -> 0 | D18: ='財務諸表（入力）'!G34 -> 0 | E18: =D18-C18 -> 0 | F18: 引当金 | J18: =I18-H18 -> 0
B19: 減価償却資産 | C19: ='財務諸表（入力）'!E37-'財務諸表（入力）'!E34-'財務諸表（入力）'!E35 -> 0 | D19: ='財務諸表（入力）'!G37-'財務諸表（入力）'!G34-'財務諸表（入力）'!G35 -> 0 | E19: =D19-C19 -> 0 | F19: その他の固定負債 | H19: ='財務諸表（入力）'!E69-CFワークシート②!H16-CFワークシート②!H17-CFワークシート②!H18 -> 0 | I19: ='財務諸表（入力）'!G69-CFワークシート②!I16-CFワークシート②!I17-CFワークシート②!I18 -> 0 | J19: =I19-H19 -> 0
B20: 建設仮勘定 | C20: ='財務諸表（入力）'!E35 -> 0 | D20: ='財務諸表（入力）'!G35 -> 0 | E20: =D20-C20 -> 0 | F20: 固定負債合計 | H20: =SUM(H16:H19) -> 0 | I20: =SUM(I16:I19) -> 0 | J20: =I20-H20 -> 0
B21: 無形固定資産 | C21: ='財務諸表（入力）'!E38 -> 0 | D21: ='財務諸表（入力）'!G38 -> 0 | E21: =D21-C21 -> 0 | F21: 負債合計 | H21: =H15+H20 -> 0 | I21: =I15+I20 -> 0 | J21: =I21-H21 -> 0
B22: 投資有価証券.子会社株式.出資金等 | E22: =D22-C22 -> 0 | F22: 資本金 | H22: ='財務諸表（入力）'!E71 -> 0 | I22: ='財務諸表（入力）'!G71 -> 0 | J22: =I22-H22 -> 0
B23: 長期貸付金 | E23: =D23-C23 -> 0 | F23: 資本剰余金 | H23: ='財務諸表（入力）'!E72 -> 0 | I23: ='財務諸表（入力）'!G72 -> 0 | J23: =I23-H23 -> 0
B24: その他の固定資産 | C24: ='財務諸表（入力）'!E47-CFワークシート②!C22-CFワークシート②!C23-CFワークシート②!C25 -> 0 | D24: ='財務諸表（入力）'!G47-CFワークシート②!D25-CFワークシート②!D22-CFワークシート②!D23 -> 0 | E24: =D24-C24 -> 0 | F24: 利益剰余金 | H24: ='財務諸表（入力）'!E73 -> 0 | I24: ='財務諸表（入力）'!G73 -> 0 | J24: =I24-H24 -> 0
B25: 貸倒引当金 | C25: ='財務諸表（入力）'!E45 -> 0 | D25: ='財務諸表（入力）'!G45 -> 0 | E25: =D25-C25 -> 0 | F25: 自己株式 | H25: ='財務諸表（入力）'!E77 -> 0 | I25: ='財務諸表（入力）'!G77 -> 0 | J25: =I25-H25 -> 0
B26: 固定資産合計 | C26: =SUM(C18:C25) -> 0 | D26: =SUM(D18:D25) -> 0 | E26: =D26-C26 -> 0 | F26: その他 | J26: =I26-H26 -> 0
B27: 繰延資産合計 | C27: ='財務諸表（入力）'!E48 -> 0 | D27: ='財務諸表（入力）'!G48 -> 0 | E27: =D27-C27 -> 0 | F27: 純資産合計 | H27: =SUM(H22:H26) -> 0 | I27: =SUM(I22:I26) -> 0 | J27: =I27-H27 -> 0
B28: 資産合計 | C28: =C17+C26+C27 -> 0 | D28: =D17+D26+D27 -> 0 | E28: =D28-C28 -> 0 | F28: 負債･純資産合計 | H28: =H21+H27 -> 0 | I28: =I21+I27 -> 0 | J28: =I28-H28 -> 0
B29: （注）有利子負債は、短期借入金又は長期借入金に含める。
B30: ２．損益計算書の入力 | E30: =J7 -> （単位：千円）
B31: 項目 | C31: =C8 -> 2020年2月1日～ 2021年1月31日 | D31: =D8 -> 2021年2月1日～2022年1月31日 | E31: 増減
B32: 売上高 | C32: ='財務諸表（入力）'!E129 -> 0 | D32: ='財務諸表（入力）'!G129 -> 0 | E32: =D32-C32 -> 0
B33: 売上原価 | C33: ='財務諸表（入力）'!E136 -> 0 | D33: ='財務諸表（入力）'!G136 -> 0 | E33: =D33-C33 -> 0
B34: 売上総利益 | C34: =C32-C33 -> 0 | D34: =D32-D33 -> 0 | E34: =D34-C34 -> 0
B35: 販売費及び一般管理費 | C35: ='財務諸表（入力）'!E156 -> 0 | D35: ='財務諸表（入力）'!G156 -> 0 | E35: =D35-C35 -> 0
B36: 営業利益 | C36: =C34-C35 -> 0 | D36: =D34-D35 -> 0 | E36: =D36-C36 -> 0
B37: 営業外収益 | C37: ='財務諸表（入力）'!E162 -> 0 | D37: ='財務諸表（入力）'!G162 -> 0 | E37: =D37-C37 -> 0
B38: 営業外費用 | C38: ='財務諸表（入力）'!E165 -> 0 | D38: ='財務諸表（入力）'!G165 -> 0 | E38: =D38-C38 -> 0
B39: 経常利益 | C39: =C36+C37-C38 -> 0 | D39: =D36+D37-D38 -> 0 | E39: =D39-C39 -> 0
B40: 特別利益 | C40: ='財務諸表（入力）'!E167 -> 0 | D40: ='財務諸表（入力）'!G167 -> 0 | E40: =D40-C40 -> 0
B41: 特別損失 | C41: ='財務諸表（入力）'!E168 -> 0 | D41: ='財務諸表（入力）'!G168 -> 0 | E41: =D41-C41 -> 0
B42: 税引前当期純利益 | C42: =C39+C40-C41 -> 0 | D42: =D39+D40-D41 -> 0 | E42: =D42-C42 -> 0
B43: 法人税、住民税及び事業税 | C43: ='財務諸表（入力）'!E170 -> 0 | D43: ='財務諸表（入力）'!G170 -> 0 | E43: =D43-C43 -> 0
B44: 当期純利益 | C44: =C42-C43 -> 0 | D44: =+D42-D43 -> 0 | E44: =D44-C44 -> 0
B46: ３．その他の入力 | E46: =J7 -> （単位：千円）
B47: 項目 | C47: =C8 -> 2020年2月1日～ 2021年1月31日 | D47: =D8 -> 2021年2月1日～2022年1月31日 | E47: 増減
B48: 減価償却費 | C48: ='財務諸表（入力）'!E182 -> 0 | D48: ='財務諸表（入力）'!G182 -> 0 | E48: =+D48-C48 -> 0
B49: 支払利息割引料 | C49: ='財務諸表（入力）'!E163 -> 0 | D49: ='財務諸表（入力）'!G163 -> 0 | E49: =+D49-C49 -> 0
B51: ４．株主資本等変動計算書の入力 | J51: =J7 -> （単位：千円）
B52: 項目 | C52: 株主資本 | I52: その他 | J52: 純資産合計
C53: 資本金 | D53: 資本剰余金 | E53: 利益剰余金 | G53: 自己株式 | H53: 株主資本合計
E54: 利益準備金 ××積立金 | F54: 繰越利益剰余金
B55: 前期首残高 | C55: =H22 -> 0 | D55: =H23 -> 0 | E55: ='財務諸表（入力）'!E74 -> 0 | F55: ='財務諸表（入力）'!E75 -> 0 | G55: =H25 -> 0 | H55: =SUM(C55:G55) -> 0 | I55: =H26 -> 0 | J55: =H55+I55 -> 0
B56: 当期変動額 | H56: =SUM(C56:G56) -> 0 | J56: =H56+I56 -> 0
B57: 目的積立金の積立て | F57: =E57*-1 -> 0 | H57: =SUM(C57:G57) -> 0 | J57: =H57+I57 -> 0
B58: 別途積立金の積立て | F58: =E58*-1 -> 0 | H58: =SUM(C58:G58) -> 0 | J58: =H58+I58 -> 0
B59: 剰余金の配当 | H59: =SUM(C59:G59) -> 0 | J59: =H59+I59 -> 0
B60: 役員賞与の支給（注） | H60: =SUM(C60:G60) -> 0 | J60: =H60+I60 -> 0
B61: 当期純利益 | F61: =D44 -> 0 | H61: =SUM(C61:G61) -> 0 | J61: =H61+I61 -> 0
B62: 自己株式の取得（又は処分） | G62: =G64 -> 0 | H62: =+G62 -> 0 | J62: =+H62 -> 0
B63: その他の当期変動額（純額） | H63: =SUM(C63:G63) -> 0 | I63: =I64 -> 0 | J63: =H63+I63 -> 0
B64: 当期変動額合計 | C64: =J22 -> 0 | D64: =J23 -> 0 | E64: =SUM(E57:E63) -> 0 | F64: =SUM(F57:F63) -> 0 | G64: =J25 -> 0 | H64: =SUM(C64:G64) -> 0 | I64: =J26 -> 0 | J64: =H64+I64 -> 0
B65: 当期末残高 | C65: =C55+C64 -> 0 | D65: =D55+D64 -> 0 | E65: =E55+E64 -> 0 | F65: =F55+F64 -> 0 | G65: =+I25 -> 0 | H65: =H55+H64 -> 0 | I65: =+I26 -> 0 | J65: =J55+J64 -> 0
B66: （注）会社法の施行により、従来、利益処分項目として計上されていた「役員賞与」が、発生した会計期間の費用として処理する方法に変わり、今後は原則として、 「販売費及び一般管理費」で計上されます。

Sheet 経営指標調査表
L1: 経営指標調査表 | AH1: 条件付き書式設定 | AN1: ✔
A4: 企業名 | Q4: コード
A5: 地域本部 | D5: 関東 | I5: シニアAD | Q5: 管理者 | Y5: 担当職員
J7: ='財務諸表（入力）'!E5 -> 前々期 | L7: 期 | O7: ='財務諸表（入力）'!G5 -> 前期 | Q7: 期 | T7: ='財務諸表（入力）'!J5 -> 今期 | V7: 期 | X7: 中間調査 | AC7: 終了調査
A8: 分類 | B8: 指標名 | G8: 単位 | K8: 年 | M8: 月期 | P8: 年 | R8: 月期 | U8: 年 | W8: 月期 | Z8: 年 | AB8: 月期 | AE8: 年 | AG8: 月期
A9: 経営基本指標の変化 | B9: 資本金 | G9: 千円 | I9: ='財務諸表（入力）'!E71 -> 0 | N9: ='財務諸表（入力）'!G71 -> 0 | S9: ='財務諸表（入力）'!J71 -> 0
B10: 従業員数 | G10: 人 | I10: ='財務諸表（入力）'!E179 -> 0 | N10: ='財務諸表（入力）'!G179 -> 0 | S10: ='財務諸表（入力）'!J179 -> 0
B11: 売上高 | G11: 千円 | I11: ='財務諸表（入力）'!E129 -> 0 | N11: ='財務諸表（入力）'!G129 -> 0 | S11: ='財務諸表（入力）'!J129 -> 0
B12: 売上総利益 | G12: 千円 | I12: ='財務諸表（入力）'!E137 -> 0 | N12: ='財務諸表（入力）'!G137 -> 0 | S12: ='財務諸表（入力）'!J137 -> 0
B13: 営業利益 | G13: 千円 | I13: ='財務諸表（入力）'!E157 -> 0 | N13: ='財務諸表（入力）'!G157 -> 0 | S13: ='財務諸表（入力）'!J157 -> 0
B14: 経常利益 | G14: 千円 | I14: ='財務諸表（入力）'!E166 -> 0 | N14: ='財務諸表（入力）'!G166 -> 0 | S14: ='財務諸表（入力）'!J166 -> 0
B15: 税引後利益 | G15: 千円 | I15: ='財務諸表（入力）'!E171 -> 0 | N15: ='財務諸表（入力）'!G171 -> 0 | S15: ='財務諸表（入力）'!J171 -> 0
B16: 減価償却費 | G16: 千円 | I16: ='財務諸表（入力）'!E182 -> 0 | N16: ='財務諸表（入力）'!G182 -> 0 | S16: ='財務諸表（入力）'!J182 -> 0
B17: 現預金残高 | G17: 千円 | I17: ='財務諸表（入力）'!E6 -> 0 | N17: ='財務諸表（入力）'!G6 -> 0 | S17: ='財務諸表（入力）'!J6 -> 0
B18: 純資産 | G18: 千円 | I18: ='財務諸表（入力）'!E79 -> 0 | N18: ='財務諸表（入力）'!G79 -> 0 | S18: ='財務諸表（入力）'!J79 -> 0
B19: 総資産 | G19: 千円 | I19: ='財務諸表（入力）'!E80 -> 0 | N19: ='財務諸表（入力）'!G80 -> 0 | S19: ='財務諸表（入力）'!J80 -> 0
B20: 借入金残高 | G20: 千円 | I20: ='財務諸表（入力）'!E184 -> 0 | N20: ='財務諸表（入力）'!G184 -> 0 | S20: ='財務諸表（入力）'!J184 -> 0
A21: 経営指標分析 | B21: 売上高粗利益率 | G21: ％ | I21: =IF(OR(I11="",I12=""),"",I12/I11*100) -> #DIV/0! | N21: =IF(OR(N11="",N12=""),"",N12/N11*100) -> #DIV/0! | S21: =IF(OR(S11="",S12=""),"",S12/S11*100) -> #DIV/0! | X21: =IF(OR(X11="",X12=""),"",X12/X11*100) | AC21: =IF(OR(AC11="",AC12=""),"",AC12/AC11*100)
B22: 売上高営業利益率 | G22: ％ | I22: =IF(OR(I11="",I13="",),"",I13/I11*100) -> #DIV/0! | N22: =IF(OR(N11="",N13="",),"",N13/N11*100) -> #DIV/0! | S22: =IF(OR(S11="",S13="",),"",S13/S11*100) -> #DIV/0! | X22: =IF(OR(X11="",X13="",),"",X13/X11*100) | AC22: =IF(OR(AC11="",AC13="",),"",AC13/AC11*100)
B23: 売上高経常利益率 | G23: ％ | I23: =IF(OR(I11="",I14=""),"",I14/I11*100) -> #DIV/0! | N23: =IF(OR(N11="",N14=""),"",N14/N11*100) -> #DIV/0! | S23: =IF(OR(S11="",S14=""),"",S14/S11*100) -> #DIV/0! | X23: =IF(OR(X11="",X14=""),"",X14/X11*100) | AC23: =IF(OR(AC11="",AC14=""),"",AC14/AC11*100)
B24: 自己資本比率 | G24: ％ | I24: =IF(OR(I18="",I19=""),"",I18/I19*100) -> #DIV/0! | N24: =IF(OR(N18="",N19=""),"",N18/N19*100) -> #DIV/0! | S24: =IF(OR(S18="",S19=""),"",S18/S19*100) -> #DIV/0! | X24: =IF(OR(X18="",X19=""),"",X18/X19*100) | AC24: =IF(OR(AC18="",AC19=""),"",AC18/AC19*100)
B25: 債務償還年数 | G25: 年 | I25: =IF(OR(I15="",I16="",I20=""),"",I20/(I15+I16)) -> #DIV/0! | N25: =IF(OR(N15="",N16="",N20=""),"",N20/(N15+N16)) -> #DIV/0! | S25: =IF(OR(S15="",S16="",S20=""),"",S20/(S15+S16)) -> #DIV/0! | X25: =IF(OR(X15="",X16="",X20=""),"",X20/(X15+X16)) | AC25: =IF(OR(AC15="",AC16="",AC20=""),"",AC20/(AC15+AC16))
B26: 総資本回転率 | G26: 回 | I26: =IF(OR(I11="",I19=""),"",I11/I19) -> #DIV/0! | N26: =IF(OR(N11="",N19=""),"",N11/N19) -> #DIV/0! | S26: =IF(OR(S11="",S19=""),"",S11/S19) -> #DIV/0! | X26: =IF(OR(X11="",X19=""),"",X11/X19) | AC26: =IF(OR(AC11="",AC19=""),"",AC11/AC19)
B27: 総資本経常利益率 | G27: ％ | I27: =IF(OR(I14="",I19=""),"",I14/I19*100) -> #DIV/0! | N27: =IF(OR(N14="",N19=""),"",N14/N19*100) -> #DIV/0! | S27: =IF(OR(S14="",S19=""),"",S14/S19*100) -> #DIV/0! | X27: =IF(OR(X14="",X19=""),"",X14/X19*100) | AC27: =IF(OR(AC14="",AC19=""),"",AC14/AC19*100)
A28: 独自設定指標
A36: 備考・その他
